Workbook
Name ABC: #REF!
Name Asher: #REF!
Name def: #REF!
Name RowTitleRegion1..D5: #REF!
Name RowTitleRegion2..G3: #REF!
Name RowTitleRegion4..G23: #REF!
Name RowTitleRegion5..H24: #REF!

Sheet Billability Summary 
B2: Average Billiability by Month
Q3: Mar'26
B4: Entity/Practice | C4: Active Resources | D4: 45748 | E4: 45778 | F4: 45809 | G4: 45839 | H4: 45870 | I4: 45901 | J4: 45931 | K4: 45962 | L4: 45992 | M4: 46023 | N4: 46054 | O4: 46082 | Q4: Avg Billability | R4: Avg Availability | T4: Non Billable cost from April'25 to March '26 | V4: Non Billable cost from Jan'26 to March '26
B5: NGL | C5: =COUNTIF('Availability Report - NGL'!$D:$D,"Active") | D5: =1-AVERAGEIF('Availability Report - NGL'!$D:$D,"Active",'Availability Report - NGL'!I:I) | E5: =1-AVERAGEIF('Availability Report - NGL'!$D:$D,"Active",'Availability Report - NGL'!J:J) | F5: =1-AVERAGEIF('Availability Report - NGL'!$D:$D,"Active",'Availability Report - NGL'!K:K) | G5: =1-AVERAGEIF('Availability Report - NGL'!$D:$D,"Active",'Availability Report - NGL'!L:L) | H5: =1-AVERAGEIF('Availability Report - NGL'!$D:$D,"Active",'Availability Report - NGL'!M:M) | I5: =1-AVERAGEIF('Availability Report - NGL'!$D:$D,"Active",'Availability Report - NGL'!N:N) | J5: =1-AVERAGEIF('Availability Report - NGL'!$D:$D,"Active",'Availability Report - NGL'!O:O) | K5: =1-AVERAGEIF('Availability Report - NGL'!$D:$D,"Active",'Availability Report - NGL'!P:P) | L5: =1-AVERAGEIF('Availability Report - NGL'!$D:$D,"Active",'Availability Report - NGL'!Q:Q) | M5: =1-AVERAGEIF('Availability Report - NGL'!$D:$D,"Active",'Availability Report - NGL'!R:R) | N5: =1-AVERAGEIF('Availability Report - NGL'!$D:$D,"Active",'Availability Report - NGL'!S:S) | O5: =1-AVERAGEIF('Availability Report - NGL'!$D:$D,"Active",'Availability Report - NGL'!T:T) | Q5: =AVERAGE(N5:O5) | R5: =1-Q5
B6: nxzen - India | C6: =COUNTIF('Availability Report - YTPL'!$D$5:$D$191,"Active")-2 | D6: =1-AVERAGEIF('Availability Report - YTPL'!$D:$D,"Active",'Availability Report - YTPL'!I:I) | E6: =1-AVERAGEIF('Availability Report - YTPL'!$D:$D,"Active",'Availability Report - YTPL'!J:J) | F6: =1-AVERAGEIF('Availability Report - YTPL'!$D:$D,"Active",'Availability Report - YTPL'!K:K) | G6: =1-AVERAGEIF('Availability Report - YTPL'!$D:$D,"Active",'Availability Report - YTPL'!L:L) | H6: =1-AVERAGEIF('Availability Report - YTPL'!$D:$D,"Active",'Availability Report - YTPL'!M:M) | I6: =1-AVERAGEIF('Availability Report - YTPL'!$D:$D,"Active",'Availability Report - YTPL'!N:N) | J6: =1-AVERAGEIF('Availability Report - YTPL'!$D:$D,"Active",'Availability Report - YTPL'!O:O) | K6: =1-AVERAGEIF('Availability Report - YTPL'!$D:$D,"Active",'Availability Report - YTPL'!P:P) | L6: =1-AVERAGEIF('Availability Report - YTPL'!$D:$D,"Active",'Availability Report - YTPL'!Q:Q) | M6: =1-AVERAGEIF('Availability Report - YTPL'!$D:$D,"Active",'Availability Report - YTPL'!R:R) | N6: =1-AVERAGEIF('Availability Report - YTPL'!$D:$D,"Active",'Availability Report - YTPL'!S:S) | O6: =1-AVERAGEIF('Availability Report - YTPL'!$D:$D,"Active",'Availability Report - YTPL'!T:T) | Q6: =AVERAGE(N6:O6) | R6: =1-Q6 | T6: =+SUMIF('Availability Report - YTPL'!$D:$D,"Active",'Availability Report - YTPL'!#REF!) | V6: =+SUMIF('Availability Report - YTPL'!$D:$D,"Active",'Availability Report - YTPL'!#REF!)
B7: D&E - INDIA | C7: =COUNTIFS('Availability Report - YTPL'!D:D,"Active",'Availability Report - YTPL'!E:E,"D&E")-2 | D7: =1-AVERAGEIF('Availability Report - YTPL'!$D:$D,"Active",'Availability Report - YTPL'!I:I) | E7: =1-AVERAGEIF('Availability Report - YTPL'!$D:$D,"Active",'Availability Report - YTPL'!J:J) | F7: =1-AVERAGEIF('Availability Report - YTPL'!$D:$D,"Active",'Availability Report - YTPL'!K:K) | G7: =1-AVERAGEIF('Availability Report - YTPL'!$D:$D,"Active",'Availability Report - YTPL'!L:L) | H7: =1-AVERAGEIF('Availability Report - YTPL'!$D:$D,"Active",'Availability Report - YTPL'!M:M) | I7: =1-AVERAGEIF('Availability Report - YTPL'!$D:$D,"Active",'Availability Report - YTPL'!N:N) | J7: =1-AVERAGEIF('Availability Report - YTPL'!$D:$D,"Active",'Availability Report - YTPL'!O:O) | K7: =1-AVERAGEIF('Availability Report - YTPL'!$D:$D,"Active",'Availability Report - YTPL'!P:P) | L7: =1-AVERAGEIF('Availability Report - YTPL'!$D:$D,"Active",'Availability Report - YTPL'!Q:Q) | M7: =1-AVERAGEIF('Availability Report - YTPL'!$D:$D,"Active",'Availability Report - YTPL'!R:R) | N7: =1-AVERAGEIF('Availability Report - YTPL'!$D:$D,"Active",'Availability Report - YTPL'!S:S) | O7: =1-AVERAGEIF('Availability Report - YTPL'!$D:$D,"Active",'Availability Report - YTPL'!T:T) | Q7: =AVERAGE(N7:O7) | R7: =1-Q7 | T7: =SUMIFS('Availability Report - YTPL'!#REF!,'Availability Report - YTPL'!$E:$E,"D&E",'Availability Report - YTPL'!D:D,"Active") | V7: =SUMIFS('Availability Report - YTPL'!#REF!,'Availability Report - YTPL'!$E:$E,"D&E",'Availability Report - YTPL'!D:D,"Active")
Q9: Mar'26
B10: Function | C10: Active Resources | D10: 45748 | E10: 45778 | F10: 45809 | G10: 45839 | H10: 45870 | I10: 45901 | J10: 45931 | K10: 45962 | L10: 45992 | M10: 46023 | N10: 46054 | O10: 46082 | Q10: Avg Billability | R10: Avg Availability | T10: Non Billable cost from April'25 to March '26 | V10: Non Billable cost from Jan'26 to March '26
B11: Digital & Engineering Services | C11: =COUNTIFS('Availability Report - NGL'!$F:$F,'Billability Summary '!$B11,'Availability Report - NGL'!$D:$D,"Active") | D11: =1-AVERAGEIFS('Availability Report - NGL'!I:I,'Availability Report - NGL'!$D:$D,"Active",'Availability Report - NGL'!$F:$F,'Billability Summary '!$B11) | E11: =1-AVERAGEIFS('Availability Report - NGL'!J:J,'Availability Report - NGL'!$D:$D,"Active",'Availability Report - NGL'!$F:$F,'Billability Summary '!$B11) | F11: =1-AVERAGEIFS('Availability Report - NGL'!K:K,'Availability Report - NGL'!$D:$D,"Active",'Availability Report - NGL'!$F:$F,'Billability Summary '!$B11) | G11: =1-AVERAGEIFS('Availability Report - NGL'!L:L,'Availability Report - NGL'!$D:$D,"Active",'Availability Report - NGL'!$F:$F,'Billability Summary '!$B11) | H11: =1-AVERAGEIFS('Availability Report - NGL'!M:M,'Availability Report - NGL'!$D:$D,"Active",'Availability Report - NGL'!$F:$F,'Billability Summary '!$B11) | I11: =1-AVERAGEIFS('Availability Report - NGL'!N:N,'Availability Report - NGL'!$D:$D,"Active",'Availability Report - NGL'!$F:$F,'Billability Summary '!$B11) | J11: =1-AVERAGEIFS('Availability Report - NGL'!O:O,'Availability Report - NGL'!$D:$D,"Active",'Availability Report - NGL'!$F:$F,'Billability Summary '!$B11) | K11: =1-AVERAGEIFS('Availability Report - NGL'!P:P,'Availability Report - NGL'!$D:$D,"Active",'Availability Report - NGL'!$F:$F,'Billability Summary '!$B11) | L11: =1-AVERAGEIFS('Availability Report - NGL'!Q:Q,'Availability Report - NGL'!$D:$D,"Active",'Availability Report - NGL'!$F:$F,'Billability Summary '!$B11) | M11: =1-AVERAGEIFS('Availability Report - NGL'!R:R,'Availability Report - NGL'!$D:$D,"Active",'Availability Report - NGL'!$F:$F,'Billability Summary '!$B11) | N11: =1-AVERAGEIFS('Availability Report - NGL'!S:S,'Availability Report - NGL'!$D:$D,"Active",'Availability Report - NGL'!$F:$F,'Billability Summary '!$B11) | O11: =1-AVERAGEIFS('Availability Report - NGL'!T:T,'Availability Report - NGL'!$D:$D,"Active",'Availability Report - NGL'!$F:$F,'Billability Summary '!$B11) | Q11: =AVERAGE(N11:O11) | R11: =1-Q11 | T11: =+SUMIFS('Availability Report - NGL'!#REF!,'Availability Report - NGL'!$F:$F,'Billability Summary '!B11,'Availability Report - NGL'!$D:$D,"Active") | V11: =+SUMIFS('Availability Report - NGL'!#REF!,'Availability Report - NGL'!$F:$F,'Billability Summary '!B11,'Availability Report - NGL'!$D:$D,"Active")
B12: Growth | C12: =COUNTIFS('Availability Report - NGL'!$F:$F,'Billability Summary '!$B12,'Availability Report - NGL'!$D:$D,"Active") | D12: =1-AVERAGEIFS('Availability Report - NGL'!I:I,'Availability Report - NGL'!$D:$D,"Active",'Availability Report - NGL'!$F:$F,'Billability Summary '!$B12) | E12: =1-AVERAGEIFS('Availability Report - NGL'!J:J,'Availability Report - NGL'!$D:$D,"Active",'Availability Report - NGL'!$F:$F,'Billability Summary '!$B12) | F12: =1-AVERAGEIFS('Availability Report - NGL'!K:K,'Availability Report - NGL'!$D:$D,"Active",'Availability Report - NGL'!$F:$F,'Billability Summary '!$B12) | G12: =1-AVERAGEIFS('Availability Report - NGL'!L:L,'Availability Report - NGL'!$D:$D,"Active",'Availability Report - NGL'!$F:$F,'Billability Summary '!$B12) | H12: =1-AVERAGEIFS('Availability Report - NGL'!M:M,'Availability Report - NGL'!$D:$D,"Active",'Availability Report - NGL'!$F:$F,'Billability Summary '!$B12) | I12: =1-AVERAGEIFS('Availability Report - NGL'!N:N,'Availability Report - NGL'!$D:$D,"Active",'Availability Report - NGL'!$F:$F,'Billability Summary '!$B12) | J12: =1-AVERAGEIFS('Availability Report - NGL'!O:O,'Availability Report - NGL'!$D:$D,"Active",'Availability Report - NGL'!$F:$F,'Billability Summary '!$B12) | K12: =1-AVERAGEIFS('Availability Report - NGL'!P:P,'Availability Report - NGL'!$D:$D,"Active",'Availability Report - NGL'!$F:$F,'Billability Summary '!$B12) | L12: =1-AVERAGEIFS('Availability Report - NGL'!Q:Q,'Availability Report - NGL'!$D:$D,"Active",'Availability Report - NGL'!$F:$F,'Billability Summary '!$B12) | M12: =1-AVERAGEIFS('Availability Report - NGL'!R:R,'Availability Report - NGL'!$D:$D,"Active",'Availability Report - NGL'!$F:$F,'Billability Summary '!$B12) | N12: =1-AVERAGEIFS('Availability Report - NGL'!S:S,'Availability Report - NGL'!$D:$D,"Active",'Availability Report - NGL'!$F:$F,'Billability Summary '!$B12) | O12: =1-AVERAGEIFS('Availability Report - NGL'!T:T,'Availability Report - NGL'!$D:$D,"Active",'Availability Report - NGL'!$F:$F,'Billability Summary '!$B12) | Q12: =AVERAGE(N12:O12) | R12: =1-Q12
B13: GCC | C13: =COUNTIFS('Availability Report - NGL'!$F:$F,'Billability Summary '!$B13,'Availability Report - NGL'!$D:$D,"Active") | D13: =1-AVERAGEIFS('Availability Report - NGL'!I:I,'Availability Report - NGL'!$D:$D,"Active",'Availability Report - NGL'!$F:$F,'Billability Summary '!$B13) | E13: =1-AVERAGEIFS('Availability Report - NGL'!J:J,'Availability Report - NGL'!$D:$D,"Active",'Availability Report - NGL'!$F:$F,'Billability Summary '!$B13) | F13: =1-AVERAGEIFS('Availability Report - NGL'!K:K,'Availability Report - NGL'!$D:$D,"Active",'Availability Report - NGL'!$F:$F,'Billability Summary '!$B13) | G13: =1-AVERAGEIFS('Availability Report - NGL'!L:L,'Availability Report - NGL'!$D:$D,"Active",'Availability Report - NGL'!$F:$F,'Billability Summary '!$B13) | H13: =1-AVERAGEIFS('Availability Report - NGL'!M:M,'Availability Report - NGL'!$D:$D,"Active",'Availability Report - NGL'!$F:$F,'Billability Summary '!$B13) | I13: =1-AVERAGEIFS('Availability Report - NGL'!N:N,'Availability Report - NGL'!$D:$D,"Active",'Availability Report - NGL'!$F:$F,'Billability Summary '!$B13) | J13: =1-AVERAGEIFS('Availability Report - NGL'!O:O,'Availability Report - NGL'!$D:$D,"Active",'Availability Report - NGL'!$F:$F,'Billability Summary '!$B13) | K13: =1-AVERAGEIFS('Availability Report - NGL'!P:P,'Availability Report - NGL'!$D:$D,"Active",'Availability Report - NGL'!$F:$F,'Billability Summary '!$B13) | L13: =1-AVERAGEIFS('Availability Report - NGL'!Q:Q,'Availability Report - NGL'!$D:$D,"Active",'Availability Report - NGL'!$F:$F,'Billability Summary '!$B13) | M13: =1-AVERAGEIFS('Availability Report - NGL'!R:R,'Availability Report - NGL'!$D:$D,"Active",'Availability Report - NGL'!$F:$F,'Billability Summary '!$B13) | N13: =1-AVERAGEIFS('Availability Report - NGL'!S:S,'Availability Report - NGL'!$D:$D,"Active",'Availability Report - NGL'!$F:$F,'Billability Summary '!$B13) | O13: =1-AVERAGEIFS('Availability Report - NGL'!T:T,'Availability Report - NGL'!$D:$D,"Active",'Availability Report - NGL'!$F:$F,'Billability Summary '!$B13) | Q13: =AVERAGE(N13:O13) | R13: =1-Q13
B14: Strategic Delivery | C14: =COUNTIFS('Availability Report - NGL'!$F:$F,'Billability Summary '!$B14,'Availability Report - NGL'!$D:$D,"Active") | D14: =1-AVERAGEIFS('Availability Report - NGL'!I:I,'Availability Report - NGL'!$D:$D,"Active",'Availability Report - NGL'!$F:$F,'Billability Summary '!$B14) | E14: =1-AVERAGEIFS('Availability Report - NGL'!J:J,'Availability Report - NGL'!$D:$D,"Active",'Availability Report - NGL'!$F:$F,'Billability Summary '!$B14) | F14: =1-AVERAGEIFS('Availability Report - NGL'!K:K,'Availability Report - NGL'!$D:$D,"Active",'Availability Report - NGL'!$F:$F,'Billability Summary '!$B14) | G14: =1-AVERAGEIFS('Availability Report - NGL'!L:L,'Availability Report - NGL'!$D:$D,"Active",'Availability Report - NGL'!$F:$F,'Billability Summary '!$B14) | H14: =1-AVERAGEIFS('Availability Report - NGL'!M:M,'Availability Report - NGL'!$D:$D,"Active",'Availability Report - NGL'!$F:$F,'Billability Summary '!$B14) | I14: =1-AVERAGEIFS('Availability Report - NGL'!N:N,'Availability Report - NGL'!$D:$D,"Active",'Availability Report - NGL'!$F:$F,'Billability Summary '!$B14) | J14: =1-AVERAGEIFS('Availability Report - NGL'!O:O,'Availability Report - NGL'!$D:$D,"Active",'Availability Report - NGL'!$F:$F,'Billability Summary '!$B14) | K14: =1-AVERAGEIFS('Availability Report - NGL'!P:P,'Availability Report - NGL'!$D:$D,"Active",'Availability Report - NGL'!$F:$F,'Billability Summary '!$B14) | L14: =1-AVERAGEIFS('Availability Report - NGL'!Q:Q,'Availability Report - NGL'!$D:$D,"Active",'Availability Report - NGL'!$F:$F,'Billability Summary '!$B14) | M14: =1-AVERAGEIFS('Availability Report - NGL'!R:R,'Availability Report - NGL'!$D:$D,"Active",'Availability Report - NGL'!$F:$F,'Billability Summary '!$B14) | N14: =1-AVERAGEIFS('Availability Report - NGL'!S:S,'Availability Report - NGL'!$D:$D,"Active",'Availability Report - NGL'!$F:$F,'Billability Summary '!$B14) | O14: =1-AVERAGEIFS('Availability Report - NGL'!T:T,'Availability Report - NGL'!$D:$D,"Active",'Availability Report - NGL'!$F:$F,'Billability Summary '!$B14) | Q14: =AVERAGE(N14:O14) | R14: =1-Q14 | T14: =+SUMIFS('Availability Report - NGL'!#REF!,'Availability Report - NGL'!$F:$F,'Billability Summary '!B14,'Availability Report - NGL'!$D:$D,"Active") | V14: =+SUMIFS('Availability Report - NGL'!#REF!,'Availability Report - NGL'!$F:$F,'Billability Summary '!B14,'Availability Report - NGL'!$D:$D,"Active")
C15: =SUM(C11:C14) | T15: =SUM(T11:T14) | V15: =SUM(V11:V14)
Q16: Mar'26
B17: Practice | C17: Active Resources | D17: 45748 | E17: 45778 | F17: 45809 | G17: 45839 | H17: 45870 | I17: 45901 | J17: 45931 | K17: 45962 | L17: 45992 | M17: 46023 | N17: 46054 | O17: 46082 | Q17: Avg Billability | R17: Avg Availability | T17: Non Billable cost from April'25 to March '26 | V17: Non Billable cost from Jan'26 to March '26
B18: OT | C18: =COUNTIFS('Availability Report - NGL'!$G:$G,'Billability Summary '!$B18,'Availability Report - NGL'!$D:$D,"Active") | D18: =1-AVERAGEIFS('Availability Report - NGL'!I:I,'Availability Report - NGL'!$G:$G,'Billability Summary '!$B18,'Availability Report - NGL'!$D:$D,"Active") | E18: =1-AVERAGEIFS('Availability Report - NGL'!J:J,'Availability Report - NGL'!$G:$G,'Billability Summary '!$B18,'Availability Report - NGL'!$D:$D,"Active") | F18: =1-AVERAGEIFS('Availability Report - NGL'!K:K,'Availability Report - NGL'!$G:$G,'Billability Summary '!$B18,'Availability Report - NGL'!$D:$D,"Active") | G18: =1-AVERAGEIFS('Availability Report - NGL'!L:L,'Availability Report - NGL'!$G:$G,'Billability Summary '!$B18,'Availability Report - NGL'!$D:$D,"Active") | H18: =1-AVERAGEIFS('Availability Report - NGL'!M:M,'Availability Report - NGL'!$G:$G,'Billability Summary '!$B18,'Availability Report - NGL'!$D:$D,"Active") | I18: =1-AVERAGEIFS('Availability Report - NGL'!N:N,'Availability Report - NGL'!$G:$G,'Billability Summary '!$B18,'Availability Report - NGL'!$D:$D,"Active") | J18: =1-AVERAGEIFS('Availability Report - NGL'!O:O,'Availability Report - NGL'!$G:$G,'Billability Summary '!$B18,'Availability Report - NGL'!$D:$D,"Active") | K18: =1-AVERAGEIFS('Availability Report - NGL'!P:P,'Availability Report - NGL'!$G:$G,'Billability Summary '!$B18,'Availability Report - NGL'!$D:$D,"Active") | L18: =1-AVERAGEIFS('Availability Report - NGL'!Q:Q,'Availability Report - NGL'!$G:$G,'Billability Summary '!$B18,'Availability Report - NGL'!$D:$D,"Active") | M18: =1-AVERAGEIFS('Availability Report - NGL'!R:R,'Availability Report - NGL'!$G:$G,'Billability Summary '!$B18,'Availability Report - NGL'!$D:$D,"Active") | N18: =1-AVERAGEIFS('Availability Report - NGL'!S:S,'Availability Report - NGL'!$G:$G,'Billability Summary '!$B18,'Availability Report - NGL'!$D:$D,"Active") | O18: =1-AVERAGEIFS('Availability Report - NGL'!T:T,'Availability Report - NGL'!$G:$G,'Billability Summary '!$B18,'Availability Report - NGL'!$D:$D,"Active") | Q18: =AVERAGE(N18:O18) | R18: =1-Q18 | T18: =+SUMIFS('Availability Report - NGL'!#REF!,'Availability Report - NGL'!$G:$G,'Billability Summary '!$B18,'Availability Report - NGL'!$D:$D,"Active") | V18: =+SUMIFS('Availability Report - NGL'!#REF!,'Availability Report - NGL'!$G:$G,'Billability Summary '!$B18,'Availability Report - NGL'!$D:$D,"Active")
B19: Apps & Development | C19: =COUNTIFS('Availability Report - NGL'!$G:$G,'Billability Summary '!$B19,'Availability Report - NGL'!$D:$D,"Active") | D19: =1-AVERAGEIFS('Availability Report - NGL'!I:I,'Availability Report - NGL'!$G:$G,'Billability Summary '!$B19,'Availability Report - NGL'!$D:$D,"Active") | E19: =1-AVERAGEIFS('Availability Report - NGL'!J:J,'Availability Report - NGL'!$G:$G,'Billability Summary '!$B19,'Availability Report - NGL'!$D:$D,"Active") | F19: =1-AVERAGEIFS('Availability Report - NGL'!K:K,'Availability Report - NGL'!$G:$G,'Billability Summary '!$B19,'Availability Report - NGL'!$D:$D,"Active") | G19: =1-AVERAGEIFS('Availability Report - NGL'!L:L,'Availability Report - NGL'!$G:$G,'Billability Summary '!$B19,'Availability Report - NGL'!$D:$D,"Active") | H19: =1-AVERAGEIFS('Availability Report - NGL'!M:M,'Availability Report - NGL'!$G:$G,'Billability Summary '!$B19,'Availability Report - NGL'!$D:$D,"Active") | I19: =1-AVERAGEIFS('Availability Report - NGL'!N:N,'Availability Report - NGL'!$G:$G,'Billability Summary '!$B19,'Availability Report - NGL'!$D:$D,"Active") | J19: =1-AVERAGEIFS('Availability Report - NGL'!O:O,'Availability Report - NGL'!$G:$G,'Billability Summary '!$B19,'Availability Report - NGL'!$D:$D,"Active") | K19: =1-AVERAGEIFS('Availability Report - NGL'!P:P,'Availability Report - NGL'!$G:$G,'Billability Summary '!$B19,'Availability Report - NGL'!$D:$D,"Active") | L19: =1-AVERAGEIFS('Availability Report - NGL'!Q:Q,'Availability Report - NGL'!$G:$G,'Billability Summary '!$B19,'Availability Report - NGL'!$D:$D,"Active") | M19: =1-AVERAGEIFS('Availability Report - NGL'!R:R,'Availability Report - NGL'!$G:$G,'Billability Summary '!$B19,'Availability Report - NGL'!$D:$D,"Active") | N19: =1-AVERAGEIFS('Availability Report - NGL'!S:S,'Availability Report - NGL'!$G:$G,'Billability Summary '!$B19,'Availability Report - NGL'!$D:$D,"Active") | O19: =1-AVERAGEIFS('Availability Report - NGL'!T:T,'Availability Report - NGL'!$G:$G,'Billability Summary '!$B19,'Availability Report - NGL'!$D:$D,"Active") | Q19: =AVERAGE(N19:O19) | R19: =1-Q19 | T19: =+SUMIFS('Availability Report - NGL'!#REF!,'Availability Report - NGL'!$G:$G,'Billability Summary '!$B19,'Availability Report - NGL'!$D:$D,"Active") | V19: =+SUMIFS('Availability Report - NGL'!#REF!,'Availability Report - NGL'!$G:$G,'Billability Summary '!$B19,'Availability Report - NGL'!$D:$D,"Active")
B20: Data & AI | C20: =COUNTIFS('Availability Report - NGL'!$G:$G,'Billability Summary '!$B20,'Availability Report - NGL'!$D:$D,"Active") | D20: =1-AVERAGEIFS('Availability Report - NGL'!I:I,'Availability Report - NGL'!$G:$G,'Billability Summary '!$B20,'Availability Report - NGL'!$D:$D,"Active") | E20: =1-AVERAGEIFS('Availability Report - NGL'!J:J,'Availability Report - NGL'!$G:$G,'Billability Summary '!$B20,'Availability Report - NGL'!$D:$D,"Active") | F20: =1-AVERAGEIFS('Availability Report - NGL'!K:K,'Availability Report - NGL'!$G:$G,'Billability Summary '!$B20,'Availability Report - NGL'!$D:$D,"Active") | G20: =1-AVERAGEIFS('Availability Report - NGL'!L:L,'Availability Report - NGL'!$G:$G,'Billability Summary '!$B20,'Availability Report - NGL'!$D:$D,"Active") | H20: =1-AVERAGEIFS('Availability Report - NGL'!M:M,'Availability Report - NGL'!$G:$G,'Billability Summary '!$B20,'Availability Report - NGL'!$D:$D,"Active") | I20: =1-AVERAGEIFS('Availability Report - NGL'!N:N,'Availability Report - NGL'!$G:$G,'Billability Summary '!$B20,'Availability Report - NGL'!$D:$D,"Active") | J20: =1-AVERAGEIFS('Availability Report - NGL'!O:O,'Availability Report - NGL'!$G:$G,'Billability Summary '!$B20,'Availability Report - NGL'!$D:$D,"Active") | K20: =1-AVERAGEIFS('Availability Report - NGL'!P:P,'Availability Report - NGL'!$G:$G,'Billability Summary '!$B20,'Availability Report - NGL'!$D:$D,"Active") | L20: =1-AVERAGEIFS('Availability Report - NGL'!Q:Q,'Availability Report - NGL'!$G:$G,'Billability Summary '!$B20,'Availability Report - NGL'!$D:$D,"Active") | M20: =1-AVERAGEIFS('Availability Report - NGL'!R:R,'Availability Report - NGL'!$G:$G,'Billability Summary '!$B20,'Availability Report - NGL'!$D:$D,"Active") | N20: =1-AVERAGEIFS('Availability Report - NGL'!S:S,'Availability Report - NGL'!$G:$G,'Billability Summary '!$B20,'Availability Report - NGL'!$D:$D,"Active") | O20: =1-AVERAGEIFS('Availability Report - NGL'!T:T,'Availability Report - NGL'!$G:$G,'Billability Summary '!$B20,'Availability Report - NGL'!$D:$D,"Active") | Q20: =AVERAGE(N20:O20) | R20: =1-Q20 | T20: =+SUMIFS('Availability Report - NGL'!#REF!,'Availability Report - NGL'!$G:$G,'Billability Summary '!$B20,'Availability Report - NGL'!$D:$D,"Active") | V20: =+SUMIFS('Availability Report - NGL'!#REF!,'Availability Report - NGL'!$G:$G,'Billability Summary '!$B20,'Availability Report - NGL'!$D:$D,"Active")
B21: Renewable and Engineering | C21: =COUNTIFS('Availability Report - NGL'!$G:$G,'Billability Summary '!$B21,'Availability Report - NGL'!$D:$D,"Active") | D21: =1-AVERAGEIFS('Availability Report - NGL'!I:I,'Availability Report - NGL'!$G:$G,'Billability Summary '!$B21,'Availability Report - NGL'!$D:$D,"Active") | E21: =1-AVERAGEIFS('Availability Report - NGL'!J:J,'Availability Report - NGL'!$G:$G,'Billability Summary '!$B21,'Availability Report - NGL'!$D:$D,"Active") | F21: =1-AVERAGEIFS('Availability Report - NGL'!K:K,'Availability Report - NGL'!$G:$G,'Billability Summary '!$B21,'Availability Report - NGL'!$D:$D,"Active") | G21: =1-AVERAGEIFS('Availability Report - NGL'!L:L,'Availability Report - NGL'!$G:$G,'Billability Summary '!$B21,'Availability Report - NGL'!$D:$D,"Active") | H21: =1-AVERAGEIFS('Availability Report - NGL'!M:M,'Availability Report - NGL'!$G:$G,'Billability Summary '!$B21,'Availability Report - NGL'!$D:$D,"Active") | I21: =1-AVERAGEIFS('Availability Report - NGL'!N:N,'Availability Report - NGL'!$G:$G,'Billability Summary '!$B21,'Availability Report - NGL'!$D:$D,"Active") | J21: =1-AVERAGEIFS('Availability Report - NGL'!O:O,'Availability Report - NGL'!$G:$G,'Billability Summary '!$B21,'Availability Report - NGL'!$D:$D,"Active") | K21: =1-AVERAGEIFS('Availability Report - NGL'!P:P,'Availability Report - NGL'!$G:$G,'Billability Summary '!$B21,'Availability Report - NGL'!$D:$D,"Active") | L21: =1-AVERAGEIFS('Availability Report - NGL'!Q:Q,'Availability Report - NGL'!$G:$G,'Billability Summary '!$B21,'Availability Report - NGL'!$D:$D,"Active") | M21: =1-AVERAGEIFS('Availability Report - NGL'!R:R,'Availability Report - NGL'!$G:$G,'Billability Summary '!$B21,'Availability Report - NGL'!$D:$D,"Active") | N21: =1-AVERAGEIFS('Availability Report - NGL'!S:S,'Availability Report - NGL'!$G:$G,'Billability Summary '!$B21,'Availability Report - NGL'!$D:$D,"Active") | O21: =1-AVERAGEIFS('Availability Report - NGL'!T:T,'Availability Report - NGL'!$G:$G,'Billability Summary '!$B21,'Availability Report - NGL'!$D:$D,"Active") | Q21: =AVERAGE(N21:O21) | R21: =1-Q21 | T21: =+SUMIFS('Availability Report - NGL'!#REF!,'Availability Report - NGL'!$G:$G,'Billability Summary '!$B21,'Availability Report - NGL'!$D:$D,"Active") | V21: =+SUMIFS('Availability Report - NGL'!#REF!,'Availability Report - NGL'!$G:$G,'Billability Summary '!$B21,'Availability Report - NGL'!$D:$D,"Active")
B22: Growth | C22: =COUNTIFS('Availability Report - NGL'!$G:$G,'Billability Summary '!$B22,'Availability Report - NGL'!$D:$D,"Active") | D22: =1-AVERAGEIFS('Availability Report - NGL'!I:I,'Availability Report - NGL'!$G:$G,'Billability Summary '!$B22,'Availability Report - NGL'!$D:$D,"Active") | E22: =1-AVERAGEIFS('Availability Report - NGL'!J:J,'Availability Report - NGL'!$G:$G,'Billability Summary '!$B22,'Availability Report - NGL'!$D:$D,"Active") | F22: =1-AVERAGEIFS('Availability Report - NGL'!K:K,'Availability Report - NGL'!$G:$G,'Billability Summary '!$B22,'Availability Report - NGL'!$D:$D,"Active") | G22: =1-AVERAGEIFS('Availability Report - NGL'!L:L,'Availability Report - NGL'!$G:$G,'Billability Summary '!$B22,'Availability Report - NGL'!$D:$D,"Active") | H22: =1-AVERAGEIFS('Availability Report - NGL'!M:M,'Availability Report - NGL'!$G:$G,'Billability Summary '!$B22,'Availability Report - NGL'!$D:$D,"Active") | I22: =1-AVERAGEIFS('Availability Report - NGL'!N:N,'Availability Report - NGL'!$G:$G,'Billability Summary '!$B22,'Availability Report - NGL'!$D:$D,"Active") | J22: =1-AVERAGEIFS('Availability Report - NGL'!O:O,'Availability Report - NGL'!$G:$G,'Billability Summary '!$B22,'Availability Report - NGL'!$D:$D,"Active") | K22: =1-AVERAGEIFS('Availability Report - NGL'!P:P,'Availability Report - NGL'!$G:$G,'Billability Summary '!$B22,'Availability Report - NGL'!$D:$D,"Active") | L22: =1-AVERAGEIFS('Availability Report - NGL'!Q:Q,'Availability Report - NGL'!$G:$G,'Billability Summary '!$B22,'Availability Report - NGL'!$D:$D,"Active") | M22: =1-AVERAGEIFS('Availability Report - NGL'!R:R,'Availability Report - NGL'!$G:$G,'Billability Summary '!$B22,'Availability Report - NGL'!$D:$D,"Active") | N22: =1-AVERAGEIFS('Availability Report - NGL'!S:S,'Availability Report - NGL'!$G:$G,'Billability Summary '!$B22,'Availability Report - NGL'!$D:$D,"Active") | O22: =1-AVERAGEIFS('Availability Report - NGL'!T:T,'Availability Report - NGL'!$G:$G,'Billability Summary '!$B22,'Availability Report - NGL'!$D:$D,"Active") | Q22: =AVERAGE(N22:O22) | R22: =1-Q22 | T22: =+SUMIFS('Availability Report - NGL'!#REF!,'Availability Report - NGL'!$G:$G,'Billability Summary '!$B22,'Availability Report - NGL'!$D:$D,"Active") | V22: =+SUMIFS('Availability Report - NGL'!#REF!,'Availability Report - NGL'!$G:$G,'Billability Summary '!$B22,'Availability Report - NGL'!$D:$D,"Active")
B23: GCC - Hyderabad | C23: =COUNTIFS('Availability Report - NGL'!$G:$G,'Billability Summary '!$B23,'Availability Report - NGL'!$D:$D,"Active") | D23: =1-AVERAGEIFS('Availability Report - NGL'!I:I,'Availability Report - NGL'!$G:$G,'Billability Summary '!$B23,'Availability Report - NGL'!$D:$D,"Active") | E23: =1-AVERAGEIFS('Availability Report - NGL'!J:J,'Availability Report - NGL'!$G:$G,'Billability Summary '!$B23,'Availability Report - NGL'!$D:$D,"Active") | F23: =1-AVERAGEIFS('Availability Report - NGL'!K:K,'Availability Report - NGL'!$G:$G,'Billability Summary '!$B23,'Availability Report - NGL'!$D:$D,"Active") | G23: =1-AVERAGEIFS('Availability Report - NGL'!L:L,'Availability Report - NGL'!$G:$G,'Billability Summary '!$B23,'Availability Report - NGL'!$D:$D,"Active") | H23: =1-AVERAGEIFS('Availability Report - NGL'!M:M,'Availability Report - NGL'!$G:$G,'Billability Summary '!$B23,'Availability Report - NGL'!$D:$D,"Active") | I23: =1-AVERAGEIFS('Availability Report - NGL'!N:N,'Availability Report - NGL'!$G:$G,'Billability Summary '!$B23,'Availability Report - NGL'!$D:$D,"Active") | J23: =1-AVERAGEIFS('Availability Report - NGL'!O:O,'Availability Report - NGL'!$G:$G,'Billability Summary '!$B23,'Availability Report - NGL'!$D:$D,"Active") | K23: =1-AVERAGEIFS('Availability Report - NGL'!P:P,'Availability Report - NGL'!$G:$G,'Billability Summary '!$B23,'Availability Report - NGL'!$D:$D,"Active") | L23: =1-AVERAGEIFS('Availability Report - NGL'!Q:Q,'Availability Report - NGL'!$G:$G,'Billability Summary '!$B23,'Availability Report - NGL'!$D:$D,"Active") | M23: =1-AVERAGEIFS('Availability Report - NGL'!R:R,'Availability Report - NGL'!$G:$G,'Billability Summary '!$B23,'Availability Report - NGL'!$D:$D,"Active") | N23: =1-AVERAGEIFS('Availability Report - NGL'!S:S,'Availability Report - NGL'!$G:$G,'Billability Summary '!$B23,'Availability Report - NGL'!$D:$D,"Active") | O23: =1-AVERAGEIFS('Availability Report - NGL'!T:T,'Availability Report - NGL'!$G:$G,'Billability Summary '!$B23,'Availability Report - NGL'!$D:$D,"Active") | Q23: =AVERAGE(N23:O23) | R23: =1-Q23 | T23: =+SUMIFS('Availability Report - NGL'!#REF!,'Availability Report - NGL'!$G:$G,'Billability Summary '!$B23,'Availability Report - NGL'!$D:$D,"Active") | V23: =+SUMIFS('Availability Report - NGL'!#REF!,'Availability Report - NGL'!$G:$G,'Billability Summary '!$B23,'Availability Report - NGL'!$D:$D,"Active")
B24: Strategic Delivery | C24: =COUNTIFS('Availability Report - NGL'!$G:$G,'Billability Summary '!$B24,'Availability Report - NGL'!$D:$D,"Active") | D24: =1-AVERAGEIFS('Availability Report - NGL'!I:I,'Availability Report - NGL'!$G:$G,'Billability Summary '!$B24,'Availability Report - NGL'!$D:$D,"Active") | E24: =1-AVERAGEIFS('Availability Report - NGL'!J:J,'Availability Report - NGL'!$G:$G,'Billability Summary '!$B24,'Availability Report - NGL'!$D:$D,"Active") | F24: =1-AVERAGEIFS('Availability Report - NGL'!K:K,'Availability Report - NGL'!$G:$G,'Billability Summary '!$B24,'Availability Report - NGL'!$D:$D,"Active") | G24: =1-AVERAGEIFS('Availability Report - NGL'!L:L,'Availability Report - NGL'!$G:$G,'Billability Summary '!$B24,'Availability Report - NGL'!$D:$D,"Active") | H24: =1-AVERAGEIFS('Availability Report - NGL'!M:M,'Availability Report - NGL'!$G:$G,'Billability Summary '!$B24,'Availability Report - NGL'!$D:$D,"Active") | I24: =1-AVERAGEIFS('Availability Report - NGL'!N:N,'Availability Report - NGL'!$G:$G,'Billability Summary '!$B24,'Availability Report - NGL'!$D:$D,"Active") | J24: =1-AVERAGEIFS('Availability Report - NGL'!O:O,'Availability Report - NGL'!$G:$G,'Billability Summary '!$B24,'Availability Report - NGL'!$D:$D,"Active") | K24: =1-AVERAGEIFS('Availability Report - NGL'!P:P,'Availability Report - NGL'!$G:$G,'Billability Summary '!$B24,'Availability Report - NGL'!$D:$D,"Active") | L24: =1-AVERAGEIFS('Availability Report - NGL'!Q:Q,'Availability Report - NGL'!$G:$G,'Billability Summary '!$B24,'Availability Report - NGL'!$D:$D,"Active") | M24: =1-AVERAGEIFS('Availability Report - NGL'!R:R,'Availability Report - NGL'!$G:$G,'Billability Summary '!$B24,'Availability Report - NGL'!$D:$D,"Active") | N24: =1-AVERAGEIFS('Availability Report - NGL'!S:S,'Availability Report - NGL'!$G:$G,'Billability Summary '!$B24,'Availability Report - NGL'!$D:$D,"Active") | O24: =1-AVERAGEIFS('Availability Report - NGL'!T:T,'Availability Report - NGL'!$G:$G,'Billability Summary '!$B24,'Availability Report - NGL'!$D:$D,"Active") | Q24: =AVERAGE(N24:O24) | R24: =1-Q24 | T24: =+SUMIFS('Availability Report - NGL'!#REF!,'Availability Report - NGL'!$G:$G,'Billability Summary '!$B24,'Availability Report - NGL'!$D:$D,"Active") | V24: =+SUMIFS('Availability Report - NGL'!#REF!,'Availability Report - NGL'!$G:$G,'Billability Summary '!$B24,'Availability Report - NGL'!$D:$D,"Active")
C25: =SUM(C18:C24) | T25: =SUM(T18:T24) | V25: =SUM(V18:V24)
Q26: Mar'26
B27: Sub Practice | C27: Active Resources | D27: 45748 | E27: 45778 | F27: 45809 | G27: 45839 | H27: 45870 | I27: 45901 | J27: 45931 | K27: 45962 | L27: 45992 | M27: 46023 | N27: 46054 | O27: 46082 | Q27: Avg Billability | R27: Avg Availability | T27: Non Billable cost from April'25 to March '26 | V27: Non Billable cost from Jan'26 to March '26
B28: OT | C28: =COUNTIFS('Availability Report - NGL'!$H:$H,'Billability Summary '!$B28,'Availability Report - NGL'!$D:$D,"Active") | D28: =IFERROR(1-AVERAGEIFS('Availability Report - NGL'!I:I,'Availability Report - NGL'!$H:$H,'Billability Summary '!$B28,'Availability Report - NGL'!$D:$D,"Active"),0) | E28: =IFERROR(1-AVERAGEIFS('Availability Report - NGL'!J:J,'Availability Report - NGL'!$H:$H,'Billability Summary '!$B28,'Availability Report - NGL'!$D:$D,"Active"),0) | F28: =IFERROR(1-AVERAGEIFS('Availability Report - NGL'!K:K,'Availability Report - NGL'!$H:$H,'Billability Summary '!$B28,'Availability Report - NGL'!$D:$D,"Active"),0) | G28: =IFERROR(1-AVERAGEIFS('Availability Report - NGL'!L:L,'Availability Report - NGL'!$H:$H,'Billability Summary '!$B28,'Availability Report - NGL'!$D:$D,"Active"),0) | H28: =IFERROR(1-AVERAGEIFS('Availability Report - NGL'!M:M,'Availability Report - NGL'!$H:$H,'Billability Summary '!$B28,'Availability Report - NGL'!$D:$D,"Active"),0) | I28: =IFERROR(1-AVERAGEIFS('Availability Report - NGL'!N:N,'Availability Report - NGL'!$H:$H,'Billability Summary '!$B28,'Availability Report - NGL'!$D:$D,"Active"),0) | J28: =IFERROR(1-AVERAGEIFS('Availability Report - NGL'!O:O,'Availability Report - NGL'!$H:$H,'Billability Summary '!$B28,'Availability Report - NGL'!$D:$D,"Active"),0) | K28: =IFERROR(1-AVERAGEIFS('Availability Report - NGL'!P:P,'Availability Report - NGL'!$H:$H,'Billability Summary '!$B28,'Availability Report - NGL'!$D:$D,"Active"),0) | L28: =IFERROR(1-AVERAGEIFS('Availability Report - NGL'!Q:Q,'Availability Report - NGL'!$H:$H,'Billability Summary '!$B28,'Availability Report - NGL'!$D:$D,"Active"),0) | M28: =IFERROR(1-AVERAGEIFS('Availability Report - NGL'!R:R,'Availability Report - NGL'!$H:$H,'Billability Summary '!$B28,'Availability Report - NGL'!$D:$D,"Active"),0) | N28: =IFERROR(1-AVERAGEIFS('Availability Report - NGL'!S:S,'Availability Report - NGL'!$H:$H,'Billability Summary '!$B28,'Availability Report - NGL'!$D:$D,"Active"),0) | O28: =IFERROR(1-AVERAGEIFS('Availability Report - NGL'!T:T,'Availability Report - NGL'!$H:$H,'Billability Summary '!$B28,'Availability Report - NGL'!$D:$D,"Active"),0) | Q28: =AVERAGE(N28:O28) | R28: =1-Q28 | T28: =+SUMIFS('Availability Report - NGL'!#REF!,'Availability Report - NGL'!$H:$H,'Billability Summary '!$B28,'Availability Report - NGL'!$D:$D,"Active") | V28: =+SUMIFS('Availability Report - NGL'!#REF!,'Availability Report - NGL'!$H:$H,'Billability Summary '!$B28,'Availability Report - NGL'!$D:$D,"Active")
B29: Digital Solutions | C29: =COUNTIFS('Availability Report - NGL'!$H:$H,'Billability Summary '!$B29,'Availability Report - NGL'!$D:$D,"Active") | D29: =IFERROR(1-AVERAGEIFS('Availability Report - NGL'!I:I,'Availability Report - NGL'!$H:$H,'Billability Summary '!$B29,'Availability Report - NGL'!$D:$D,"Active"),0) | E29: =IFERROR(1-AVERAGEIFS('Availability Report - NGL'!J:J,'Availability Report - NGL'!$H:$H,'Billability Summary '!$B29,'Availability Report - NGL'!$D:$D,"Active"),0) | F29: =IFERROR(1-AVERAGEIFS('Availability Report - NGL'!K:K,'Availability Report - NGL'!$H:$H,'Billability Summary '!$B29,'Availability Report - NGL'!$D:$D,"Active"),0) | G29: =IFERROR(1-AVERAGEIFS('Availability Report - NGL'!L:L,'Availability Report - NGL'!$H:$H,'Billability Summary '!$B29,'Availability Report - NGL'!$D:$D,"Active"),0) | H29: =IFERROR(1-AVERAGEIFS('Availability Report - NGL'!M:M,'Availability Report - NGL'!$H:$H,'Billability Summary '!$B29,'Availability Report - NGL'!$D:$D,"Active"),0) | I29: =IFERROR(1-AVERAGEIFS('Availability Report - NGL'!N:N,'Availability Report - NGL'!$H:$H,'Billability Summary '!$B29,'Availability Report - NGL'!$D:$D,"Active"),0) | J29: =IFERROR(1-AVERAGEIFS('Availability Report - NGL'!O:O,'Availability Report - NGL'!$H:$H,'Billability Summary '!$B29,'Availability Report - NGL'!$D:$D,"Active"),0) | K29: =IFERROR(1-AVERAGEIFS('Availability Report - NGL'!P:P,'Availability Report - NGL'!$H:$H,'Billability Summary '!$B29,'Availability Report - NGL'!$D:$D,"Active"),0) | L29: =IFERROR(1-AVERAGEIFS('Availability Report - NGL'!Q:Q,'Availability Report - NGL'!$H:$H,'Billability Summary '!$B29,'Availability Report - NGL'!$D:$D,"Active"),0) | M29: =IFERROR(1-AVERAGEIFS('Availability Report - NGL'!R:R,'Availability Report - NGL'!$H:$H,'Billability Summary '!$B29,'Availability Report - NGL'!$D:$D,"Active"),0) | N29: =IFERROR(1-AVERAGEIFS('Availability Report - NGL'!S:S,'Availability Report - NGL'!$H:$H,'Billability Summary '!$B29,'Availability Report - NGL'!$D:$D,"Active"),0) | O29: =IFERROR(1-AVERAGEIFS('Availability Report - NGL'!T:T,'Availability Report - NGL'!$H:$H,'Billability Summary '!$B29,'Availability Report - NGL'!$D:$D,"Active"),0) | Q29: =AVERAGE(N29:O29) | R29: =1-Q29 | T29: =+SUMIFS('Availability Report - NGL'!#REF!,'Availability Report - NGL'!$H:$H,'Billability Summary '!$B29,'Availability Report - NGL'!$D:$D,"Active") | V29: =+SUMIFS('Availability Report - NGL'!#REF!,'Availability Report - NGL'!$H:$H,'Billability Summary '!$B29,'Availability Report - NGL'!$D:$D,"Active")
B30: Platform Engineering | C30: =COUNTIFS('Availability Report - NGL'!$H:$H,'Billability Summary '!$B30,'Availability Report - NGL'!$D:$D,"Active") | D30: =IFERROR(1-AVERAGEIFS('Availability Report - NGL'!I:I,'Availability Report - NGL'!$H:$H,'Billability Summary '!$B30,'Availability Report - NGL'!$D:$D,"Active"),0) | E30: =IFERROR(1-AVERAGEIFS('Availability Report - NGL'!J:J,'Availability Report - NGL'!$H:$H,'Billability Summary '!$B30,'Availability Report - NGL'!$D:$D,"Active"),0) | F30: =IFERROR(1-AVERAGEIFS('Availability Report - NGL'!K:K,'Availability Report - NGL'!$H:$H,'Billability Summary '!$B30,'Availability Report - NGL'!$D:$D,"Active"),0) | G30: =IFERROR(1-AVERAGEIFS('Availability Report - NGL'!L:L,'Availability Report - NGL'!$H:$H,'Billability Summary '!$B30,'Availability Report - NGL'!$D:$D,"Active"),0) | H30: =IFERROR(1-AVERAGEIFS('Availability Report - NGL'!M:M,'Availability Report - NGL'!$H:$H,'Billability Summary '!$B30,'Availability Report - NGL'!$D:$D,"Active"),0) | I30: =IFERROR(1-AVERAGEIFS('Availability Report - NGL'!N:N,'Availability Report - NGL'!$H:$H,'Billability Summary '!$B30,'Availability Report - NGL'!$D:$D,"Active"),0) | J30: =IFERROR(1-AVERAGEIFS('Availability Report - NGL'!O:O,'Availability Report - NGL'!$H:$H,'Billability Summary '!$B30,'Availability Report - NGL'!$D:$D,"Active"),0) | K30: =IFERROR(1-AVERAGEIFS('Availability Report - NGL'!P:P,'Availability Report - NGL'!$H:$H,'Billability Summary '!$B30,'Availability Report - NGL'!$D:$D,"Active"),0) | L30: =IFERROR(1-AVERAGEIFS('Availability Report - NGL'!Q:Q,'Availability Report - NGL'!$H:$H,'Billability Summary '!$B30,'Availability Report - NGL'!$D:$D,"Active"),0) | M30: =IFERROR(1-AVERAGEIFS('Availability Report - NGL'!R:R,'Availability Report - NGL'!$H:$H,'Billability Summary '!$B30,'Availability Report - NGL'!$D:$D,"Active"),0) | N30: =IFERROR(1-AVERAGEIFS('Availability Report - NGL'!S:S,'Availability Report - NGL'!$H:$H,'Billability Summary '!$B30,'Availability Report - NGL'!$D:$D,"Active"),0) | O30: =IFERROR(1-AVERAGEIFS('Availability Report - NGL'!T:T,'Availability Report - NGL'!$H:$H,'Billability Summary '!$B30,'Availability Report - NGL'!$D:$D,"Active"),0) | Q30: =AVERAGE(N30:O30) | R30: =1-Q30 | T30: =+SUMIFS('Availability Report - NGL'!#REF!,'Availability Report - NGL'!$H:$H,'Billability Summary '!$B30,'Availability Report - NGL'!$D:$D,"Active") | V30: =+SUMIFS('Availability Report - NGL'!#REF!,'Availability Report - NGL'!$H:$H,'Billability Summary '!$B30,'Availability Report - NGL'!$D:$D,"Active")
B31: Project & Buiness Analysis | C31: =COUNTIFS('Availability Report - NGL'!$H:$H,'Billability Summary '!$B31,'Availability Report - NGL'!$D:$D,"Active") | D31: =IFERROR(1-AVERAGEIFS('Availability Report - NGL'!I:I,'Availability Report - NGL'!$H:$H,'Billability Summary '!$B31,'Availability Report - NGL'!$D:$D,"Active"),0) | E31: =IFERROR(1-AVERAGEIFS('Availability Report - NGL'!J:J,'Availability Report - NGL'!$H:$H,'Billability Summary '!$B31,'Availability Report - NGL'!$D:$D,"Active"),0) | F31: =IFERROR(1-AVERAGEIFS('Availability Report - NGL'!K:K,'Availability Report - NGL'!$H:$H,'Billability Summary '!$B31,'Availability Report - NGL'!$D:$D,"Active"),0) | G31: =IFERROR(1-AVERAGEIFS('Availability Report - NGL'!L:L,'Availability Report - NGL'!$H:$H,'Billability Summary '!$B31,'Availability Report - NGL'!$D:$D,"Active"),0) | H31: =IFERROR(1-AVERAGEIFS('Availability Report - NGL'!M:M,'Availability Report - NGL'!$H:$H,'Billability Summary '!$B31,'Availability Report - NGL'!$D:$D,"Active"),0) | I31: =IFERROR(1-AVERAGEIFS('Availability Report - NGL'!N:N,'Availability Report - NGL'!$H:$H,'Billability Summary '!$B31,'Availability Report - NGL'!$D:$D,"Active"),0) | J31: =IFERROR(1-AVERAGEIFS('Availability Report - NGL'!O:O,'Availability Report - NGL'!$H:$H,'Billability Summary '!$B31,'Availability Report - NGL'!$D:$D,"Active"),0) | K31: =IFERROR(1-AVERAGEIFS('Availability Report - NGL'!P:P,'Availability Report - NGL'!$H:$H,'Billability Summary '!$B31,'Availability Report - NGL'!$D:$D,"Active"),0) | L31: =IFERROR(1-AVERAGEIFS('Availability Report - NGL'!Q:Q,'Availability Report - NGL'!$H:$H,'Billability Summary '!$B31,'Availability Report - NGL'!$D:$D,"Active"),0) | M31: =IFERROR(1-AVERAGEIFS('Availability Report - NGL'!R:R,'Availability Report - NGL'!$H:$H,'Billability Summary '!$B31,'Availability Report - NGL'!$D:$D,"Active"),0) | N31: =IFERROR(1-AVERAGEIFS('Availability Report - NGL'!S:S,'Availability Report - NGL'!$H:$H,'Billability Summary '!$B31,'Availability Report - NGL'!$D:$D,"Active"),0) | O31: =IFERROR(1-AVERAGEIFS('Availability Report - NGL'!T:T,'Availability Report - NGL'!$H:$H,'Billability Summary '!$B31,'Availability Report - NGL'!$D:$D,"Active"),0) | Q31: =AVERAGE(N31:O31) | R31: =1-Q31 | T31: =+SUMIFS('Availability Report - NGL'!#REF!,'Availability Report - NGL'!$H:$H,'Billability Summary '!$B31,'Availability Report - NGL'!$D:$D,"Active") | V31: =+SUMIFS('Availability Report - NGL'!#REF!,'Availability Report - NGL'!$H:$H,'Billability Summary '!$B31,'Availability Report - NGL'!$D:$D,"Active")
B32: AI and Analytics | C32: =COUNTIFS('Availability Report - NGL'!$H:$H,'Billability Summary '!$B32,'Availability Report - NGL'!$D:$D,"Active") | D32: =IFERROR(1-AVERAGEIFS('Availability Report - NGL'!I:I,'Availability Report - NGL'!$H:$H,'Billability Summary '!$B32,'Availability Report - NGL'!$D:$D,"Active"),0) | E32: =IFERROR(1-AVERAGEIFS('Availability Report - NGL'!J:J,'Availability Report - NGL'!$H:$H,'Billability Summary '!$B32,'Availability Report - NGL'!$D:$D,"Active"),0) | F32: =IFERROR(1-AVERAGEIFS('Availability Report - NGL'!K:K,'Availability Report - NGL'!$H:$H,'Billability Summary '!$B32,'Availability Report - NGL'!$D:$D,"Active"),0) | G32: =IFERROR(1-AVERAGEIFS('Availability Report - NGL'!L:L,'Availability Report - NGL'!$H:$H,'Billability Summary '!$B32,'Availability Report - NGL'!$D:$D,"Active"),0) | H32: =IFERROR(1-AVERAGEIFS('Availability Report - NGL'!M:M,'Availability Report - NGL'!$H:$H,'Billability Summary '!$B32,'Availability Report - NGL'!$D:$D,"Active"),0) | I32: =IFERROR(1-AVERAGEIFS('Availability Report - NGL'!N:N,'Availability Report - NGL'!$H:$H,'Billability Summary '!$B32,'Availability Report - NGL'!$D:$D,"Active"),0) | J32: =IFERROR(1-AVERAGEIFS('Availability Report - NGL'!O:O,'Availability Report - NGL'!$H:$H,'Billability Summary '!$B32,'Availability Report - NGL'!$D:$D,"Active"),0) | K32: =IFERROR(1-AVERAGEIFS('Availability Report - NGL'!P:P,'Availability Report - NGL'!$H:$H,'Billability Summary '!$B32,'Availability Report - NGL'!$D:$D,"Active"),0) | L32: =IFERROR(1-AVERAGEIFS('Availability Report - NGL'!Q:Q,'Availability Report - NGL'!$H:$H,'Billability Summary '!$B32,'Availability Report - NGL'!$D:$D,"Active"),0) | M32: =IFERROR(1-AVERAGEIFS('Availability Report - NGL'!R:R,'Availability Report - NGL'!$H:$H,'Billability Summary '!$B32,'Availability Report - NGL'!$D:$D,"Active"),0) | N32: =IFERROR(1-AVERAGEIFS('Availability Report - NGL'!S:S,'Availability Report - NGL'!$H:$H,'Billability Summary '!$B32,'Availability Report - NGL'!$D:$D,"Active"),0) | O32: =IFERROR(1-AVERAGEIFS('Availability Report - NGL'!T:T,'Availability Report - NGL'!$H:$H,'Billability Summary '!$B32,'Availability Report - NGL'!$D:$D,"Active"),0) | Q32: =AVERAGE(N32:O32) | R32: =1-Q32 | T32: =+SUMIFS('Availability Report - NGL'!#REF!,'Availability Report - NGL'!$H:$H,'Billability Summary '!$B32,'Availability Report - NGL'!$D:$D,"Active") | V32: =+SUMIFS('Availability Report - NGL'!#REF!,'Availability Report - NGL'!$H:$H,'Billability Summary '!$B32,'Availability Report - NGL'!$D:$D,"Active")
B33: Renewable Advisory | C33: =COUNTIFS('Availability Report - NGL'!$H:$H,'Billability Summary '!$B33,'Availability Report - NGL'!$D:$D,"Active") | D33: =IFERROR(1-AVERAGEIFS('Availability Report - NGL'!I:I,'Availability Report - NGL'!$H:$H,'Billability Summary '!$B33,'Availability Report - NGL'!$D:$D,"Active"),0) | E33: =IFERROR(1-AVERAGEIFS('Availability Report - NGL'!J:J,'Availability Report - NGL'!$H:$H,'Billability Summary '!$B33,'Availability Report - NGL'!$D:$D,"Active"),0) | F33: =IFERROR(1-AVERAGEIFS('Availability Report - NGL'!K:K,'Availability Report - NGL'!$H:$H,'Billability Summary '!$B33,'Availability Report - NGL'!$D:$D,"Active"),0) | G33: =IFERROR(1-AVERAGEIFS('Availability Report - NGL'!L:L,'Availability Report - NGL'!$H:$H,'Billability Summary '!$B33,'Availability Report - NGL'!$D:$D,"Active"),0) | H33: =IFERROR(1-AVERAGEIFS('Availability Report - NGL'!M:M,'Availability Report - NGL'!$H:$H,'Billability Summary '!$B33,'Availability Report - NGL'!$D:$D,"Active"),0) | I33: =IFERROR(1-AVERAGEIFS('Availability Report - NGL'!N:N,'Availability Report - NGL'!$H:$H,'Billability Summary '!$B33,'Availability Report - NGL'!$D:$D,"Active"),0) | J33: =IFERROR(1-AVERAGEIFS('Availability Report - NGL'!O:O,'Availability Report - NGL'!$H:$H,'Billability Summary '!$B33,'Availability Report - NGL'!$D:$D,"Active"),0) | K33: =IFERROR(1-AVERAGEIFS('Availability Report - NGL'!P:P,'Availability Report - NGL'!$H:$H,'Billability Summary '!$B33,'Availability Report - NGL'!$D:$D,"Active"),0) | L33: =IFERROR(1-AVERAGEIFS('Availability Report - NGL'!Q:Q,'Availability Report - NGL'!$H:$H,'Billability Summary '!$B33,'Availability Report - NGL'!$D:$D,"Active"),0) | M33: =IFERROR(1-AVERAGEIFS('Availability Report - NGL'!R:R,'Availability Report - NGL'!$H:$H,'Billability Summary '!$B33,'Availability Report - NGL'!$D:$D,"Active"),0) | N33: =IFERROR(1-AVERAGEIFS('Availability Report - NGL'!S:S,'Availability Report - NGL'!$H:$H,'Billability Summary '!$B33,'Availability Report - NGL'!$D:$D,"Active"),0) | O33: =IFERROR(1-AVERAGEIFS('Availability Report - NGL'!T:T,'Availability Report - NGL'!$H:$H,'Billability Summary '!$B33,'Availability Report - NGL'!$D:$D,"Active"),0) | Q33: =AVERAGE(N33:O33) | R33: =1-Q33 | T33: =+SUMIFS('Availability Report - NGL'!#REF!,'Availability Report - NGL'!$H:$H,'Billability Summary '!$B33,'Availability Report - NGL'!$D:$D,"Active") | V33: =+SUMIFS('Availability Report - NGL'!#REF!,'Availability Report - NGL'!$H:$H,'Billability Summary '!$B33,'Availability Report - NGL'!$D:$D,"Active")
B34: SAP | C34: =COUNTIFS('Availability Report - NGL'!$H:$H,'Billability Summary '!$B34,'Availability Report - NGL'!$D:$D,"Active") | D34: =IFERROR(1-AVERAGEIFS('Availability Report - NGL'!I:I,'Availability Report - NGL'!$H:$H,'Billability Summary '!$B34,'Availability Report - NGL'!$D:$D,"Active"),0) | E34: =IFERROR(1-AVERAGEIFS('Availability Report - NGL'!J:J,'Availability Report - NGL'!$H:$H,'Billability Summary '!$B34,'Availability Report - NGL'!$D:$D,"Active"),0) | F34: =IFERROR(1-AVERAGEIFS('Availability Report - NGL'!K:K,'Availability Report - NGL'!$H:$H,'Billability Summary '!$B34,'Availability Report - NGL'!$D:$D,"Active"),0) | G34: =IFERROR(1-AVERAGEIFS('Availability Report - NGL'!L:L,'Availability Report - NGL'!$H:$H,'Billability Summary '!$B34,'Availability Report - NGL'!$D:$D,"Active"),0) | H34: =IFERROR(1-AVERAGEIFS('Availability Report - NGL'!M:M,'Availability Report - NGL'!$H:$H,'Billability Summary '!$B34,'Availability Report - NGL'!$D:$D,"Active"),0) | I34: =IFERROR(1-AVERAGEIFS('Availability Report - NGL'!N:N,'Availability Report - NGL'!$H:$H,'Billability Summary '!$B34,'Availability Report - NGL'!$D:$D,"Active"),0) | J34: =IFERROR(1-AVERAGEIFS('Availability Report - NGL'!O:O,'Availability Report - NGL'!$H:$H,'Billability Summary '!$B34,'Availability Report - NGL'!$D:$D,"Active"),0) | K34: =IFERROR(1-AVERAGEIFS('Availability Report - NGL'!P:P,'Availability Report - NGL'!$H:$H,'Billability Summary '!$B34,'Availability Report - NGL'!$D:$D,"Active"),0) | L34: =IFERROR(1-AVERAGEIFS('Availability Report - NGL'!Q:Q,'Availability Report - NGL'!$H:$H,'Billability Summary '!$B34,'Availability Report - NGL'!$D:$D,"Active"),0) | M34: =IFERROR(1-AVERAGEIFS('Availability Report - NGL'!R:R,'Availability Report - NGL'!$H:$H,'Billability Summary '!$B34,'Availability Report - NGL'!$D:$D,"Active"),0) | N34: =IFERROR(1-AVERAGEIFS('Availability Report - NGL'!S:S,'Availability Report - NGL'!$H:$H,'Billability Summary '!$B34,'Availability Report - NGL'!$D:$D,"Active"),0) | O34: =IFERROR(1-AVERAGEIFS('Availability Report - NGL'!T:T,'Availability Report - NGL'!$H:$H,'Billability Summary '!$B34,'Availability Report - NGL'!$D:$D,"Active"),0) | Q34: =AVERAGE(N34:O34) | R34: =1-Q34 | T34: =+SUMIFS('Availability Report - NGL'!#REF!,'Availability Report - NGL'!$H:$H,'Billability Summary '!$B34,'Availability Report - NGL'!$D:$D,"Active") | V34: =+SUMIFS('Availability Report - NGL'!#REF!,'Availability Report - NGL'!$H:$H,'Billability Summary '!$B34,'Availability Report - NGL'!$D:$D,"Active")
B35: Design Engineering | C35: =COUNTIFS('Availability Report - NGL'!$H:$H,'Billability Summary '!$B35,'Availability Report - NGL'!$D:$D,"Active") | D35: =IFERROR(1-AVERAGEIFS('Availability Report - NGL'!I:I,'Availability Report - NGL'!$H:$H,'Billability Summary '!$B35,'Availability Report - NGL'!$D:$D,"Active"),0) | E35: =IFERROR(1-AVERAGEIFS('Availability Report - NGL'!J:J,'Availability Report - NGL'!$H:$H,'Billability Summary '!$B35,'Availability Report - NGL'!$D:$D,"Active"),0) | F35: =IFERROR(1-AVERAGEIFS('Availability Report - NGL'!K:K,'Availability Report - NGL'!$H:$H,'Billability Summary '!$B35,'Availability Report - NGL'!$D:$D,"Active"),0) | G35: =IFERROR(1-AVERAGEIFS('Availability Report - NGL'!L:L,'Availability Report - NGL'!$H:$H,'Billability Summary '!$B35,'Availability Report - NGL'!$D:$D,"Active"),0) | H35: =IFERROR(1-AVERAGEIFS('Availability Report - NGL'!M:M,'Availability Report - NGL'!$H:$H,'Billability Summary '!$B35,'Availability Report - NGL'!$D:$D,"Active"),0) | I35: =IFERROR(1-AVERAGEIFS('Availability Report - NGL'!N:N,'Availability Report - NGL'!$H:$H,'Billability Summary '!$B35,'Availability Report - NGL'!$D:$D,"Active"),0) | J35: =IFERROR(1-AVERAGEIFS('Availability Report - NGL'!O:O,'Availability Report - NGL'!$H:$H,'Billability Summary '!$B35,'Availability Report - NGL'!$D:$D,"Active"),0) | K35: =IFERROR(1-AVERAGEIFS('Availability Report - NGL'!P:P,'Availability Report - NGL'!$H:$H,'Billability Summary '!$B35,'Availability Report - NGL'!$D:$D,"Active"),0) | L35: =IFERROR(1-AVERAGEIFS('Availability Report - NGL'!Q:Q,'Availability Report - NGL'!$H:$H,'Billability Summary '!$B35,'Availability Report - NGL'!$D:$D,"Active"),0) | M35: =IFERROR(1-AVERAGEIFS('Availability Report - NGL'!R:R,'Availability Report - NGL'!$H:$H,'Billability Summary '!$B35,'Availability Report - NGL'!$D:$D,"Active"),0) | N35: =IFERROR(1-AVERAGEIFS('Availability Report - NGL'!S:S,'Availability Report - NGL'!$H:$H,'Billability Summary '!$B35,'Availability Report - NGL'!$D:$D,"Active"),0) | O35: =IFERROR(1-AVERAGEIFS('Availability Report - NGL'!T:T,'Availability Report - NGL'!$H:$H,'Billability Summary '!$B35,'Availability Report - NGL'!$D:$D,"Active"),0) | Q35: =AVERAGE(N35:O35) | R35: =1-Q35 | T35: =+SUMIFS('Availability Report - NGL'!#REF!,'Availability Report - NGL'!$H:$H,'Billability Summary '!$B35,'Availability Report - NGL'!$D:$D,"Active") | V35: =+SUMIFS('Availability Report - NGL'!#REF!,'Availability Report - NGL'!$H:$H,'Billability Summary '!$B35,'Availability Report - NGL'!$D:$D,"Active")
B36: Growth | C36: =COUNTIFS('Availability Report - NGL'!$H:$H,'Billability Summary '!$B36,'Availability Report - NGL'!$D:$D,"Active") | D36: =IFERROR(1-AVERAGEIFS('Availability Report - NGL'!I:I,'Availability Report - NGL'!$H:$H,'Billability Summary '!$B36,'Availability Report - NGL'!$D:$D,"Active"),0) | E36: =IFERROR(1-AVERAGEIFS('Availability Report - NGL'!J:J,'Availability Report - NGL'!$H:$H,'Billability Summary '!$B36,'Availability Report - NGL'!$D:$D,"Active"),0) | F36: =IFERROR(1-AVERAGEIFS('Availability Report - NGL'!K:K,'Availability Report - NGL'!$H:$H,'Billability Summary '!$B36,'Availability Report - NGL'!$D:$D,"Active"),0) | G36: =IFERROR(1-AVERAGEIFS('Availability Report - NGL'!L:L,'Availability Report - NGL'!$H:$H,'Billability Summary '!$B36,'Availability Report - NGL'!$D:$D,"Active"),0) | H36: =IFERROR(1-AVERAGEIFS('Availability Report - NGL'!M:M,'Availability Report - NGL'!$H:$H,'Billability Summary '!$B36,'Availability Report - NGL'!$D:$D,"Active"),0) | I36: =IFERROR(1-AVERAGEIFS('Availability Report - NGL'!N:N,'Availability Report - NGL'!$H:$H,'Billability Summary '!$B36,'Availability Report - NGL'!$D:$D,"Active"),0) | J36: =IFERROR(1-AVERAGEIFS('Availability Report - NGL'!O:O,'Availability Report - NGL'!$H:$H,'Billability Summary '!$B36,'Availability Report - NGL'!$D:$D,"Active"),0) | K36: =IFERROR(1-AVERAGEIFS('Availability Report - NGL'!P:P,'Availability Report - NGL'!$H:$H,'Billability Summary '!$B36,'Availability Report - NGL'!$D:$D,"Active"),0) | L36: =IFERROR(1-AVERAGEIFS('Availability Report - NGL'!Q:Q,'Availability Report - NGL'!$H:$H,'Billability Summary '!$B36,'Availability Report - NGL'!$D:$D,"Active"),0) | M36: =IFERROR(1-AVERAGEIFS('Availability Report - NGL'!R:R,'Availability Report - NGL'!$H:$H,'Billability Summary '!$B36,'Availability Report - NGL'!$D:$D,"Active"),0) | N36: =IFERROR(1-AVERAGEIFS('Availability Report - NGL'!S:S,'Availability Report - NGL'!$H:$H,'Billability Summary '!$B36,'Availability Report - NGL'!$D:$D,"Active"),0) | O36: =IFERROR(1-AVERAGEIFS('Availability Report - NGL'!T:T,'Availability Report - NGL'!$H:$H,'Billability Summary '!$B36,'Availability Report - NGL'!$D:$D,"Active"),0) | Q36: =AVERAGE(N36:O36) | R36: =1-Q36 | T36: =+SUMIFS('Availability Report - NGL'!#REF!,'Availability Report - NGL'!$H:$H,'Billability Summary '!$B36,'Availability Report - NGL'!$D:$D,"Active") | V36: =+SUMIFS('Availability Report - NGL'!#REF!,'Availability Report - NGL'!$H:$H,'Billability Summary '!$B36,'Availability Report - NGL'!$D:$D,"Active")
B37: Managed Services | C37: =COUNTIFS('Availability Report - NGL'!$H:$H,'Billability Summary '!$B37,'Availability Report - NGL'!$D:$D,"Active") | D37: =IFERROR(1-AVERAGEIFS('Availability Report - NGL'!I:I,'Availability Report - NGL'!$H:$H,'Billability Summary '!$B37,'Availability Report - NGL'!$D:$D,"Active"),0) | E37: =IFERROR(1-AVERAGEIFS('Availability Report - NGL'!J:J,'Availability Report - NGL'!$H:$H,'Billability Summary '!$B37,'Availability Report - NGL'!$D:$D,"Active"),0) | F37: =IFERROR(1-AVERAGEIFS('Availability Report - NGL'!K:K,'Availability Report - NGL'!$H:$H,'Billability Summary '!$B37,'Availability Report - NGL'!$D:$D,"Active"),0) | G37: =IFERROR(1-AVERAGEIFS('Availability Report - NGL'!L:L,'Availability Report - NGL'!$H:$H,'Billability Summary '!$B37,'Availability Report - NGL'!$D:$D,"Active"),0) | H37: =IFERROR(1-AVERAGEIFS('Availability Report - NGL'!M:M,'Availability Report - NGL'!$H:$H,'Billability Summary '!$B37,'Availability Report - NGL'!$D:$D,"Active"),0) | I37: =IFERROR(1-AVERAGEIFS('Availability Report - NGL'!N:N,'Availability Report - NGL'!$H:$H,'Billability Summary '!$B37,'Availability Report - NGL'!$D:$D,"Active"),0) | J37: =IFERROR(1-AVERAGEIFS('Availability Report - NGL'!O:O,'Availability Report - NGL'!$H:$H,'Billability Summary '!$B37,'Availability Report - NGL'!$D:$D,"Active"),0) | K37: =IFERROR(1-AVERAGEIFS('Availability Report - NGL'!P:P,'Availability Report - NGL'!$H:$H,'Billability Summary '!$B37,'Availability Report - NGL'!$D:$D,"Active"),0) | L37: =IFERROR(1-AVERAGEIFS('Availability Report - NGL'!Q:Q,'Availability Report - NGL'!$H:$H,'Billability Summary '!$B37,'Availability Report - NGL'!$D:$D,"Active"),0) | M37: =IFERROR(1-AVERAGEIFS('Availability Report - NGL'!R:R,'Availability Report - NGL'!$H:$H,'Billability Summary '!$B37,'Availability Report - NGL'!$D:$D,"Active"),0) | N37: =IFERROR(1-AVERAGEIFS('Availability Report - NGL'!S:S,'Availability Report - NGL'!$H:$H,'Billability Summary '!$B37,'Availability Report - NGL'!$D:$D,"Active"),0) | O37: =IFERROR(1-AVERAGEIFS('Availability Report - NGL'!T:T,'Availability Report - NGL'!$H:$H,'Billability Summary '!$B37,'Availability Report - NGL'!$D:$D,"Active"),0) | Q37: =AVERAGE(N37:O37) | R37: =1-Q37 | T37: =+SUMIFS('Availability Report - NGL'!#REF!,'Availability Report - NGL'!$H:$H,'Billability Summary '!$B37,'Availability Report - NGL'!$D:$D,"Active") | V37: =+SUMIFS('Availability Report - NGL'!#REF!,'Availability Report - NGL'!$H:$H,'Billability Summary '!$B37,'Availability Report - NGL'!$D:$D,"Active")
B38: Asset & Intelligence | C38: =COUNTIFS('Availability Report - NGL'!$H:$H,'Billability Summary '!$B38,'Availability Report - NGL'!$D:$D,"Active") | D38: =IFERROR(1-AVERAGEIFS('Availability Report - NGL'!I:I,'Availability Report - NGL'!$H:$H,'Billability Summary '!$B38,'Availability Report - NGL'!$D:$D,"Active"),0) | E38: =IFERROR(1-AVERAGEIFS('Availability Report - NGL'!J:J,'Availability Report - NGL'!$H:$H,'Billability Summary '!$B38,'Availability Report - NGL'!$D:$D,"Active"),0) | F38: =IFERROR(1-AVERAGEIFS('Availability Report - NGL'!K:K,'Availability Report - NGL'!$H:$H,'Billability Summary '!$B38,'Availability Report - NGL'!$D:$D,"Active"),0) | G38: =IFERROR(1-AVERAGEIFS('Availability Report - NGL'!L:L,'Availability Report - NGL'!$H:$H,'Billability Summary '!$B38,'Availability Report - NGL'!$D:$D,"Active"),0) | H38: =IFERROR(1-AVERAGEIFS('Availability Report - NGL'!M:M,'Availability Report - NGL'!$H:$H,'Billability Summary '!$B38,'Availability Report - NGL'!$D:$D,"Active"),0) | I38: =IFERROR(1-AVERAGEIFS('Availability Report - NGL'!N:N,'Availability Report - NGL'!$H:$H,'Billability Summary '!$B38,'Availability Report - NGL'!$D:$D,"Active"),0) | J38: =IFERROR(1-AVERAGEIFS('Availability Report - NGL'!O:O,'Availability Report - NGL'!$H:$H,'Billability Summary '!$B38,'Availability Report - NGL'!$D:$D,"Active"),0) | K38: =IFERROR(1-AVERAGEIFS('Availability Report - NGL'!P:P,'Availability Report - NGL'!$H:$H,'Billability Summary '!$B38,'Availability Report - NGL'!$D:$D,"Active"),0) | L38: =IFERROR(1-AVERAGEIFS('Availability Report - NGL'!Q:Q,'Availability Report - NGL'!$H:$H,'Billability Summary '!$B38,'Availability Report - NGL'!$D:$D,"Active"),0) | M38: =IFERROR(1-AVERAGEIFS('Availability Report - NGL'!R:R,'Availability Report - NGL'!$H:$H,'Billability Summary '!$B38,'Availability Report - NGL'!$D:$D,"Active"),0) | N38: =IFERROR(1-AVERAGEIFS('Availability Report - NGL'!S:S,'Availability Report - NGL'!$H:$H,'Billability Summary '!$B38,'Availability Report - NGL'!$D:$D,"Active"),0) | O38: =IFERROR(1-AVERAGEIFS('Availability Report - NGL'!T:T,'Availability Report - NGL'!$H:$H,'Billability Summary '!$B38,'Availability Report - NGL'!$D:$D,"Active"),0) | Q38: =AVERAGE(N38:O38) | R38: =1-Q38 | T38: =+SUMIFS('Availability Report - NGL'!#REF!,'Availability Report - NGL'!$H:$H,'Billability Summary '!$B38,'Availability Report - NGL'!$D:$D,"Active") | V38: =+SUMIFS('Availability Report - NGL'!#REF!,'Availability Report - NGL'!$H:$H,'Billability Summary '!$B38,'Availability Report - NGL'!$D:$D,"Active")
B39: Testing & Assurance | C39: =COUNTIFS('Availability Report - NGL'!$H:$H,'Billability Summary '!$B39,'Availability Report - NGL'!$D:$D,"Active") | D39: =IFERROR(1-AVERAGEIFS('Availability Report - NGL'!I:I,'Availability Report - NGL'!$H:$H,'Billability Summary '!$B39,'Availability Report - NGL'!$D:$D,"Active"),0) | E39: =IFERROR(1-AVERAGEIFS('Availability Report - NGL'!J:J,'Availability Report - NGL'!$H:$H,'Billability Summary '!$B39,'Availability Report - NGL'!$D:$D,"Active"),0) | F39: =IFERROR(1-AVERAGEIFS('Availability Report - NGL'!K:K,'Availability Report - NGL'!$H:$H,'Billability Summary '!$B39,'Availability Report - NGL'!$D:$D,"Active"),0) | G39: =IFERROR(1-AVERAGEIFS('Availability Report - NGL'!L:L,'Availability Report - NGL'!$H:$H,'Billability Summary '!$B39,'Availability Report - NGL'!$D:$D,"Active"),0) | H39: =IFERROR(1-AVERAGEIFS('Availability Report - NGL'!M:M,'Availability Report - NGL'!$H:$H,'Billability Summary '!$B39,'Availability Report - NGL'!$D:$D,"Active"),0) | I39: =IFERROR(1-AVERAGEIFS('Availability Report - NGL'!N:N,'Availability Report - NGL'!$H:$H,'Billability Summary '!$B39,'Availability Report - NGL'!$D:$D,"Active"),0) | J39: =IFERROR(1-AVERAGEIFS('Availability Report - NGL'!O:O,'Availability Report - NGL'!$H:$H,'Billability Summary '!$B39,'Availability Report - NGL'!$D:$D,"Active"),0) | K39: =IFERROR(1-AVERAGEIFS('Availability Report - NGL'!P:P,'Availability Report - NGL'!$H:$H,'Billability Summary '!$B39,'Availability Report - NGL'!$D:$D,"Active"),0) | L39: =IFERROR(1-AVERAGEIFS('Availability Report - NGL'!Q:Q,'Availability Report - NGL'!$H:$H,'Billability Summary '!$B39,'Availability Report - NGL'!$D:$D,"Active"),0) | M39: =IFERROR(1-AVERAGEIFS('Availability Report - NGL'!R:R,'Availability Report - NGL'!$H:$H,'Billability Summary '!$B39,'Availability Report - NGL'!$D:$D,"Active"),0) | N39: =IFERROR(1-AVERAGEIFS('Availability Report - NGL'!S:S,'Availability Report - NGL'!$H:$H,'Billability Summary '!$B39,'Availability Report - NGL'!$D:$D,"Active"),0) | O39: =IFERROR(1-AVERAGEIFS('Availability Report - NGL'!T:T,'Availability Report - NGL'!$H:$H,'Billability Summary '!$B39,'Availability Report - NGL'!$D:$D,"Active"),0) | Q39: =AVERAGE(N39:O39) | R39: =1-Q39 | T39: =+SUMIFS('Availability Report - NGL'!#REF!,'Availability Report - NGL'!$H:$H,'Billability Summary '!$B39,'Availability Report - NGL'!$D:$D,"Active") | V39: =+SUMIFS('Availability Report - NGL'!#REF!,'Availability Report - NGL'!$H:$H,'Billability Summary '!$B39,'Availability Report - NGL'!$D:$D,"Active")
... B42: GCC - Hyderabad | C42: =COUNTIFS('Availability Report - NGL'!$H:$H,'Billability Summary '!$B42,'Availability Report - NGL'!$D:$D,"Active") | D42: =IFERROR(1-AVERAGEIFS('Availability Report - NGL'!I:I,'Availability Report - NGL'!$H:$H,'Billability Summary '!$B42,'Availability Report - NGL'!$D:$D,"Active"),0) | E42: =IFERROR(1-AVERAGEIFS('Availability Report - NGL'!J:J,'Availability Report - NGL'!$H:$H,'Billability Summary '!$B42,'Availability Report - NGL'!$D:$D,"Active"),0) | F42: =IFERROR(1-AVERAGEIFS('Availability Report - NGL'!K:K,'Availability Report - NGL'!$H:$H,'Billability Summary '!$B42,'Availability Report - NGL'!$D:$D,"Active"),0) | G42: =IFERROR(1-AVERAGEIFS('Availability Report - NGL'!L:L,'Availability Report - NGL'!$H:$H,'Billability Summary '!$B42,'Availability Report - NGL'!$D:$D,"Active"),0) | H42: =IFERROR(1-AVERAGEIFS('Availability Report - NGL'!M:M,'Availability Report - NGL'!$H:$H,'Billability Summary '!$B42,'Availability Report - NGL'!$D:$D,"Active"),0) | I42: =IFERROR(1-AVERAGEIFS('Availability Report - NGL'!N:N,'Availability Report - NGL'!$H:$H,'Billability Summary '!$B42,'Availability Report - NGL'!$D:$D,"Active"),0) | J42: =IFERROR(1-AVERAGEIFS('Availability Report - NGL'!O:O,'Availability Report - NGL'!$H:$H,'Billability Summary '!$B42,'Availability Report - NGL'!$D:$D,"Active"),0) | K42: =IFERROR(1-AVERAGEIFS('Availability Report - NGL'!P:P,'Availability Report - NGL'!$H:$H,'Billability Summary '!$B42,'Availability Report - NGL'!$D:$D,"Active"),0) | L42: =IFERROR(1-AVERAGEIFS('Availability Report - NGL'!Q:Q,'Availability Report - NGL'!$H:$H,'Billability Summary '!$B42,'Availability Report - NGL'!$D:$D,"Active"),0) | M42: =IFERROR(1-AVERAGEIFS('Availability Report - NGL'!R:R,'Availability Report - NGL'!$H:$H,'Billability Summary '!$B42,'Availability Report - NGL'!$D:$D,"Active"),0) | N42: =IFERROR(1-AVERAGEIFS('Availability Report - NGL'!S:S,'Availability Report - NGL'!$H:$H,'Billability Summary '!$B42,'Availability Report - NGL'!$D:$D,"Active"),0) | O42: =IFERROR(1-AVERAGEIFS('Availability Report - NGL'!T:T,'Availability Report - NGL'!$H:$H,'Billability Summary '!$B42,'Availability Report - NGL'!$D:$D,"Active"),0) | Q42: =AVERAGE(N42:O42) | R42: =1-Q42 | T42: =+SUMIFS('Availability Report - NGL'!#REF!,'Availability Report - NGL'!$H:$H,'Billability Summary '!$B42,'Availability Report - NGL'!$D:$D,"Active") | V42: =+SUMIFS('Availability Report - NGL'!#REF!,'Availability Report - NGL'!$H:$H,'Billability Summary '!$B42,'Availability Report - NGL'!$D:$D,"Active")
B43: Strategic Delivery | C43: =COUNTIFS('Availability Report - NGL'!$H:$H,'Billability Summary '!$B43,'Availability Report - NGL'!$D:$D,"Active") | D43: =IFERROR(1-AVERAGEIFS('Availability Report - NGL'!I:I,'Availability Report - NGL'!$H:$H,'Billability Summary '!$B43,'Availability Report - NGL'!$D:$D,"Active"),0) | E43: =IFERROR(1-AVERAGEIFS('Availability Report - NGL'!J:J,'Availability Report - NGL'!$H:$H,'Billability Summary '!$B43,'Availability Report - NGL'!$D:$D,"Active"),0) | F43: =IFERROR(1-AVERAGEIFS('Availability Report - NGL'!K:K,'Availability Report - NGL'!$H:$H,'Billability Summary '!$B43,'Availability Report - NGL'!$D:$D,"Active"),0) | G43: =IFERROR(1-AVERAGEIFS('Availability Report - NGL'!L:L,'Availability Report - NGL'!$H:$H,'Billability Summary '!$B43,'Availability Report - NGL'!$D:$D,"Active"),0) | H43: =IFERROR(1-AVERAGEIFS('Availability Report - NGL'!M:M,'Availability Report - NGL'!$H:$H,'Billability Summary '!$B43,'Availability Report - NGL'!$D:$D,"Active"),0) | I43: =IFERROR(1-AVERAGEIFS('Availability Report - NGL'!N:N,'Availability Report - NGL'!$H:$H,'Billability Summary '!$B43,'Availability Report - NGL'!$D:$D,"Active"),0) | J43: =IFERROR(1-AVERAGEIFS('Availability Report - NGL'!O:O,'Availability Report - NGL'!$H:$H,'Billability Summary '!$B43,'Availability Report - NGL'!$D:$D,"Active"),0) | K43: =IFERROR(1-AVERAGEIFS('Availability Report - NGL'!P:P,'Availability Report - NGL'!$H:$H,'Billability Summary '!$B43,'Availability Report - NGL'!$D:$D,"Active"),0) | L43: =IFERROR(1-AVERAGEIFS('Availability Report - NGL'!Q:Q,'Availability Report - NGL'!$H:$H,'Billability Summary '!$B43,'Availability Report - NGL'!$D:$D,"Active"),0) | M43: =IFERROR(1-AVERAGEIFS('Availability Report - NGL'!R:R,'Availability Report - NGL'!$H:$H,'Billability Summary '!$B43,'Availability Report - NGL'!$D:$D,"Active"),0) | N43: =IFERROR(1-AVERAGEIFS('Availability Report - NGL'!S:S,'Availability Report - NGL'!$H:$H,'Billability Summary '!$B43,'Availability Report - NGL'!$D:$D,"Active"),0) | O43: =IFERROR(1-AVERAGEIFS('Availability Report - NGL'!T:T,'Availability Report - NGL'!$H:$H,'Billability Summary '!$B43,'Availability Report - NGL'!$D:$D,"Active"),0) | Q43: =AVERAGE(N43:O43) | R43: =1-Q43
B44: GIS | C44: =COUNTIFS('Availability Report - NGL'!$H:$H,'Billability Summary '!$B44,'Availability Report - NGL'!$D:$D,"Active") | D44: =IFERROR(1-AVERAGEIFS('Availability Report - NGL'!I:I,'Availability Report - NGL'!$H:$H,'Billability Summary '!$B44,'Availability Report - NGL'!$D:$D,"Active"),0) | E44: =IFERROR(1-AVERAGEIFS('Availability Report - NGL'!J:J,'Availability Report - NGL'!$H:$H,'Billability Summary '!$B44,'Availability Report - NGL'!$D:$D,"Active"),0) | F44: =IFERROR(1-AVERAGEIFS('Availability Report - NGL'!K:K,'Availability Report - NGL'!$H:$H,'Billability Summary '!$B44,'Availability Report - NGL'!$D:$D,"Active"),0) | G44: =IFERROR(1-AVERAGEIFS('Availability Report - NGL'!L:L,'Availability Report - NGL'!$H:$H,'Billability Summary '!$B44,'Availability Report - NGL'!$D:$D,"Active"),0) | H44: =IFERROR(1-AVERAGEIFS('Availability Report - NGL'!M:M,'Availability Report - NGL'!$H:$H,'Billability Summary '!$B44,'Availability Report - NGL'!$D:$D,"Active"),0) | I44: =IFERROR(1-AVERAGEIFS('Availability Report - NGL'!N:N,'Availability Report - NGL'!$H:$H,'Billability Summary '!$B44,'Availability Report - NGL'!$D:$D,"Active"),0) | J44: =IFERROR(1-AVERAGEIFS('Availability Report - NGL'!O:O,'Availability Report - NGL'!$H:$H,'Billability Summary '!$B44,'Availability Report - NGL'!$D:$D,"Active"),0) | K44: =IFERROR(1-AVERAGEIFS('Availability Report - NGL'!P:P,'Availability Report - NGL'!$H:$H,'Billability Summary '!$B44,'Availability Report - NGL'!$D:$D,"Active"),0) | L44: =IFERROR(1-AVERAGEIFS('Availability Report - NGL'!Q:Q,'Availability Report - NGL'!$H:$H,'Billability Summary '!$B44,'Availability Report - NGL'!$D:$D,"Active"),0) | M44: =IFERROR(1-AVERAGEIFS('Availability Report - NGL'!R:R,'Availability Report - NGL'!$H:$H,'Billability Summary '!$B44,'Availability Report - NGL'!$D:$D,"Active"),0) | N44: =IFERROR(1-AVERAGEIFS('Availability Report - NGL'!S:S,'Availability Report - NGL'!$H:$H,'Billability Summary '!$B44,'Availability Report - NGL'!$D:$D,"Active"),0) | O44: =IFERROR(1-AVERAGEIFS('Availability Report - NGL'!T:T,'Availability Report - NGL'!$H:$H,'Billability Summary '!$B44,'Availability Report - NGL'!$D:$D,"Active"),0) | Q44: =AVERAGE(N44:O44) | R44: =1-Q44 | T44: =+SUMIFS('Availability Report - NGL'!#REF!,'Availability Report - NGL'!$H:$H,'Billability Summary '!$B44,'Availability Report - NGL'!$D:$D,"Active") | V44: =+SUMIFS('Availability Report - NGL'!#REF!,'Availability Report - NGL'!$H:$H,'Billability Summary '!$B44,'Availability Report - NGL'!$D:$D,"Active")
C45: =SUM(C28:C44) | T45: =SUM(T28:T44) | V45: =SUM(V28:V44)
B49: Non Billable cost from April'25 to March '26
B50: Entity/Practice | C50: Cost
B51: NGL | C51: =+SUMIF('Availability Report - NGL'!$D:$D,"Active",'Availability Report - NGL'!#REF!) | D51: =+C51-C58-C64
B52: nxzen - India | C52: =SUMIF('Availability Report - YTPL'!$D:$D,"Active",'Availability Report - YTPL'!#REF!) | D52: =+C52-C59-C65
B53: D&E - INDIA | C53: =SUMIFS('Availability Report - YTPL'!#REF!,'Availability Report - YTPL'!$E:$E,"D&E",'Availability Report - YTPL'!D:D,"Active") | D53: =+C53-C60-C66
B56: Non Billable cost from April'25 to Feb'26
B57: Entity/Practice | C57: Cost
B58: NGL | C58: =+C51-C64
B59: nxzen - India | C59: =+C52-C65
B60: D&E - INDIA | C60: =+C53-C66
B62: Non Billable cost for March '26
B63: Entity/Practice | C63: Cost
B64: NGL | C64: =SUMIF('Availability Report - NGL'!$D:$D,"Active",'Availability Report - NGL'!#REF!)
B65: nxzen - India | C65: =SUMIF('Availability Report - YTPL'!$D:$D,"Active",'Availability Report - YTPL'!#REF!)
B66: D&E - INDIA | C66: =SUMIFS('Availability Report - YTPL'!#REF!,'Availability Report - YTPL'!$D:$D,"Active",'Availability Report - YTPL'!$E:$E,"D&E")

Sheet Availability Summary
B2: Average Availability by Month
Q3: Feb'26 to Mar'26
B4: Entity/Practice | C4: Active Resources | D4: 45748 | E4: 45778 | F4: 45809 | G4: 45839 | H4: 45870 | I4: 45901 | J4: 45931 | K4: 45962 | L4: 45992 | M4: 46023 | N4: 46054 | O4: 46082 | Q4: Avg Avialability | R4: Avg Billability | T4: Non Billable cost from April'25 to March '26 | V4: Non Billable cost from Jan'26 to March '26
B5: NGL | C5: =COUNTIF('Availability Report - NGL'!$D:$D,"Active") | D5: =AVERAGEIF('Availability Report - NGL'!$D:$D,"Active",'Availability Report - NGL'!I:I) | E5: =AVERAGEIF('Availability Report - NGL'!$D:$D,"Active",'Availability Report - NGL'!J:J) | F5: =AVERAGEIF('Availability Report - NGL'!$D:$D,"Active",'Availability Report - NGL'!K:K) | G5: =AVERAGEIF('Availability Report - NGL'!$D:$D,"Active",'Availability Report - NGL'!L:L) | H5: =AVERAGEIF('Availability Report - NGL'!$D:$D,"Active",'Availability Report - NGL'!M:M) | I5: =AVERAGEIF('Availability Report - NGL'!$D:$D,"Active",'Availability Report - NGL'!N:N) | J5: =AVERAGEIF('Availability Report - NGL'!$D:$D,"Active",'Availability Report - NGL'!O:O) | K5: =AVERAGEIF('Availability Report - NGL'!$D:$D,"Active",'Availability Report - NGL'!P:P) | L5: =AVERAGEIF('Availability Report - NGL'!$D:$D,"Active",'Availability Report - NGL'!Q:Q) | M5: =AVERAGEIF('Availability Report - NGL'!$D:$D,"Active",'Availability Report - NGL'!R:R) | N5: =AVERAGEIF('Availability Report - NGL'!$D:$D,"Active",'Availability Report - NGL'!S:S) | O5: =AVERAGEIF('Availability Report - NGL'!$D:$D,"Active",'Availability Report - NGL'!T:T) | Q5: =AVERAGE(N5:O5) | R5: =1-Q5
B6: nxzen - India | C6: =COUNTIF('Availability Report - YTPL'!$D$5:$D$191,"Active")-2 | D6: =AVERAGEIF('Availability Report - YTPL'!$D:$D,"Active",'Availability Report - YTPL'!I:I) | E6: =AVERAGEIF('Availability Report - YTPL'!$D:$D,"Active",'Availability Report - YTPL'!J:J) | F6: =AVERAGEIF('Availability Report - YTPL'!$D:$D,"Active",'Availability Report - YTPL'!K:K) | G6: =AVERAGEIF('Availability Report - YTPL'!$D:$D,"Active",'Availability Report - YTPL'!L:L) | H6: =AVERAGEIF('Availability Report - YTPL'!$D:$D,"Active",'Availability Report - YTPL'!M:M) | I6: =AVERAGEIF('Availability Report - YTPL'!$D:$D,"Active",'Availability Report - YTPL'!N:N) | J6: =AVERAGEIF('Availability Report - YTPL'!$D:$D,"Active",'Availability Report - YTPL'!O:O) | K6: =AVERAGEIF('Availability Report - YTPL'!$D:$D,"Active",'Availability Report - YTPL'!P:P) | L6: =AVERAGEIF('Availability Report - YTPL'!$D:$D,"Active",'Availability Report - YTPL'!Q:Q) | M6: =AVERAGEIF('Availability Report - YTPL'!$D:$D,"Active",'Availability Report - YTPL'!R:R) | N6: =AVERAGEIF('Availability Report - YTPL'!$D:$D,"Active",'Availability Report - YTPL'!S:S) | O6: =AVERAGEIF('Availability Report - YTPL'!$D:$D,"Active",'Availability Report - YTPL'!T:T) | Q6: =AVERAGE(N6:O6) | R6: =1-Q6 | T6: =+SUMIF('Availability Report - YTPL'!$D:$D,"Active",'Availability Report - YTPL'!#REF!) | V6: =+SUMIF('Availability Report - YTPL'!$D:$D,"Active",'Availability Report - YTPL'!#REF!)
B7: D&E - INDIA | C7: =COUNTIFS('Availability Report - YTPL'!D:D,"Active",'Availability Report - YTPL'!E:E,"D&E")-2 | D7: =AVERAGEIFS('Availability Report - YTPL'!I:I,'Availability Report - YTPL'!$D:$D,"Active",'Availability Report - YTPL'!$E:$E,"D&E") | E7: =AVERAGEIFS('Availability Report - YTPL'!J:J,'Availability Report - YTPL'!$D:$D,"Active",'Availability Report - YTPL'!$E:$E,"D&E") | F7: =AVERAGEIFS('Availability Report - YTPL'!K:K,'Availability Report - YTPL'!$D:$D,"Active",'Availability Report - YTPL'!$E:$E,"D&E") | G7: =AVERAGEIFS('Availability Report - YTPL'!L:L,'Availability Report - YTPL'!$D:$D,"Active",'Availability Report - YTPL'!$E:$E,"D&E") | H7: =AVERAGEIFS('Availability Report - YTPL'!M:M,'Availability Report - YTPL'!$D:$D,"Active",'Availability Report - YTPL'!$E:$E,"D&E") | I7: =AVERAGEIFS('Availability Report - YTPL'!N:N,'Availability Report - YTPL'!$D:$D,"Active",'Availability Report - YTPL'!$E:$E,"D&E") | J7: =AVERAGEIFS('Availability Report - YTPL'!O:O,'Availability Report - YTPL'!$D:$D,"Active",'Availability Report - YTPL'!$E:$E,"D&E") | K7: =AVERAGEIFS('Availability Report - YTPL'!P:P,'Availability Report - YTPL'!$D:$D,"Active",'Availability Report - YTPL'!$E:$E,"D&E") | L7: =AVERAGEIFS('Availability Report - YTPL'!Q:Q,'Availability Report - YTPL'!$D:$D,"Active",'Availability Report - YTPL'!$E:$E,"D&E") | M7: =AVERAGEIFS('Availability Report - YTPL'!R:R,'Availability Report - YTPL'!$D:$D,"Active",'Availability Report - YTPL'!$E:$E,"D&E") | N7: =AVERAGEIFS('Availability Report - YTPL'!S:S,'Availability Report - YTPL'!$D:$D,"Active",'Availability Report - YTPL'!$E:$E,"D&E") | O7: =AVERAGEIFS('Availability Report - YTPL'!T:T,'Availability Report - YTPL'!$D:$D,"Active",'Availability Report - YTPL'!$E:$E,"D&E") | Q7: =AVERAGE(N7:O7) | R7: =1-Q7 | T7: =SUMIFS('Availability Report - YTPL'!#REF!,'Availability Report - YTPL'!$E:$E,"D&E",'Availability Report - YTPL'!D:D,"Active") | V7: =SUMIFS('Availability Report - YTPL'!#REF!,'Availability Report - YTPL'!$E:$E,"D&E",'Availability Report - YTPL'!D:D,"Active")
Q9: Feb'26 to Mar'26
B10: Function | C10: Active Resources | D10: 45748 | E10: 45778 | F10: 45809 | G10: 45839 | H10: 45870 | I10: 45901 | J10: 45931 | K10: 45962 | L10: 45992 | M10: 46023 | N10: 46054 | O10: 46082 | Q10: Avg Avialability | R10: Avg Billability | T10: Non Billable cost from April'25 to March '26 | V10: Non Billable cost from Jan'26 to March '26
B11: Digital & Engineering Services | C11: =COUNTIFS('Availability Report - NGL'!$F:$F,'Availability Summary'!$B11,'Availability Report - NGL'!$D:$D,"Active") | D11: =AVERAGEIFS('Availability Report - NGL'!I:I,'Availability Report - NGL'!$D:$D,"Active",'Availability Report - NGL'!$F:$F,'Availability Summary'!$B11) | E11: =AVERAGEIFS('Availability Report - NGL'!J:J,'Availability Report - NGL'!$D:$D,"Active",'Availability Report - NGL'!$F:$F,'Availability Summary'!$B11) | F11: =AVERAGEIFS('Availability Report - NGL'!K:K,'Availability Report - NGL'!$D:$D,"Active",'Availability Report - NGL'!$F:$F,'Availability Summary'!$B11) | G11: =AVERAGEIFS('Availability Report - NGL'!L:L,'Availability Report - NGL'!$D:$D,"Active",'Availability Report - NGL'!$F:$F,'Availability Summary'!$B11) | H11: =AVERAGEIFS('Availability Report - NGL'!M:M,'Availability Report - NGL'!$D:$D,"Active",'Availability Report - NGL'!$F:$F,'Availability Summary'!$B11) | I11: =AVERAGEIFS('Availability Report - NGL'!N:N,'Availability Report - NGL'!$D:$D,"Active",'Availability Report - NGL'!$F:$F,'Availability Summary'!$B11) | J11: =AVERAGEIFS('Availability Report - NGL'!O:O,'Availability Report - NGL'!$D:$D,"Active",'Availability Report - NGL'!$F:$F,'Availability Summary'!$B11) | K11: =AVERAGEIFS('Availability Report - NGL'!P:P,'Availability Report - NGL'!$D:$D,"Active",'Availability Report - NGL'!$F:$F,'Availability Summary'!$B11) | L11: =AVERAGEIFS('Availability Report - NGL'!Q:Q,'Availability Report - NGL'!$D:$D,"Active",'Availability Report - NGL'!$F:$F,'Availability Summary'!$B11) | M11: =AVERAGEIFS('Availability Report - NGL'!R:R,'Availability Report - NGL'!$D:$D,"Active",'Availability Report - NGL'!$F:$F,'Availability Summary'!$B11) | N11: =AVERAGEIFS('Availability Report - NGL'!S:S,'Availability Report - NGL'!$D:$D,"Active",'Availability Report - NGL'!$F:$F,'Availability Summary'!$B11) | O11: =AVERAGEIFS('Availability Report - NGL'!T:T,'Availability Report - NGL'!$D:$D,"Active",'Availability Report - NGL'!$F:$F,'Availability Summary'!$B11) | Q11: =AVERAGE(N11:O11) | R11: =1-Q11 | T11: =+SUMIFS('Availability Report - NGL'!#REF!,'Availability Report - NGL'!$F:$F,'Availability Summary'!B11,'Availability Report - NGL'!$D:$D,"Active") | V11: =+SUMIFS('Availability Report - NGL'!#REF!,'Availability Report - NGL'!$F:$F,'Availability Summary'!B11,'Availability Report - NGL'!$D:$D,"Active")
B12: Growth | C12: =COUNTIFS('Availability Report - NGL'!$F:$F,'Availability Summary'!$B12,'Availability Report - NGL'!$D:$D,"Active") | D12: =AVERAGEIFS('Availability Report - NGL'!I:I,'Availability Report - NGL'!$D:$D,"Active",'Availability Report - NGL'!$F:$F,'Availability Summary'!$B12) | E12: =AVERAGEIFS('Availability Report - NGL'!J:J,'Availability Report - NGL'!$D:$D,"Active",'Availability Report - NGL'!$F:$F,'Availability Summary'!$B12) | F12: =AVERAGEIFS('Availability Report - NGL'!K:K,'Availability Report - NGL'!$D:$D,"Active",'Availability Report - NGL'!$F:$F,'Availability Summary'!$B12) | G12: =AVERAGEIFS('Availability Report - NGL'!L:L,'Availability Report - NGL'!$D:$D,"Active",'Availability Report - NGL'!$F:$F,'Availability Summary'!$B12) | H12: =AVERAGEIFS('Availability Report - NGL'!M:M,'Availability Report - NGL'!$D:$D,"Active",'Availability Report - NGL'!$F:$F,'Availability Summary'!$B12) | I12: =AVERAGEIFS('Availability Report - NGL'!N:N,'Availability Report - NGL'!$D:$D,"Active",'Availability Report - NGL'!$F:$F,'Availability Summary'!$B12) | J12: =AVERAGEIFS('Availability Report - NGL'!O:O,'Availability Report - NGL'!$D:$D,"Active",'Availability Report - NGL'!$F:$F,'Availability Summary'!$B12) | K12: =AVERAGEIFS('Availability Report - NGL'!P:P,'Availability Report - NGL'!$D:$D,"Active",'Availability Report - NGL'!$F:$F,'Availability Summary'!$B12) | L12: =AVERAGEIFS('Availability Report - NGL'!Q:Q,'Availability Report - NGL'!$D:$D,"Active",'Availability Report - NGL'!$F:$F,'Availability Summary'!$B12) | M12: =AVERAGEIFS('Availability Report - NGL'!R:R,'Availability Report - NGL'!$D:$D,"Active",'Availability Report - NGL'!$F:$F,'Availability Summary'!$B12) | N12: =AVERAGEIFS('Availability Report - NGL'!S:S,'Availability Report - NGL'!$D:$D,"Active",'Availability Report - NGL'!$F:$F,'Availability Summary'!$B12) | O12: =AVERAGEIFS('Availability Report - NGL'!T:T,'Availability Report - NGL'!$D:$D,"Active",'Availability Report - NGL'!$F:$F,'Availability Summary'!$B12) | Q12: =AVERAGE(N12:O12) | R12: =1-Q12 | T12: =+SUMIFS('Availability Report - NGL'!#REF!,'Availability Report - NGL'!$F:$F,'Availability Summary'!B12,'Availability Report - NGL'!$D:$D,"Active") | V12: =+SUMIFS('Availability Report - NGL'!#REF!,'Availability Report - NGL'!$F:$F,'Availability Summary'!B12,'Availability Report - NGL'!$D:$D,"Active")
B13: GCC | C13: =COUNTIFS('Availability Report - NGL'!$F:$F,'Availability Summary'!$B13,'Availability Report - NGL'!$D:$D,"Active") | D13: =AVERAGEIFS('Availability Report - NGL'!I:I,'Availability Report - NGL'!$D:$D,"Active",'Availability Report - NGL'!$F:$F,'Availability Summary'!$B13) | E13: =AVERAGEIFS('Availability Report - NGL'!J:J,'Availability Report - NGL'!$D:$D,"Active",'Availability Report - NGL'!$F:$F,'Availability Summary'!$B13) | F13: =AVERAGEIFS('Availability Report - NGL'!K:K,'Availability Report - NGL'!$D:$D,"Active",'Availability Report - NGL'!$F:$F,'Availability Summary'!$B13) | G13: =AVERAGEIFS('Availability Report - NGL'!L:L,'Availability Report - NGL'!$D:$D,"Active",'Availability Report - NGL'!$F:$F,'Availability Summary'!$B13) | H13: =AVERAGEIFS('Availability Report - NGL'!M:M,'Availability Report - NGL'!$D:$D,"Active",'Availability Report - NGL'!$F:$F,'Availability Summary'!$B13) | I13: =AVERAGEIFS('Availability Report - NGL'!N:N,'Availability Report - NGL'!$D:$D,"Active",'Availability Report - NGL'!$F:$F,'Availability Summary'!$B13) | J13: =AVERAGEIFS('Availability Report - NGL'!O:O,'Availability Report - NGL'!$D:$D,"Active",'Availability Report - NGL'!$F:$F,'Availability Summary'!$B13) | K13: =AVERAGEIFS('Availability Report - NGL'!P:P,'Availability Report - NGL'!$D:$D,"Active",'Availability Report - NGL'!$F:$F,'Availability Summary'!$B13) | L13: =AVERAGEIFS('Availability Report - NGL'!Q:Q,'Availability Report - NGL'!$D:$D,"Active",'Availability Report - NGL'!$F:$F,'Availability Summary'!$B13) | M13: =AVERAGEIFS('Availability Report - NGL'!R:R,'Availability Report - NGL'!$D:$D,"Active",'Availability Report - NGL'!$F:$F,'Availability Summary'!$B13) | N13: =AVERAGEIFS('Availability Report - NGL'!S:S,'Availability Report - NGL'!$D:$D,"Active",'Availability Report - NGL'!$F:$F,'Availability Summary'!$B13) | O13: =AVERAGEIFS('Availability Report - NGL'!T:T,'Availability Report - NGL'!$D:$D,"Active",'Availability Report - NGL'!$F:$F,'Availability Summary'!$B13) | Q13: =AVERAGE(N13:O13) | R13: =1-Q13
B14: Strategic Delivery | C14: =COUNTIFS('Availability Report - NGL'!$F:$F,'Availability Summary'!$B14,'Availability Report - NGL'!$D:$D,"Active") | D14: =AVERAGEIFS('Availability Report - NGL'!I:I,'Availability Report - NGL'!$D:$D,"Active",'Availability Report - NGL'!$F:$F,'Availability Summary'!$B14) | E14: =AVERAGEIFS('Availability Report - NGL'!J:J,'Availability Report - NGL'!$D:$D,"Active",'Availability Report - NGL'!$F:$F,'Availability Summary'!$B14) | F14: =AVERAGEIFS('Availability Report - NGL'!K:K,'Availability Report - NGL'!$D:$D,"Active",'Availability Report - NGL'!$F:$F,'Availability Summary'!$B14) | G14: =AVERAGEIFS('Availability Report - NGL'!L:L,'Availability Report - NGL'!$D:$D,"Active",'Availability Report - NGL'!$F:$F,'Availability Summary'!$B14) | H14: =AVERAGEIFS('Availability Report - NGL'!M:M,'Availability Report - NGL'!$D:$D,"Active",'Availability Report - NGL'!$F:$F,'Availability Summary'!$B14) | I14: =AVERAGEIFS('Availability Report - NGL'!N:N,'Availability Report - NGL'!$D:$D,"Active",'Availability Report - NGL'!$F:$F,'Availability Summary'!$B14) | J14: =AVERAGEIFS('Availability Report - NGL'!O:O,'Availability Report - NGL'!$D:$D,"Active",'Availability Report - NGL'!$F:$F,'Availability Summary'!$B14) | K14: =AVERAGEIFS('Availability Report - NGL'!P:P,'Availability Report - NGL'!$D:$D,"Active",'Availability Report - NGL'!$F:$F,'Availability Summary'!$B14) | L14: =AVERAGEIFS('Availability Report - NGL'!Q:Q,'Availability Report - NGL'!$D:$D,"Active",'Availability Report - NGL'!$F:$F,'Availability Summary'!$B14) | M14: =AVERAGEIFS('Availability Report - NGL'!R:R,'Availability Report - NGL'!$D:$D,"Active",'Availability Report - NGL'!$F:$F,'Availability Summary'!$B14) | N14: =AVERAGEIFS('Availability Report - NGL'!S:S,'Availability Report - NGL'!$D:$D,"Active",'Availability Report - NGL'!$F:$F,'Availability Summary'!$B14) | O14: =AVERAGEIFS('Availability Report - NGL'!T:T,'Availability Report - NGL'!$D:$D,"Active",'Availability Report - NGL'!$F:$F,'Availability Summary'!$B14) | Q14: =AVERAGE(N14:O14) | R14: =1-Q14
C15: =SUM(C11:C14)
T16: =SUM(T11:T12) | V16: =SUM(V11:V12)
Q17: Feb'26 to Mar'26
B18: Practice | C18: Active Resources | D18: 45748 | E18: 45778 | F18: 45809 | G18: 45839 | H18: 45870 | I18: 45901 | J18: 45931 | K18: 45962 | L18: 45992 | M18: 46023 | N18: 46054 | O18: 46082 | Q18: Avg Avialability | R18: Avg Billability | T18: Non Billable cost from April'25 to March '26 | V18: Non Billable cost from Jan'26 to March '26
B19: OT | C19: =COUNTIFS('Availability Report - NGL'!$G:$G,'Availability Summary'!$B19,'Availability Report - NGL'!$D:$D,"Active") | D19: =AVERAGEIFS('Availability Report - NGL'!I:I,'Availability Report - NGL'!$G:$G,'Availability Summary'!$B19,'Availability Report - NGL'!$D:$D,"Active") | E19: =AVERAGEIFS('Availability Report - NGL'!J:J,'Availability Report - NGL'!$G:$G,'Availability Summary'!$B19,'Availability Report - NGL'!$D:$D,"Active") | F19: =AVERAGEIFS('Availability Report - NGL'!K:K,'Availability Report - NGL'!$G:$G,'Availability Summary'!$B19,'Availability Report - NGL'!$D:$D,"Active") | G19: =AVERAGEIFS('Availability Report - NGL'!L:L,'Availability Report - NGL'!$G:$G,'Availability Summary'!$B19,'Availability Report - NGL'!$D:$D,"Active") | H19: =AVERAGEIFS('Availability Report - NGL'!M:M,'Availability Report - NGL'!$G:$G,'Availability Summary'!$B19,'Availability Report - NGL'!$D:$D,"Active") | I19: =AVERAGEIFS('Availability Report - NGL'!N:N,'Availability Report - NGL'!$G:$G,'Availability Summary'!$B19,'Availability Report - NGL'!$D:$D,"Active") | J19: =AVERAGEIFS('Availability Report - NGL'!O:O,'Availability Report - NGL'!$G:$G,'Availability Summary'!$B19,'Availability Report - NGL'!$D:$D,"Active") | K19: =AVERAGEIFS('Availability Report - NGL'!P:P,'Availability Report - NGL'!$G:$G,'Availability Summary'!$B19,'Availability Report - NGL'!$D:$D,"Active") | L19: =AVERAGEIFS('Availability Report - NGL'!Q:Q,'Availability Report - NGL'!$G:$G,'Availability Summary'!$B19,'Availability Report - NGL'!$D:$D,"Active") | M19: =AVERAGEIFS('Availability Report - NGL'!R:R,'Availability Report - NGL'!$G:$G,'Availability Summary'!$B19,'Availability Report - NGL'!$D:$D,"Active") | N19: =AVERAGEIFS('Availability Report - NGL'!S:S,'Availability Report - NGL'!$G:$G,'Availability Summary'!$B19,'Availability Report - NGL'!$D:$D,"Active") | O19: =AVERAGEIFS('Availability Report - NGL'!T:T,'Availability Report - NGL'!$G:$G,'Availability Summary'!$B19,'Availability Report - NGL'!$D:$D,"Active") | Q19: =AVERAGE(N19:O19) | R19: =1-Q19 | T19: =+SUMIFS('Availability Report - NGL'!#REF!,'Availability Report - NGL'!$G:$G,'Availability Summary'!$B19,'Availability Report - NGL'!$D:$D,"Active") | V19: =+SUMIFS('Availability Report - NGL'!#REF!,'Availability Report - NGL'!$G:$G,'Availability Summary'!$B19,'Availability Report - NGL'!$D:$D,"Active")
B20: Apps & Development | C20: =COUNTIFS('Availability Report - NGL'!$G:$G,'Availability Summary'!$B20,'Availability Report - NGL'!$D:$D,"Active") | D20: =AVERAGEIFS('Availability Report - NGL'!I:I,'Availability Report - NGL'!$G:$G,'Availability Summary'!$B20,'Availability Report - NGL'!$D:$D,"Active") | E20: =AVERAGEIFS('Availability Report - NGL'!J:J,'Availability Report - NGL'!$G:$G,'Availability Summary'!$B20,'Availability Report - NGL'!$D:$D,"Active") | F20: =AVERAGEIFS('Availability Report - NGL'!K:K,'Availability Report - NGL'!$G:$G,'Availability Summary'!$B20,'Availability Report - NGL'!$D:$D,"Active") | G20: =AVERAGEIFS('Availability Report - NGL'!L:L,'Availability Report - NGL'!$G:$G,'Availability Summary'!$B20,'Availability Report - NGL'!$D:$D,"Active") | H20: =AVERAGEIFS('Availability Report - NGL'!M:M,'Availability Report - NGL'!$G:$G,'Availability Summary'!$B20,'Availability Report - NGL'!$D:$D,"Active") | I20: =AVERAGEIFS('Availability Report - NGL'!N:N,'Availability Report - NGL'!$G:$G,'Availability Summary'!$B20,'Availability Report - NGL'!$D:$D,"Active") | J20: =AVERAGEIFS('Availability Report - NGL'!O:O,'Availability Report - NGL'!$G:$G,'Availability Summary'!$B20,'Availability Report - NGL'!$D:$D,"Active") | K20: =AVERAGEIFS('Availability Report - NGL'!P:P,'Availability Report - NGL'!$G:$G,'Availability Summary'!$B20,'Availability Report - NGL'!$D:$D,"Active") | L20: =AVERAGEIFS('Availability Report - NGL'!Q:Q,'Availability Report - NGL'!$G:$G,'Availability Summary'!$B20,'Availability Report - NGL'!$D:$D,"Active") | M20: =AVERAGEIFS('Availability Report - NGL'!R:R,'Availability Report - NGL'!$G:$G,'Availability Summary'!$B20,'Availability Report - NGL'!$D:$D,"Active") | N20: =AVERAGEIFS('Availability Report - NGL'!S:S,'Availability Report - NGL'!$G:$G,'Availability Summary'!$B20,'Availability Report - NGL'!$D:$D,"Active") | O20: =AVERAGEIFS('Availability Report - NGL'!T:T,'Availability Report - NGL'!$G:$G,'Availability Summary'!$B20,'Availability Report - NGL'!$D:$D,"Active") | Q20: =AVERAGE(N20:O20) | R20: =1-Q20 | T20: =+SUMIFS('Availability Report - NGL'!#REF!,'Availability Report - NGL'!$G:$G,'Availability Summary'!$B20,'Availability Report - NGL'!$D:$D,"Active") | V20: =+SUMIFS('Availability Report - NGL'!#REF!,'Availability Report - NGL'!$G:$G,'Availability Summary'!$B20,'Availability Report - NGL'!$D:$D,"Active")
B21: Data & AI | C21: =COUNTIFS('Availability Report - NGL'!$G:$G,'Availability Summary'!$B21,'Availability Report - NGL'!$D:$D,"Active") | D21: =AVERAGEIFS('Availability Report - NGL'!I:I,'Availability Report - NGL'!$G:$G,'Availability Summary'!$B21,'Availability Report - NGL'!$D:$D,"Active") | E21: =AVERAGEIFS('Availability Report - NGL'!J:J,'Availability Report - NGL'!$G:$G,'Availability Summary'!$B21,'Availability Report - NGL'!$D:$D,"Active") | F21: =AVERAGEIFS('Availability Report - NGL'!K:K,'Availability Report - NGL'!$G:$G,'Availability Summary'!$B21,'Availability Report - NGL'!$D:$D,"Active") | G21: =AVERAGEIFS('Availability Report - NGL'!L:L,'Availability Report - NGL'!$G:$G,'Availability Summary'!$B21,'Availability Report - NGL'!$D:$D,"Active") | H21: =AVERAGEIFS('Availability Report - NGL'!M:M,'Availability Report - NGL'!$G:$G,'Availability Summary'!$B21,'Availability Report - NGL'!$D:$D,"Active") | I21: =AVERAGEIFS('Availability Report - NGL'!N:N,'Availability Report - NGL'!$G:$G,'Availability Summary'!$B21,'Availability Report - NGL'!$D:$D,"Active") | J21: =AVERAGEIFS('Availability Report - NGL'!O:O,'Availability Report - NGL'!$G:$G,'Availability Summary'!$B21,'Availability Report - NGL'!$D:$D,"Active") | K21: =AVERAGEIFS('Availability Report - NGL'!P:P,'Availability Report - NGL'!$G:$G,'Availability Summary'!$B21,'Availability Report - NGL'!$D:$D,"Active") | L21: =AVERAGEIFS('Availability Report - NGL'!Q:Q,'Availability Report - NGL'!$G:$G,'Availability Summary'!$B21,'Availability Report - NGL'!$D:$D,"Active") | M21: =AVERAGEIFS('Availability Report - NGL'!R:R,'Availability Report - NGL'!$G:$G,'Availability Summary'!$B21,'Availability Report - NGL'!$D:$D,"Active") | N21: =AVERAGEIFS('Availability Report - NGL'!S:S,'Availability Report - NGL'!$G:$G,'Availability Summary'!$B21,'Availability Report - NGL'!$D:$D,"Active") | O21: =AVERAGEIFS('Availability Report - NGL'!T:T,'Availability Report - NGL'!$G:$G,'Availability Summary'!$B21,'Availability Report - NGL'!$D:$D,"Active") | Q21: =AVERAGE(N21:O21) | R21: =1-Q21 | T21: =+SUMIFS('Availability Report - NGL'!#REF!,'Availability Report - NGL'!$G:$G,'Availability Summary'!$B21,'Availability Report - NGL'!$D:$D,"Active") | V21: =+SUMIFS('Availability Report - NGL'!#REF!,'Availability Report - NGL'!$G:$G,'Availability Summary'!$B21,'Availability Report - NGL'!$D:$D,"Active")
B22: Renewable and Engineering | C22: =COUNTIFS('Availability Report - NGL'!$G:$G,'Availability Summary'!$B22,'Availability Report - NGL'!$D:$D,"Active") | D22: =AVERAGEIFS('Availability Report - NGL'!I:I,'Availability Report - NGL'!$G:$G,'Availability Summary'!$B22,'Availability Report - NGL'!$D:$D,"Active") | E22: =AVERAGEIFS('Availability Report - NGL'!J:J,'Availability Report - NGL'!$G:$G,'Availability Summary'!$B22,'Availability Report - NGL'!$D:$D,"Active") | F22: =AVERAGEIFS('Availability Report - NGL'!K:K,'Availability Report - NGL'!$G:$G,'Availability Summary'!$B22,'Availability Report - NGL'!$D:$D,"Active") | G22: =AVERAGEIFS('Availability Report - NGL'!L:L,'Availability Report - NGL'!$G:$G,'Availability Summary'!$B22,'Availability Report - NGL'!$D:$D,"Active") | H22: =AVERAGEIFS('Availability Report - NGL'!M:M,'Availability Report - NGL'!$G:$G,'Availability Summary'!$B22,'Availability Report - NGL'!$D:$D,"Active") | I22: =AVERAGEIFS('Availability Report - NGL'!N:N,'Availability Report - NGL'!$G:$G,'Availability Summary'!$B22,'Availability Report - NGL'!$D:$D,"Active") | J22: =AVERAGEIFS('Availability Report - NGL'!O:O,'Availability Report - NGL'!$G:$G,'Availability Summary'!$B22,'Availability Report - NGL'!$D:$D,"Active") | K22: =AVERAGEIFS('Availability Report - NGL'!P:P,'Availability Report - NGL'!$G:$G,'Availability Summary'!$B22,'Availability Report - NGL'!$D:$D,"Active") | L22: =AVERAGEIFS('Availability Report - NGL'!Q:Q,'Availability Report - NGL'!$G:$G,'Availability Summary'!$B22,'Availability Report - NGL'!$D:$D,"Active") | M22: =AVERAGEIFS('Availability Report - NGL'!R:R,'Availability Report - NGL'!$G:$G,'Availability Summary'!$B22,'Availability Report - NGL'!$D:$D,"Active") | N22: =AVERAGEIFS('Availability Report - NGL'!S:S,'Availability Report - NGL'!$G:$G,'Availability Summary'!$B22,'Availability Report - NGL'!$D:$D,"Active") | O22: =AVERAGEIFS('Availability Report - NGL'!T:T,'Availability Report - NGL'!$G:$G,'Availability Summary'!$B22,'Availability Report - NGL'!$D:$D,"Active") | Q22: =AVERAGE(N22:O22) | R22: =1-Q22 | T22: =+SUMIFS('Availability Report - NGL'!#REF!,'Availability Report - NGL'!$G:$G,'Availability Summary'!$B22,'Availability Report - NGL'!$D:$D,"Active") | V22: =+SUMIFS('Availability Report - NGL'!#REF!,'Availability Report - NGL'!$G:$G,'Availability Summary'!$B22,'Availability Report - NGL'!$D:$D,"Active")
B23: Growth | C23: =COUNTIFS('Availability Report - NGL'!$G:$G,'Availability Summary'!$B23,'Availability Report - NGL'!$D:$D,"Active") | D23: =AVERAGEIFS('Availability Report - NGL'!I:I,'Availability Report - NGL'!$G:$G,'Availability Summary'!$B23,'Availability Report - NGL'!$D:$D,"Active") | E23: =AVERAGEIFS('Availability Report - NGL'!J:J,'Availability Report - NGL'!$G:$G,'Availability Summary'!$B23,'Availability Report - NGL'!$D:$D,"Active") | F23: =AVERAGEIFS('Availability Report - NGL'!K:K,'Availability Report - NGL'!$G:$G,'Availability Summary'!$B23,'Availability Report - NGL'!$D:$D,"Active") | G23: =AVERAGEIFS('Availability Report - NGL'!L:L,'Availability Report - NGL'!$G:$G,'Availability Summary'!$B23,'Availability Report - NGL'!$D:$D,"Active") | H23: =AVERAGEIFS('Availability Report - NGL'!M:M,'Availability Report - NGL'!$G:$G,'Availability Summary'!$B23,'Availability Report - NGL'!$D:$D,"Active") | I23: =AVERAGEIFS('Availability Report - NGL'!N:N,'Availability Report - NGL'!$G:$G,'Availability Summary'!$B23,'Availability Report - NGL'!$D:$D,"Active") | J23: =AVERAGEIFS('Availability Report - NGL'!O:O,'Availability Report - NGL'!$G:$G,'Availability Summary'!$B23,'Availability Report - NGL'!$D:$D,"Active") | K23: =AVERAGEIFS('Availability Report - NGL'!P:P,'Availability Report - NGL'!$G:$G,'Availability Summary'!$B23,'Availability Report - NGL'!$D:$D,"Active") | L23: =AVERAGEIFS('Availability Report - NGL'!Q:Q,'Availability Report - NGL'!$G:$G,'Availability Summary'!$B23,'Availability Report - NGL'!$D:$D,"Active") | M23: =AVERAGEIFS('Availability Report - NGL'!R:R,'Availability Report - NGL'!$G:$G,'Availability Summary'!$B23,'Availability Report - NGL'!$D:$D,"Active") | N23: =AVERAGEIFS('Availability Report - NGL'!S:S,'Availability Report - NGL'!$G:$G,'Availability Summary'!$B23,'Availability Report - NGL'!$D:$D,"Active") | O23: =AVERAGEIFS('Availability Report - NGL'!T:T,'Availability Report - NGL'!$G:$G,'Availability Summary'!$B23,'Availability Report - NGL'!$D:$D,"Active") | Q23: =AVERAGE(N23:O23) | R23: =1-Q23 | T23: =+SUMIFS('Availability Report - NGL'!#REF!,'Availability Report - NGL'!$G:$G,'Availability Summary'!$B23,'Availability Report - NGL'!$D:$D,"Active") | V23: =+SUMIFS('Availability Report - NGL'!#REF!,'Availability Report - NGL'!$G:$G,'Availability Summary'!$B23,'Availability Report - NGL'!$D:$D,"Active")
B24: GCC - Hyderabad | C24: =COUNTIFS('Availability Report - NGL'!$G:$G,'Availability Summary'!$B24,'Availability Report - NGL'!$D:$D,"Active") | D24: =AVERAGEIFS('Availability Report - NGL'!I:I,'Availability Report - NGL'!$G:$G,'Availability Summary'!$B24,'Availability Report - NGL'!$D:$D,"Active") | E24: =AVERAGEIFS('Availability Report - NGL'!J:J,'Availability Report - NGL'!$G:$G,'Availability Summary'!$B24,'Availability Report - NGL'!$D:$D,"Active") | F24: =AVERAGEIFS('Availability Report - NGL'!K:K,'Availability Report - NGL'!$G:$G,'Availability Summary'!$B24,'Availability Report - NGL'!$D:$D,"Active") | G24: =AVERAGEIFS('Availability Report - NGL'!L:L,'Availability Report - NGL'!$G:$G,'Availability Summary'!$B24,'Availability Report - NGL'!$D:$D,"Active") | H24: =AVERAGEIFS('Availability Report - NGL'!M:M,'Availability Report - NGL'!$G:$G,'Availability Summary'!$B24,'Availability Report - NGL'!$D:$D,"Active") | I24: =AVERAGEIFS('Availability Report - NGL'!N:N,'Availability Report - NGL'!$G:$G,'Availability Summary'!$B24,'Availability Report - NGL'!$D:$D,"Active") | J24: =AVERAGEIFS('Availability Report - NGL'!O:O,'Availability Report - NGL'!$G:$G,'Availability Summary'!$B24,'Availability Report - NGL'!$D:$D,"Active") | K24: =AVERAGEIFS('Availability Report - NGL'!P:P,'Availability Report - NGL'!$G:$G,'Availability Summary'!$B24,'Availability Report - NGL'!$D:$D,"Active") | L24: =AVERAGEIFS('Availability Report - NGL'!Q:Q,'Availability Report - NGL'!$G:$G,'Availability Summary'!$B24,'Availability Report - NGL'!$D:$D,"Active") | M24: =AVERAGEIFS('Availability Report - NGL'!R:R,'Availability Report - NGL'!$G:$G,'Availability Summary'!$B24,'Availability Report - NGL'!$D:$D,"Active") | N24: =AVERAGEIFS('Availability Report - NGL'!S:S,'Availability Report - NGL'!$G:$G,'Availability Summary'!$B24,'Availability Report - NGL'!$D:$D,"Active") | O24: =AVERAGEIFS('Availability Report - NGL'!T:T,'Availability Report - NGL'!$G:$G,'Availability Summary'!$B24,'Availability Report - NGL'!$D:$D,"Active") | Q24: =AVERAGE(N24:O24) | R24: =1-Q24 | T24: =+SUMIFS('Availability Report - NGL'!#REF!,'Availability Report - NGL'!$G:$G,'Availability Summary'!$B24,'Availability Report - NGL'!$D:$D,"Active") | V24: =+SUMIFS('Availability Report - NGL'!#REF!,'Availability Report - NGL'!$G:$G,'Availability Summary'!$B24,'Availability Report - NGL'!$D:$D,"Active")
B25: Strategic Delivery | C25: =COUNTIFS('Availability Report - NGL'!$G:$G,'Availability Summary'!$B25,'Availability Report - NGL'!$D:$D,"Active") | D25: =AVERAGEIFS('Availability Report - NGL'!I:I,'Availability Report - NGL'!$G:$G,'Availability Summary'!$B25,'Availability Report - NGL'!$D:$D,"Active") | E25: =AVERAGEIFS('Availability Report - NGL'!J:J,'Availability Report - NGL'!$G:$G,'Availability Summary'!$B25,'Availability Report - NGL'!$D:$D,"Active") | F25: =AVERAGEIFS('Availability Report - NGL'!K:K,'Availability Report - NGL'!$G:$G,'Availability Summary'!$B25,'Availability Report - NGL'!$D:$D,"Active") | G25: =AVERAGEIFS('Availability Report - NGL'!L:L,'Availability Report - NGL'!$G:$G,'Availability Summary'!$B25,'Availability Report - NGL'!$D:$D,"Active") | H25: =AVERAGEIFS('Availability Report - NGL'!M:M,'Availability Report - NGL'!$G:$G,'Availability Summary'!$B25,'Availability Report - NGL'!$D:$D,"Active") | I25: =AVERAGEIFS('Availability Report - NGL'!N:N,'Availability Report - NGL'!$G:$G,'Availability Summary'!$B25,'Availability Report - NGL'!$D:$D,"Active") | J25: =AVERAGEIFS('Availability Report - NGL'!O:O,'Availability Report - NGL'!$G:$G,'Availability Summary'!$B25,'Availability Report - NGL'!$D:$D,"Active") | K25: =AVERAGEIFS('Availability Report - NGL'!P:P,'Availability Report - NGL'!$G:$G,'Availability Summary'!$B25,'Availability Report - NGL'!$D:$D,"Active") | L25: =AVERAGEIFS('Availability Report - NGL'!Q:Q,'Availability Report - NGL'!$G:$G,'Availability Summary'!$B25,'Availability Report - NGL'!$D:$D,"Active") | M25: =AVERAGEIFS('Availability Report - NGL'!R:R,'Availability Report - NGL'!$G:$G,'Availability Summary'!$B25,'Availability Report - NGL'!$D:$D,"Active") | N25: =AVERAGEIFS('Availability Report - NGL'!S:S,'Availability Report - NGL'!$G:$G,'Availability Summary'!$B25,'Availability Report - NGL'!$D:$D,"Active") | O25: =AVERAGEIFS('Availability Report - NGL'!T:T,'Availability Report - NGL'!$G:$G,'Availability Summary'!$B25,'Availability Report - NGL'!$D:$D,"Active") | Q25: =AVERAGE(N25:O25) | R25: =1-Q25 | T25: =+SUMIFS('Availability Report - NGL'!#REF!,'Availability Report - NGL'!$G:$G,'Availability Summary'!$B25,'Availability Report - NGL'!$D:$D,"Active") | V25: =+SUMIFS('Availability Report - NGL'!#REF!,'Availability Report - NGL'!$G:$G,'Availability Summary'!$B25,'Availability Report - NGL'!$D:$D,"Active")
C26: =SUM(C19:C25) | T26: =SUM(T19:T25) | V26: =SUM(V19:V25)
Q27: Feb'26 to Mar'26
B28: Sub Practice | C28: Active Resources | D28: 45748 | E28: 45778 | F28: 45809 | G28: 45839 | H28: 45870 | I28: 45901 | J28: 45931 | K28: 45962 | L28: 45992 | M28: 46023 | N28: 46054 | O28: 46082 | Q28: Avg Avialability | R28: Avg Billability | T28: Non Billable cost from April'25 to March '26 | V28: Non Billable cost from Jan'26 to March '26
B29: OT | C29: =COUNTIFS('Availability Report - NGL'!$H:$H,'Availability Summary'!$B29,'Availability Report - NGL'!$D:$D,"Active") | D29: =IFERROR(AVERAGEIFS('Availability Report - NGL'!I:I,'Availability Report - NGL'!$H:$H,'Availability Summary'!$B29,'Availability Report - NGL'!$D:$D,"Active"),0) | E29: =IFERROR(AVERAGEIFS('Availability Report - NGL'!J:J,'Availability Report - NGL'!$H:$H,'Availability Summary'!$B29,'Availability Report - NGL'!$D:$D,"Active"),0) | F29: =IFERROR(AVERAGEIFS('Availability Report - NGL'!K:K,'Availability Report - NGL'!$H:$H,'Availability Summary'!$B29,'Availability Report - NGL'!$D:$D,"Active"),0) | G29: =IFERROR(AVERAGEIFS('Availability Report - NGL'!L:L,'Availability Report - NGL'!$H:$H,'Availability Summary'!$B29,'Availability Report - NGL'!$D:$D,"Active"),0) | H29: =IFERROR(AVERAGEIFS('Availability Report - NGL'!M:M,'Availability Report - NGL'!$H:$H,'Availability Summary'!$B29,'Availability Report - NGL'!$D:$D,"Active"),0) | I29: =IFERROR(AVERAGEIFS('Availability Report - NGL'!N:N,'Availability Report - NGL'!$H:$H,'Availability Summary'!$B29,'Availability Report - NGL'!$D:$D,"Active"),0) | J29: =IFERROR(AVERAGEIFS('Availability Report - NGL'!O:O,'Availability Report - NGL'!$H:$H,'Availability Summary'!$B29,'Availability Report - NGL'!$D:$D,"Active"),0) | K29: =IFERROR(AVERAGEIFS('Availability Report - NGL'!P:P,'Availability Report - NGL'!$H:$H,'Availability Summary'!$B29,'Availability Report - NGL'!$D:$D,"Active"),0) | L29: =IFERROR(AVERAGEIFS('Availability Report - NGL'!Q:Q,'Availability Report - NGL'!$H:$H,'Availability Summary'!$B29,'Availability Report - NGL'!$D:$D,"Active"),0) | M29: =IFERROR(AVERAGEIFS('Availability Report - NGL'!R:R,'Availability Report - NGL'!$H:$H,'Availability Summary'!$B29,'Availability Report - NGL'!$D:$D,"Active"),0) | N29: =IFERROR(AVERAGEIFS('Availability Report - NGL'!S:S,'Availability Report - NGL'!$H:$H,'Availability Summary'!$B29,'Availability Report - NGL'!$D:$D,"Active"),0) | O29: =IFERROR(AVERAGEIFS('Availability Report - NGL'!T:T,'Availability Report - NGL'!$H:$H,'Availability Summary'!$B29,'Availability Report - NGL'!$D:$D,"Active"),0) | Q29: =AVERAGE(N29:O29) | R29: =1-Q29 | T29: =+SUMIFS('Availability Report - NGL'!#REF!,'Availability Report - NGL'!$H:$H,'Availability Summary'!$B29,'Availability Report - NGL'!$D:$D,"Active") | V29: =+SUMIFS('Availability Report - NGL'!#REF!,'Availability Report - NGL'!$H:$H,'Availability Summary'!$B29,'Availability Report - NGL'!$D:$D,"Active")
B30: Digital Solutions | C30: =COUNTIFS('Availability Report - NGL'!$H:$H,'Availability Summary'!$B30,'Availability Report - NGL'!$D:$D,"Active") | D30: =IFERROR(AVERAGEIFS('Availability Report - NGL'!I:I,'Availability Report - NGL'!$H:$H,'Availability Summary'!$B30,'Availability Report - NGL'!$D:$D,"Active"),0) | E30: =IFERROR(AVERAGEIFS('Availability Report - NGL'!J:J,'Availability Report - NGL'!$H:$H,'Availability Summary'!$B30,'Availability Report - NGL'!$D:$D,"Active"),0) | F30: =IFERROR(AVERAGEIFS('Availability Report - NGL'!K:K,'Availability Report - NGL'!$H:$H,'Availability Summary'!$B30,'Availability Report - NGL'!$D:$D,"Active"),0) | G30: =IFERROR(AVERAGEIFS('Availability Report - NGL'!L:L,'Availability Report - NGL'!$H:$H,'Availability Summary'!$B30,'Availability Report - NGL'!$D:$D,"Active"),0) | H30: =IFERROR(AVERAGEIFS('Availability Report - NGL'!M:M,'Availability Report - NGL'!$H:$H,'Availability Summary'!$B30,'Availability Report - NGL'!$D:$D,"Active"),0) | I30: =IFERROR(AVERAGEIFS('Availability Report - NGL'!N:N,'Availability Report - NGL'!$H:$H,'Availability Summary'!$B30,'Availability Report - NGL'!$D:$D,"Active"),0) | J30: =IFERROR(AVERAGEIFS('Availability Report - NGL'!O:O,'Availability Report - NGL'!$H:$H,'Availability Summary'!$B30,'Availability Report - NGL'!$D:$D,"Active"),0) | K30: =IFERROR(AVERAGEIFS('Availability Report - NGL'!P:P,'Availability Report - NGL'!$H:$H,'Availability Summary'!$B30,'Availability Report - NGL'!$D:$D,"Active"),0) | L30: =IFERROR(AVERAGEIFS('Availability Report - NGL'!Q:Q,'Availability Report - NGL'!$H:$H,'Availability Summary'!$B30,'Availability Report - NGL'!$D:$D,"Active"),0) | M30: =IFERROR(AVERAGEIFS('Availability Report - NGL'!R:R,'Availability Report - NGL'!$H:$H,'Availability Summary'!$B30,'Availability Report - NGL'!$D:$D,"Active"),0) | N30: =IFERROR(AVERAGEIFS('Availability Report - NGL'!S:S,'Availability Report - NGL'!$H:$H,'Availability Summary'!$B30,'Availability Report - NGL'!$D:$D,"Active"),0) | O30: =IFERROR(AVERAGEIFS('Availability Report - NGL'!T:T,'Availability Report - NGL'!$H:$H,'Availability Summary'!$B30,'Availability Report - NGL'!$D:$D,"Active"),0) | Q30: =AVERAGE(N30:O30) | R30: =1-Q30 | T30: =+SUMIFS('Availability Report - NGL'!#REF!,'Availability Report - NGL'!$H:$H,'Availability Summary'!$B30,'Availability Report - NGL'!$D:$D,"Active") | V30: =+SUMIFS('Availability Report - NGL'!#REF!,'Availability Report - NGL'!$H:$H,'Availability Summary'!$B30,'Availability Report - NGL'!$D:$D,"Active")
B31: Platform Engineering | C31: =COUNTIFS('Availability Report - NGL'!$H:$H,'Availability Summary'!$B31,'Availability Report - NGL'!$D:$D,"Active") | D31: =IFERROR(AVERAGEIFS('Availability Report - NGL'!I:I,'Availability Report - NGL'!$H:$H,'Availability Summary'!$B31,'Availability Report - NGL'!$D:$D,"Active"),0) | E31: =IFERROR(AVERAGEIFS('Availability Report - NGL'!J:J,'Availability Report - NGL'!$H:$H,'Availability Summary'!$B31,'Availability Report - NGL'!$D:$D,"Active"),0) | F31: =IFERROR(AVERAGEIFS('Availability Report - NGL'!K:K,'Availability Report - NGL'!$H:$H,'Availability Summary'!$B31,'Availability Report - NGL'!$D:$D,"Active"),0) | G31: =IFERROR(AVERAGEIFS('Availability Report - NGL'!L:L,'Availability Report - NGL'!$H:$H,'Availability Summary'!$B31,'Availability Report - NGL'!$D:$D,"Active"),0) | H31: =IFERROR(AVERAGEIFS('Availability Report - NGL'!M:M,'Availability Report - NGL'!$H:$H,'Availability Summary'!$B31,'Availability Report - NGL'!$D:$D,"Active"),0) | I31: =IFERROR(AVERAGEIFS('Availability Report - NGL'!N:N,'Availability Report - NGL'!$H:$H,'Availability Summary'!$B31,'Availability Report - NGL'!$D:$D,"Active"),0) | J31: =IFERROR(AVERAGEIFS('Availability Report - NGL'!O:O,'Availability Report - NGL'!$H:$H,'Availability Summary'!$B31,'Availability Report - NGL'!$D:$D,"Active"),0) | K31: =IFERROR(AVERAGEIFS('Availability Report - NGL'!P:P,'Availability Report - NGL'!$H:$H,'Availability Summary'!$B31,'Availability Report - NGL'!$D:$D,"Active"),0) | L31: =IFERROR(AVERAGEIFS('Availability Report - NGL'!Q:Q,'Availability Report - NGL'!$H:$H,'Availability Summary'!$B31,'Availability Report - NGL'!$D:$D,"Active"),0) | M31: =IFERROR(AVERAGEIFS('Availability Report - NGL'!R:R,'Availability Report - NGL'!$H:$H,'Availability Summary'!$B31,'Availability Report - NGL'!$D:$D,"Active"),0) | N31: =IFERROR(AVERAGEIFS('Availability Report - NGL'!S:S,'Availability Report - NGL'!$H:$H,'Availability Summary'!$B31,'Availability Report - NGL'!$D:$D,"Active"),0) | O31: =IFERROR(AVERAGEIFS('Availability Report - NGL'!T:T,'Availability Report - NGL'!$H:$H,'Availability Summary'!$B31,'Availability Report - NGL'!$D:$D,"Active"),0) | Q31: =AVERAGE(N31:O31) | R31: =1-Q31 | T31: =+SUMIFS('Availability Report - NGL'!#REF!,'Availability Report - NGL'!$H:$H,'Availability Summary'!$B31,'Availability Report - NGL'!$D:$D,"Active") | V31: =+SUMIFS('Availability Report - NGL'!#REF!,'Availability Report - NGL'!$H:$H,'Availability Summary'!$B31,'Availability Report - NGL'!$D:$D,"Active")
B32: Project & Buiness Analysis | C32: =COUNTIFS('Availability Report - NGL'!$H:$H,'Availability Summary'!$B32,'Availability Report - NGL'!$D:$D,"Active") | D32: =IFERROR(AVERAGEIFS('Availability Report - NGL'!I:I,'Availability Report - NGL'!$H:$H,'Availability Summary'!$B32,'Availability Report - NGL'!$D:$D,"Active"),0) | E32: =IFERROR(AVERAGEIFS('Availability Report - NGL'!J:J,'Availability Report - NGL'!$H:$H,'Availability Summary'!$B32,'Availability Report - NGL'!$D:$D,"Active"),0) | F32: =IFERROR(AVERAGEIFS('Availability Report - NGL'!K:K,'Availability Report - NGL'!$H:$H,'Availability Summary'!$B32,'Availability Report - NGL'!$D:$D,"Active"),0) | G32: =IFERROR(AVERAGEIFS('Availability Report - NGL'!L:L,'Availability Report - NGL'!$H:$H,'Availability Summary'!$B32,'Availability Report - NGL'!$D:$D,"Active"),0) | H32: =IFERROR(AVERAGEIFS('Availability Report - NGL'!M:M,'Availability Report - NGL'!$H:$H,'Availability Summary'!$B32,'Availability Report - NGL'!$D:$D,"Active"),0) | I32: =IFERROR(AVERAGEIFS('Availability Report - NGL'!N:N,'Availability Report - NGL'!$H:$H,'Availability Summary'!$B32,'Availability Report - NGL'!$D:$D,"Active"),0) | J32: =IFERROR(AVERAGEIFS('Availability Report - NGL'!O:O,'Availability Report - NGL'!$H:$H,'Availability Summary'!$B32,'Availability Report - NGL'!$D:$D,"Active"),0) | K32: =IFERROR(AVERAGEIFS('Availability Report - NGL'!P:P,'Availability Report - NGL'!$H:$H,'Availability Summary'!$B32,'Availability Report - NGL'!$D:$D,"Active"),0) | L32: =IFERROR(AVERAGEIFS('Availability Report - NGL'!Q:Q,'Availability Report - NGL'!$H:$H,'Availability Summary'!$B32,'Availability Report - NGL'!$D:$D,"Active"),0) | M32: =IFERROR(AVERAGEIFS('Availability Report - NGL'!R:R,'Availability Report - NGL'!$H:$H,'Availability Summary'!$B32,'Availability Report - NGL'!$D:$D,"Active"),0) | N32: =IFERROR(AVERAGEIFS('Availability Report - NGL'!S:S,'Availability Report - NGL'!$H:$H,'Availability Summary'!$B32,'Availability Report - NGL'!$D:$D,"Active"),0) | O32: =IFERROR(AVERAGEIFS('Availability Report - NGL'!T:T,'Availability Report - NGL'!$H:$H,'Availability Summary'!$B32,'Availability Report - NGL'!$D:$D,"Active"),0) | Q32: =AVERAGE(N32:O32) | R32: =1-Q32 | T32: =+SUMIFS('Availability Report - NGL'!#REF!,'Availability Report - NGL'!$H:$H,'Availability Summary'!$B32,'Availability Report - NGL'!$D:$D,"Active") | V32: =+SUMIFS('Availability Report - NGL'!#REF!,'Availability Report - NGL'!$H:$H,'Availability Summary'!$B32,'Availability Report - NGL'!$D:$D,"Active")
B33: AI and Analytics | C33: =COUNTIFS('Availability Report - NGL'!$H:$H,'Availability Summary'!$B33,'Availability Report - NGL'!$D:$D,"Active") | D33: =IFERROR(AVERAGEIFS('Availability Report - NGL'!I:I,'Availability Report - NGL'!$H:$H,'Availability Summary'!$B33,'Availability Report - NGL'!$D:$D,"Active"),0) | E33: =IFERROR(AVERAGEIFS('Availability Report - NGL'!J:J,'Availability Report - NGL'!$H:$H,'Availability Summary'!$B33,'Availability Report - NGL'!$D:$D,"Active"),0) | F33: =IFERROR(AVERAGEIFS('Availability Report - NGL'!K:K,'Availability Report - NGL'!$H:$H,'Availability Summary'!$B33,'Availability Report - NGL'!$D:$D,"Active"),0) | G33: =IFERROR(AVERAGEIFS('Availability Report - NGL'!L:L,'Availability Report - NGL'!$H:$H,'Availability Summary'!$B33,'Availability Report - NGL'!$D:$D,"Active"),0) | H33: =IFERROR(AVERAGEIFS('Availability Report - NGL'!M:M,'Availability Report - NGL'!$H:$H,'Availability Summary'!$B33,'Availability Report - NGL'!$D:$D,"Active"),0) | I33: =IFERROR(AVERAGEIFS('Availability Report - NGL'!N:N,'Availability Report - NGL'!$H:$H,'Availability Summary'!$B33,'Availability Report - NGL'!$D:$D,"Active"),0) | J33: =IFERROR(AVERAGEIFS('Availability Report - NGL'!O:O,'Availability Report - NGL'!$H:$H,'Availability Summary'!$B33,'Availability Report - NGL'!$D:$D,"Active"),0) | K33: =IFERROR(AVERAGEIFS('Availability Report - NGL'!P:P,'Availability Report - NGL'!$H:$H,'Availability Summary'!$B33,'Availability Report - NGL'!$D:$D,"Active"),0) | L33: =IFERROR(AVERAGEIFS('Availability Report - NGL'!Q:Q,'Availability Report - NGL'!$H:$H,'Availability Summary'!$B33,'Availability Report - NGL'!$D:$D,"Active"),0) | M33: =IFERROR(AVERAGEIFS('Availability Report - NGL'!R:R,'Availability Report - NGL'!$H:$H,'Availability Summary'!$B33,'Availability Report - NGL'!$D:$D,"Active"),0) | N33: =IFERROR(AVERAGEIFS('Availability Report - NGL'!S:S,'Availability Report - NGL'!$H:$H,'Availability Summary'!$B33,'Availability Report - NGL'!$D:$D,"Active"),0) | O33: =IFERROR(AVERAGEIFS('Availability Report - NGL'!T:T,'Availability Report - NGL'!$H:$H,'Availability Summary'!$B33,'Availability Report - NGL'!$D:$D,"Active"),0) | Q33: =AVERAGE(N33:O33) | R33: =1-Q33 | T33: =+SUMIFS('Availability Report - NGL'!#REF!,'Availability Report - NGL'!$H:$H,'Availability Summary'!$B33,'Availability Report - NGL'!$D:$D,"Active") | V33: =+SUMIFS('Availability Report - NGL'!#REF!,'Availability Report - NGL'!$H:$H,'Availability Summary'!$B33,'Availability Report - NGL'!$D:$D,"Active")
B34: Renewable Advisory | C34: =COUNTIFS('Availability Report - NGL'!$H:$H,'Availability Summary'!$B34,'Availability Report - NGL'!$D:$D,"Active") | D34: =IFERROR(AVERAGEIFS('Availability Report - NGL'!I:I,'Availability Report - NGL'!$H:$H,'Availability Summary'!$B34,'Availability Report - NGL'!$D:$D,"Active"),0) | E34: =IFERROR(AVERAGEIFS('Availability Report - NGL'!J:J,'Availability Report - NGL'!$H:$H,'Availability Summary'!$B34,'Availability Report - NGL'!$D:$D,"Active"),0) | F34: =IFERROR(AVERAGEIFS('Availability Report - NGL'!K:K,'Availability Report - NGL'!$H:$H,'Availability Summary'!$B34,'Availability Report - NGL'!$D:$D,"Active"),0) | G34: =IFERROR(AVERAGEIFS('Availability Report - NGL'!L:L,'Availability Report - NGL'!$H:$H,'Availability Summary'!$B34,'Availability Report - NGL'!$D:$D,"Active"),0) | H34: =IFERROR(AVERAGEIFS('Availability Report - NGL'!M:M,'Availability Report - NGL'!$H:$H,'Availability Summary'!$B34,'Availability Report - NGL'!$D:$D,"Active"),0) | I34: =IFERROR(AVERAGEIFS('Availability Report - NGL'!N:N,'Availability Report - NGL'!$H:$H,'Availability Summary'!$B34,'Availability Report - NGL'!$D:$D,"Active"),0) | J34: =IFERROR(AVERAGEIFS('Availability Report - NGL'!O:O,'Availability Report - NGL'!$H:$H,'Availability Summary'!$B34,'Availability Report - NGL'!$D:$D,"Active"),0) | K34: =IFERROR(AVERAGEIFS('Availability Report - NGL'!P:P,'Availability Report - NGL'!$H:$H,'Availability Summary'!$B34,'Availability Report - NGL'!$D:$D,"Active"),0) | L34: =IFERROR(AVERAGEIFS('Availability Report - NGL'!Q:Q,'Availability Report - NGL'!$H:$H,'Availability Summary'!$B34,'Availability Report - NGL'!$D:$D,"Active"),0) | M34: =IFERROR(AVERAGEIFS('Availability Report - NGL'!R:R,'Availability Report - NGL'!$H:$H,'Availability Summary'!$B34,'Availability Report - NGL'!$D:$D,"Active"),0) | N34: =IFERROR(AVERAGEIFS('Availability Report - NGL'!S:S,'Availability Report - NGL'!$H:$H,'Availability Summary'!$B34,'Availability Report - NGL'!$D:$D,"Active"),0) | O34: =IFERROR(AVERAGEIFS('Availability Report - NGL'!T:T,'Availability Report - NGL'!$H:$H,'Availability Summary'!$B34,'Availability Report - NGL'!$D:$D,"Active"),0) | Q34: =AVERAGE(N34:O34) | R34: =1-Q34 | T34: =+SUMIFS('Availability Report - NGL'!#REF!,'Availability Report - NGL'!$H:$H,'Availability Summary'!$B34,'Availability Report - NGL'!$D:$D,"Active") | V34: =+SUMIFS('Availability Report - NGL'!#REF!,'Availability Report - NGL'!$H:$H,'Availability Summary'!$B34,'Availability Report - NGL'!$D:$D,"Active")
B35: SAP | C35: =COUNTIFS('Availability Report - NGL'!$H:$H,'Availability Summary'!$B35,'Availability Report - NGL'!$D:$D,"Active") | D35: =IFERROR(AVERAGEIFS('Availability Report - NGL'!I:I,'Availability Report - NGL'!$H:$H,'Availability Summary'!$B35,'Availability Report - NGL'!$D:$D,"Active"),0) | E35: =IFERROR(AVERAGEIFS('Availability Report - NGL'!J:J,'Availability Report - NGL'!$H:$H,'Availability Summary'!$B35,'Availability Report - NGL'!$D:$D,"Active"),0) | F35: =IFERROR(AVERAGEIFS('Availability Report - NGL'!K:K,'Availability Report - NGL'!$H:$H,'Availability Summary'!$B35,'Availability Report - NGL'!$D:$D,"Active"),0) | G35: =IFERROR(AVERAGEIFS('Availability Report - NGL'!L:L,'Availability Report - NGL'!$H:$H,'Availability Summary'!$B35,'Availability Report - NGL'!$D:$D,"Active"),0) | H35: =IFERROR(AVERAGEIFS('Availability Report - NGL'!M:M,'Availability Report - NGL'!$H:$H,'Availability Summary'!$B35,'Availability Report - NGL'!$D:$D,"Active"),0) | I35: =IFERROR(AVERAGEIFS('Availability Report - NGL'!N:N,'Availability Report - NGL'!$H:$H,'Availability Summary'!$B35,'Availability Report - NGL'!$D:$D,"Active"),0) | J35: =IFERROR(AVERAGEIFS('Availability Report - NGL'!O:O,'Availability Report - NGL'!$H:$H,'Availability Summary'!$B35,'Availability Report - NGL'!$D:$D,"Active"),0) | K35: =IFERROR(AVERAGEIFS('Availability Report - NGL'!P:P,'Availability Report - NGL'!$H:$H,'Availability Summary'!$B35,'Availability Report - NGL'!$D:$D,"Active"),0) | L35: =IFERROR(AVERAGEIFS('Availability Report - NGL'!Q:Q,'Availability Report - NGL'!$H:$H,'Availability Summary'!$B35,'Availability Report - NGL'!$D:$D,"Active"),0) | M35: =IFERROR(AVERAGEIFS('Availability Report - NGL'!R:R,'Availability Report - NGL'!$H:$H,'Availability Summary'!$B35,'Availability Report - NGL'!$D:$D,"Active"),0) | N35: =IFERROR(AVERAGEIFS('Availability Report - NGL'!S:S,'Availability Report - NGL'!$H:$H,'Availability Summary'!$B35,'Availability Report - NGL'!$D:$D,"Active"),0) | O35: =IFERROR(AVERAGEIFS('Availability Report - NGL'!T:T,'Availability Report - NGL'!$H:$H,'Availability Summary'!$B35,'Availability Report - NGL'!$D:$D,"Active"),0) | Q35: =AVERAGE(N35:O35) | R35: =1-Q35 | T35: =+SUMIFS('Availability Report - NGL'!#REF!,'Availability Report - NGL'!$H:$H,'Availability Summary'!$B35,'Availability Report - NGL'!$D:$D,"Active") | V35: =+SUMIFS('Availability Report - NGL'!#REF!,'Availability Report - NGL'!$H:$H,'Availability Summary'!$B35,'Availability Report - NGL'!$D:$D,"Active")
B36: Design Engineering | C36: =COUNTIFS('Availability Report - NGL'!$H:$H,'Availability Summary'!$B36,'Availability Report - NGL'!$D:$D,"Active") | D36: =IFERROR(AVERAGEIFS('Availability Report - NGL'!I:I,'Availability Report - NGL'!$H:$H,'Availability Summary'!$B36,'Availability Report - NGL'!$D:$D,"Active"),0) | E36: =IFERROR(AVERAGEIFS('Availability Report - NGL'!J:J,'Availability Report - NGL'!$H:$H,'Availability Summary'!$B36,'Availability Report - NGL'!$D:$D,"Active"),0) | F36: =IFERROR(AVERAGEIFS('Availability Report - NGL'!K:K,'Availability Report - NGL'!$H:$H,'Availability Summary'!$B36,'Availability Report - NGL'!$D:$D,"Active"),0) | G36: =IFERROR(AVERAGEIFS('Availability Report - NGL'!L:L,'Availability Report - NGL'!$H:$H,'Availability Summary'!$B36,'Availability Report - NGL'!$D:$D,"Active"),0) | H36: =IFERROR(AVERAGEIFS('Availability Report - NGL'!M:M,'Availability Report - NGL'!$H:$H,'Availability Summary'!$B36,'Availability Report - NGL'!$D:$D,"Active"),0) | I36: =IFERROR(AVERAGEIFS('Availability Report - NGL'!N:N,'Availability Report - NGL'!$H:$H,'Availability Summary'!$B36,'Availability Report - NGL'!$D:$D,"Active"),0) | J36: =IFERROR(AVERAGEIFS('Availability Report - NGL'!O:O,'Availability Report - NGL'!$H:$H,'Availability Summary'!$B36,'Availability Report - NGL'!$D:$D,"Active"),0) | K36: =IFERROR(AVERAGEIFS('Availability Report - NGL'!P:P,'Availability Report - NGL'!$H:$H,'Availability Summary'!$B36,'Availability Report - NGL'!$D:$D,"Active"),0) | L36: =IFERROR(AVERAGEIFS('Availability Report - NGL'!Q:Q,'Availability Report - NGL'!$H:$H,'Availability Summary'!$B36,'Availability Report - NGL'!$D:$D,"Active"),0) | M36: =IFERROR(AVERAGEIFS('Availability Report - NGL'!R:R,'Availability Report - NGL'!$H:$H,'Availability Summary'!$B36,'Availability Report - NGL'!$D:$D,"Active"),0) | N36: =IFERROR(AVERAGEIFS('Availability Report - NGL'!S:S,'Availability Report - NGL'!$H:$H,'Availability Summary'!$B36,'Availability Report - NGL'!$D:$D,"Active"),0) | O36: =IFERROR(AVERAGEIFS('Availability Report - NGL'!T:T,'Availability Report - NGL'!$H:$H,'Availability Summary'!$B36,'Availability Report - NGL'!$D:$D,"Active"),0) | Q36: =AVERAGE(N36:O36) | R36: =1-Q36 | T36: =+SUMIFS('Availability Report - NGL'!#REF!,'Availability Report - NGL'!$H:$H,'Availability Summary'!$B36,'Availability Report - NGL'!$D:$D,"Active") | V36: =+SUMIFS('Availability Report - NGL'!#REF!,'Availability Report - NGL'!$H:$H,'Availability Summary'!$B36,'Availability Report - NGL'!$D:$D,"Active")
B37: Growth | C37: =COUNTIFS('Availability Report - NGL'!$H:$H,'Availability Summary'!$B37,'Availability Report - NGL'!$D:$D,"Active") | D37: =IFERROR(AVERAGEIFS('Availability Report - NGL'!I:I,'Availability Report - NGL'!$H:$H,'Availability Summary'!$B37,'Availability Report - NGL'!$D:$D,"Active"),0) | E37: =IFERROR(AVERAGEIFS('Availability Report - NGL'!J:J,'Availability Report - NGL'!$H:$H,'Availability Summary'!$B37,'Availability Report - NGL'!$D:$D,"Active"),0) | F37: =IFERROR(AVERAGEIFS('Availability Report - NGL'!K:K,'Availability Report - NGL'!$H:$H,'Availability Summary'!$B37,'Availability Report - NGL'!$D:$D,"Active"),0) | G37: =IFERROR(AVERAGEIFS('Availability Report - NGL'!L:L,'Availability Report - NGL'!$H:$H,'Availability Summary'!$B37,'Availability Report - NGL'!$D:$D,"Active"),0) | H37: =IFERROR(AVERAGEIFS('Availability Report - NGL'!M:M,'Availability Report - NGL'!$H:$H,'Availability Summary'!$B37,'Availability Report - NGL'!$D:$D,"Active"),0) | I37: =IFERROR(AVERAGEIFS('Availability Report - NGL'!N:N,'Availability Report - NGL'!$H:$H,'Availability Summary'!$B37,'Availability Report - NGL'!$D:$D,"Active"),0) | J37: =IFERROR(AVERAGEIFS('Availability Report - NGL'!O:O,'Availability Report - NGL'!$H:$H,'Availability Summary'!$B37,'Availability Report - NGL'!$D:$D,"Active"),0) | K37: =IFERROR(AVERAGEIFS('Availability Report - NGL'!P:P,'Availability Report - NGL'!$H:$H,'Availability Summary'!$B37,'Availability Report - NGL'!$D:$D,"Active"),0) | L37: =IFERROR(AVERAGEIFS('Availability Report - NGL'!Q:Q,'Availability Report - NGL'!$H:$H,'Availability Summary'!$B37,'Availability Report - NGL'!$D:$D,"Active"),0) | M37: =IFERROR(AVERAGEIFS('Availability Report - NGL'!R:R,'Availability Report - NGL'!$H:$H,'Availability Summary'!$B37,'Availability Report - NGL'!$D:$D,"Active"),0) | N37: =IFERROR(AVERAGEIFS('Availability Report - NGL'!S:S,'Availability Report - NGL'!$H:$H,'Availability Summary'!$B37,'Availability Report - NGL'!$D:$D,"Active"),0) | O37: =IFERROR(AVERAGEIFS('Availability Report - NGL'!T:T,'Availability Report - NGL'!$H:$H,'Availability Summary'!$B37,'Availability Report - NGL'!$D:$D,"Active"),0) | Q37: =AVERAGE(N37:O37) | R37: =1-Q37 | T37: =+SUMIFS('Availability Report - NGL'!#REF!,'Availability Report - NGL'!$H:$H,'Availability Summary'!$B37,'Availability Report - NGL'!$D:$D,"Active") | V37: =+SUMIFS('Availability Report - NGL'!#REF!,'Availability Report - NGL'!$H:$H,'Availability Summary'!$B37,'Availability Report - NGL'!$D:$D,"Active")
B38: Managed Services | C38: =COUNTIFS('Availability Report - NGL'!$H:$H,'Availability Summary'!$B38,'Availability Report - NGL'!$D:$D,"Active") | D38: =IFERROR(AVERAGEIFS('Availability Report - NGL'!I:I,'Availability Report - NGL'!$H:$H,'Availability Summary'!$B38,'Availability Report - NGL'!$D:$D,"Active"),0) | E38: =IFERROR(AVERAGEIFS('Availability Report - NGL'!J:J,'Availability Report - NGL'!$H:$H,'Availability Summary'!$B38,'Availability Report - NGL'!$D:$D,"Active"),0) | F38: =IFERROR(AVERAGEIFS('Availability Report - NGL'!K:K,'Availability Report - NGL'!$H:$H,'Availability Summary'!$B38,'Availability Report - NGL'!$D:$D,"Active"),0) | G38: =IFERROR(AVERAGEIFS('Availability Report - NGL'!L:L,'Availability Report - NGL'!$H:$H,'Availability Summary'!$B38,'Availability Report - NGL'!$D:$D,"Active"),0) | H38: =IFERROR(AVERAGEIFS('Availability Report - NGL'!M:M,'Availability Report - NGL'!$H:$H,'Availability Summary'!$B38,'Availability Report - NGL'!$D:$D,"Active"),0) | I38: =IFERROR(AVERAGEIFS('Availability Report - NGL'!N:N,'Availability Report - NGL'!$H:$H,'Availability Summary'!$B38,'Availability Report - NGL'!$D:$D,"Active"),0) | J38: =IFERROR(AVERAGEIFS('Availability Report - NGL'!O:O,'Availability Report - NGL'!$H:$H,'Availability Summary'!$B38,'Availability Report - NGL'!$D:$D,"Active"),0) | K38: =IFERROR(AVERAGEIFS('Availability Report - NGL'!P:P,'Availability Report - NGL'!$H:$H,'Availability Summary'!$B38,'Availability Report - NGL'!$D:$D,"Active"),0) | L38: =IFERROR(AVERAGEIFS('Availability Report - NGL'!Q:Q,'Availability Report - NGL'!$H:$H,'Availability Summary'!$B38,'Availability Report - NGL'!$D:$D,"Active"),0) | M38: =IFERROR(AVERAGEIFS('Availability Report - NGL'!R:R,'Availability Report - NGL'!$H:$H,'Availability Summary'!$B38,'Availability Report - NGL'!$D:$D,"Active"),0) | N38: =IFERROR(AVERAGEIFS('Availability Report - NGL'!S:S,'Availability Report - NGL'!$H:$H,'Availability Summary'!$B38,'Availability Report - NGL'!$D:$D,"Active"),0) | O38: =IFERROR(AVERAGEIFS('Availability Report - NGL'!T:T,'Availability Report - NGL'!$H:$H,'Availability Summary'!$B38,'Availability Report - NGL'!$D:$D,"Active"),0) | Q38: =AVERAGE(N38:O38) | R38: =1-Q38 | T38: =+SUMIFS('Availability Report - NGL'!#REF!,'Availability Report - NGL'!$H:$H,'Availability Summary'!$B38,'Availability Report - NGL'!$D:$D,"Active") | V38: =+SUMIFS('Availability Report - NGL'!#REF!,'Availability Report - NGL'!$H:$H,'Availability Summary'!$B38,'Availability Report - NGL'!$D:$D,"Active")
B39: Asset & Intelligence | C39: =COUNTIFS('Availability Report - NGL'!$H:$H,'Availability Summary'!$B39,'Availability Report - NGL'!$D:$D,"Active") | D39: =IFERROR(AVERAGEIFS('Availability Report - NGL'!I:I,'Availability Report - NGL'!$H:$H,'Availability Summary'!$B39,'Availability Report - NGL'!$D:$D,"Active"),0) | E39: =IFERROR(AVERAGEIFS('Availability Report - NGL'!J:J,'Availability Report - NGL'!$H:$H,'Availability Summary'!$B39,'Availability Report - NGL'!$D:$D,"Active"),0) | F39: =IFERROR(AVERAGEIFS('Availability Report - NGL'!K:K,'Availability Report - NGL'!$H:$H,'Availability Summary'!$B39,'Availability Report - NGL'!$D:$D,"Active"),0) | G39: =IFERROR(AVERAGEIFS('Availability Report - NGL'!L:L,'Availability Report - NGL'!$H:$H,'Availability Summary'!$B39,'Availability Report - NGL'!$D:$D,"Active"),0) | H39: =IFERROR(AVERAGEIFS('Availability Report - NGL'!M:M,'Availability Report - NGL'!$H:$H,'Availability Summary'!$B39,'Availability Report - NGL'!$D:$D,"Active"),0) | I39: =IFERROR(AVERAGEIFS('Availability Report - NGL'!N:N,'Availability Report - NGL'!$H:$H,'Availability Summary'!$B39,'Availability Report - NGL'!$D:$D,"Active"),0) | J39: =IFERROR(AVERAGEIFS('Availability Report - NGL'!O:O,'Availability Report - NGL'!$H:$H,'Availability Summary'!$B39,'Availability Report - NGL'!$D:$D,"Active"),0) | K39: =IFERROR(AVERAGEIFS('Availability Report - NGL'!P:P,'Availability Report - NGL'!$H:$H,'Availability Summary'!$B39,'Availability Report - NGL'!$D:$D,"Active"),0) | L39: =IFERROR(AVERAGEIFS('Availability Report - NGL'!Q:Q,'Availability Report - NGL'!$H:$H,'Availability Summary'!$B39,'Availability Report - NGL'!$D:$D,"Active"),0) | M39: =IFERROR(AVERAGEIFS('Availability Report - NGL'!R:R,'Availability Report - NGL'!$H:$H,'Availability Summary'!$B39,'Availability Report - NGL'!$D:$D,"Active"),0) | N39: =IFERROR(AVERAGEIFS('Availability Report - NGL'!S:S,'Availability Report - NGL'!$H:$H,'Availability Summary'!$B39,'Availability Report - NGL'!$D:$D,"Active"),0) | O39: =IFERROR(AVERAGEIFS('Availability Report - NGL'!T:T,'Availability Report - NGL'!$H:$H,'Availability Summary'!$B39,'Availability Report - NGL'!$D:$D,"Active"),0) | Q39: =AVERAGE(N39:O39) | R39: =1-Q39 | T39: =+SUMIFS('Availability Report - NGL'!#REF!,'Availability Report - NGL'!$H:$H,'Availability Summary'!$B39,'Availability Report - NGL'!$D:$D,"Active") | V39: =+SUMIFS('Availability Report - NGL'!#REF!,'Availability Report - NGL'!$H:$H,'Availability Summary'!$B39,'Availability Report - NGL'!$D:$D,"Active")
B40: Testing & Assurance | C40: =COUNTIFS('Availability Report - NGL'!$H:$H,'Availability Summary'!$B40,'Availability Report - NGL'!$D:$D,"Active") | D40: =IFERROR(AVERAGEIFS('Availability Report - NGL'!I:I,'Availability Report - NGL'!$H:$H,'Availability Summary'!$B40,'Availability Report - NGL'!$D:$D,"Active"),0) | E40: =IFERROR(AVERAGEIFS('Availability Report - NGL'!J:J,'Availability Report - NGL'!$H:$H,'Availability Summary'!$B40,'Availability Report - NGL'!$D:$D,"Active"),0) | F40: =IFERROR(AVERAGEIFS('Availability Report - NGL'!K:K,'Availability Report - NGL'!$H:$H,'Availability Summary'!$B40,'Availability Report - NGL'!$D:$D,"Active"),0) | G40: =IFERROR(AVERAGEIFS('Availability Report - NGL'!L:L,'Availability Report - NGL'!$H:$H,'Availability Summary'!$B40,'Availability Report - NGL'!$D:$D,"Active"),0) | H40: =IFERROR(AVERAGEIFS('Availability Report - NGL'!M:M,'Availability Report - NGL'!$H:$H,'Availability Summary'!$B40,'Availability Report - NGL'!$D:$D,"Active"),0) | I40: =IFERROR(AVERAGEIFS('Availability Report - NGL'!N:N,'Availability Report - NGL'!$H:$H,'Availability Summary'!$B40,'Availability Report - NGL'!$D:$D,"Active"),0) | J40: =IFERROR(AVERAGEIFS('Availability Report - NGL'!O:O,'Availability Report - NGL'!$H:$H,'Availability Summary'!$B40,'Availability Report - NGL'!$D:$D,"Active"),0) | K40: =IFERROR(AVERAGEIFS('Availability Report - NGL'!P:P,'Availability Report - NGL'!$H:$H,'Availability Summary'!$B40,'Availability Report - NGL'!$D:$D,"Active"),0) | L40: =IFERROR(AVERAGEIFS('Availability Report - NGL'!Q:Q,'Availability Report - NGL'!$H:$H,'Availability Summary'!$B40,'Availability Report - NGL'!$D:$D,"Active"),0) | M40: =IFERROR(AVERAGEIFS('Availability Report - NGL'!R:R,'Availability Report - NGL'!$H:$H,'Availability Summary'!$B40,'Availability Report - NGL'!$D:$D,"Active"),0) | N40: =IFERROR(AVERAGEIFS('Availability Report - NGL'!S:S,'Availability Report - NGL'!$H:$H,'Availability Summary'!$B40,'Availability Report - NGL'!$D:$D,"Active"),0) | O40: =IFERROR(AVERAGEIFS('Availability Report - NGL'!T:T,'Availability Report - NGL'!$H:$H,'Availability Summary'!$B40,'Availability Report - NGL'!$D:$D,"Active"),0) | Q40: =AVERAGE(N40:O40) | R40: =1-Q40 | T40: =+SUMIFS('Availability Report - NGL'!#REF!,'Availability Report - NGL'!$H:$H,'Availability Summary'!$B40,'Availability Report - NGL'!$D:$D,"Active") | V40: =+SUMIFS('Availability Report - NGL'!#REF!,'Availability Report - NGL'!$H:$H,'Availability Summary'!$B40,'Availability Report - NGL'!$D:$D,"Active")
... B43: GCC - Hyderabad | C43: =COUNTIFS('Availability Report - NGL'!$H:$H,'Availability Summary'!$B43,'Availability Report - NGL'!$D:$D,"Active") | D43: =IFERROR(AVERAGEIFS('Availability Report - NGL'!I:I,'Availability Report - NGL'!$H:$H,'Availability Summary'!$B43,'Availability Report - NGL'!$D:$D,"Active"),0) | E43: =IFERROR(AVERAGEIFS('Availability Report - NGL'!J:J,'Availability Report - NGL'!$H:$H,'Availability Summary'!$B43,'Availability Report - NGL'!$D:$D,"Active"),0) | F43: =IFERROR(AVERAGEIFS('Availability Report - NGL'!K:K,'Availability Report - NGL'!$H:$H,'Availability Summary'!$B43,'Availability Report - NGL'!$D:$D,"Active"),0) | G43: =IFERROR(AVERAGEIFS('Availability Report - NGL'!L:L,'Availability Report - NGL'!$H:$H,'Availability Summary'!$B43,'Availability Report - NGL'!$D:$D,"Active"),0) | H43: =IFERROR(AVERAGEIFS('Availability Report - NGL'!M:M,'Availability Report - NGL'!$H:$H,'Availability Summary'!$B43,'Availability Report - NGL'!$D:$D,"Active"),0) | I43: =IFERROR(AVERAGEIFS('Availability Report - NGL'!N:N,'Availability Report - NGL'!$H:$H,'Availability Summary'!$B43,'Availability Report - NGL'!$D:$D,"Active"),0) | J43: =IFERROR(AVERAGEIFS('Availability Report - NGL'!O:O,'Availability Report - NGL'!$H:$H,'Availability Summary'!$B43,'Availability Report - NGL'!$D:$D,"Active"),0) | K43: =IFERROR(AVERAGEIFS('Availability Report - NGL'!P:P,'Availability Report - NGL'!$H:$H,'Availability Summary'!$B43,'Availability Report - NGL'!$D:$D,"Active"),0) | L43: =IFERROR(AVERAGEIFS('Availability Report - NGL'!Q:Q,'Availability Report - NGL'!$H:$H,'Availability Summary'!$B43,'Availability Report - NGL'!$D:$D,"Active"),0) | M43: =IFERROR(AVERAGEIFS('Availability Report - NGL'!R:R,'Availability Report - NGL'!$H:$H,'Availability Summary'!$B43,'Availability Report - NGL'!$D:$D,"Active"),0) | N43: =IFERROR(AVERAGEIFS('Availability Report - NGL'!S:S,'Availability Report - NGL'!$H:$H,'Availability Summary'!$B43,'Availability Report - NGL'!$D:$D,"Active"),0) | O43: =IFERROR(AVERAGEIFS('Availability Report - NGL'!T:T,'Availability Report - NGL'!$H:$H,'Availability Summary'!$B43,'Availability Report - NGL'!$D:$D,"Active"),0) | Q43: =AVERAGE(N43:O43) | R43: =1-Q43 | T43: =+SUMIFS('Availability Report - NGL'!#REF!,'Availability Report - NGL'!$H:$H,'Availability Summary'!$B43,'Availability Report - NGL'!$D:$D,"Active") | V43: =+SUMIFS('Availability Report - NGL'!#REF!,'Availability Report - NGL'!$H:$H,'Availability Summary'!$B43,'Availability Report - NGL'!$D:$D,"Active")
B44: Strategic Delivery | C44: =COUNTIFS('Availability Report - NGL'!$H:$H,'Availability Summary'!$B44,'Availability Report - NGL'!$D:$D,"Active") | D44: =IFERROR(AVERAGEIFS('Availability Report - NGL'!I:I,'Availability Report - NGL'!$H:$H,'Availability Summary'!$B44,'Availability Report - NGL'!$D:$D,"Active"),0) | E44: =IFERROR(AVERAGEIFS('Availability Report - NGL'!J:J,'Availability Report - NGL'!$H:$H,'Availability Summary'!$B44,'Availability Report - NGL'!$D:$D,"Active"),0) | F44: =IFERROR(AVERAGEIFS('Availability Report - NGL'!K:K,'Availability Report - NGL'!$H:$H,'Availability Summary'!$B44,'Availability Report - NGL'!$D:$D,"Active"),0) | G44: =IFERROR(AVERAGEIFS('Availability Report - NGL'!L:L,'Availability Report - NGL'!$H:$H,'Availability Summary'!$B44,'Availability Report - NGL'!$D:$D,"Active"),0) | H44: =IFERROR(AVERAGEIFS('Availability Report - NGL'!M:M,'Availability Report - NGL'!$H:$H,'Availability Summary'!$B44,'Availability Report - NGL'!$D:$D,"Active"),0) | I44: =IFERROR(AVERAGEIFS('Availability Report - NGL'!N:N,'Availability Report - NGL'!$H:$H,'Availability Summary'!$B44,'Availability Report - NGL'!$D:$D,"Active"),0) | J44: =IFERROR(AVERAGEIFS('Availability Report - NGL'!O:O,'Availability Report - NGL'!$H:$H,'Availability Summary'!$B44,'Availability Report - NGL'!$D:$D,"Active"),0) | K44: =IFERROR(AVERAGEIFS('Availability Report - NGL'!P:P,'Availability Report - NGL'!$H:$H,'Availability Summary'!$B44,'Availability Report - NGL'!$D:$D,"Active"),0) | L44: =IFERROR(AVERAGEIFS('Availability Report - NGL'!Q:Q,'Availability Report - NGL'!$H:$H,'Availability Summary'!$B44,'Availability Report - NGL'!$D:$D,"Active"),0) | M44: =IFERROR(AVERAGEIFS('Availability Report - NGL'!R:R,'Availability Report - NGL'!$H:$H,'Availability Summary'!$B44,'Availability Report - NGL'!$D:$D,"Active"),0) | N44: =IFERROR(AVERAGEIFS('Availability Report - NGL'!S:S,'Availability Report - NGL'!$H:$H,'Availability Summary'!$B44,'Availability Report - NGL'!$D:$D,"Active"),0) | O44: =IFERROR(AVERAGEIFS('Availability Report - NGL'!T:T,'Availability Report - NGL'!$H:$H,'Availability Summary'!$B44,'Availability Report - NGL'!$D:$D,"Active"),0) | Q44: =AVERAGE(N44:O44) | R44: =1-Q44
B45: GIS | C45: =COUNTIFS('Availability Report - NGL'!$H:$H,'Availability Summary'!$B45,'Availability Report - NGL'!$D:$D,"Active") | D45: =IFERROR(AVERAGEIFS('Availability Report - NGL'!I:I,'Availability Report - NGL'!$H:$H,'Availability Summary'!$B45,'Availability Report - NGL'!$D:$D,"Active"),0) | E45: =IFERROR(AVERAGEIFS('Availability Report - NGL'!J:J,'Availability Report - NGL'!$H:$H,'Availability Summary'!$B45,'Availability Report - NGL'!$D:$D,"Active"),0) | F45: =IFERROR(AVERAGEIFS('Availability Report - NGL'!K:K,'Availability Report - NGL'!$H:$H,'Availability Summary'!$B45,'Availability Report - NGL'!$D:$D,"Active"),0) | G45: =IFERROR(AVERAGEIFS('Availability Report - NGL'!L:L,'Availability Report - NGL'!$H:$H,'Availability Summary'!$B45,'Availability Report - NGL'!$D:$D,"Active"),0) | H45: =IFERROR(AVERAGEIFS('Availability Report - NGL'!M:M,'Availability Report - NGL'!$H:$H,'Availability Summary'!$B45,'Availability Report - NGL'!$D:$D,"Active"),0) | I45: =IFERROR(AVERAGEIFS('Availability Report - NGL'!N:N,'Availability Report - NGL'!$H:$H,'Availability Summary'!$B45,'Availability Report - NGL'!$D:$D,"Active"),0) | J45: =IFERROR(AVERAGEIFS('Availability Report - NGL'!O:O,'Availability Report - NGL'!$H:$H,'Availability Summary'!$B45,'Availability Report - NGL'!$D:$D,"Active"),0) | K45: =IFERROR(AVERAGEIFS('Availability Report - NGL'!P:P,'Availability Report - NGL'!$H:$H,'Availability Summary'!$B45,'Availability Report - NGL'!$D:$D,"Active"),0) | L45: =IFERROR(AVERAGEIFS('Availability Report - NGL'!Q:Q,'Availability Report - NGL'!$H:$H,'Availability Summary'!$B45,'Availability Report - NGL'!$D:$D,"Active"),0) | M45: =IFERROR(AVERAGEIFS('Availability Report - NGL'!R:R,'Availability Report - NGL'!$H:$H,'Availability Summary'!$B45,'Availability Report - NGL'!$D:$D,"Active"),0) | N45: =IFERROR(AVERAGEIFS('Availability Report - NGL'!S:S,'Availability Report - NGL'!$H:$H,'Availability Summary'!$B45,'Availability Report - NGL'!$D:$D,"Active"),0) | O45: =IFERROR(AVERAGEIFS('Availability Report - NGL'!T:T,'Availability Report - NGL'!$H:$H,'Availability Summary'!$B45,'Availability Report - NGL'!$D:$D,"Active"),0) | Q45: =AVERAGE(N45:O45) | R45: =1-Q45 | T45: =+SUMIFS('Availability Report - NGL'!#REF!,'Availability Report - NGL'!$H:$H,'Availability Summary'!$B45,'Availability Report - NGL'!$D:$D,"Active") | V45: =+SUMIFS('Availability Report - NGL'!#REF!,'Availability Report - NGL'!$H:$H,'Availability Summary'!$B45,'Availability Report - NGL'!$D:$D,"Active")
C46: =SUM(C29:C45) | T46: =SUM(T29:T45) | V46: =SUM(V29:V45)
B50: Non Billable cost from April'25 to March '26
B51: Entity/Practice | C51: Cost
B52: NGL | C52: =+SUMIF('Availability Report - NGL'!$D:$D,"Active",'Availability Report - NGL'!#REF!) | D52: =+C52-C59-C65
B53: nxzen - India | C53: =SUMIF('Availability Report - YTPL'!$D:$D,"Active",'Availability Report - YTPL'!#REF!) | D53: =+C53-C60-C66
B54: D&E - INDIA | C54: =SUMIFS('Availability Report - YTPL'!#REF!,'Availability Report - YTPL'!$E:$E,"D&E",'Availability Report - YTPL'!D:D,"Active") | D54: =+C54-C61-C67
B57: Non Billable cost from April'25 to Jan'26
B58: Entity/Practice | C58: Cost
B59: NGL | C59: =+C52-C65
B60: nxzen - India | C60: =+C53-C66
B61: D&E - INDIA | C61: =+C54-C67
B63: Non Billable cost from Feb'26 to March '26
B64: Entity/Practice | C64: Cost
B65: NGL | C65: =SUMIF('Availability Report - NGL'!$D:$D,"Active",'Availability Report - NGL'!#REF!)
B66: nxzen - India | C66: =SUMIF('Availability Report - YTPL'!$D:$D,"Active",'Availability Report - YTPL'!#REF!)
B67: D&E - INDIA | C67: =SUMIFS('Availability Report - YTPL'!#REF!,'Availability Report - YTPL'!$D:$D,"Active",'Availability Report - YTPL'!$E:$E,"D&E")

Sheet Availability Report - NGL
B2: 0% indicates fully utilised, and 100% indicates fully available.
I3: 20 | J3: 20 | K3: 20 | L3: 20 | M3: 20 | N3: 20 | O3: 20 | P3: 20 | Q3: 20 | R3: 20 | S3: 20 | T3: 20 | AC3: Syed's Update
B4: No. | C4: Name | D4: Status | E4: Business Unit | F4: Function | G4: Practice | H4: Sub Pratcice | I4: 45748 | J4: 45778 | K4: 45809 | L4: 45839 | M4: 45870 | N4: 45901 | O4: 45931 | P4: 45962 | Q4: 45992 | R4: 46023 | S4: 46054 | T4: 46082 | U4: Competency | V4: Primary Skill | W4: Secondary Skills | X4: Other Skills | Y4: RAG | Z4: Actions/Comments | AA4: Avg Availability | AB4: Mar | AC4: Average Availability | AD4: Remarks | AE4: Bids/Proposal/Frameworks | AF4: Internal Apps Development | AG4: Customer Wireframes | AH4: Capability Development | AI4: Partnerships | AJ4: Skills | AK4: Actions
B5: 1 | C5: Abhinav Singh | D5: Active | E5: D&E | F5: Digital & Engineering Services | G5: OT | H5: OT | I5: =IF((I$3-SUMIF(NGL!$C:$C,'Availability Report - NGL'!$C5,NGL!I:I))/I$3<0%,0%,(I$3-SUMIF(NGL!$C:$C,'Availability Report - NGL'!$C5,NGL!I:I))/I$3) | J5: =IF((J$3-SUMIF(NGL!$C:$C,'Availability Report - NGL'!$C5,NGL!J:J))/J$3<0%,0%,(J$3-SUMIF(NGL!$C:$C,'Availability Report - NGL'!$C5,NGL!J:J))/J$3) | K5: =IF((K$3-SUMIF(NGL!$C:$C,'Availability Report - NGL'!$C5,NGL!K:K))/K$3<0%,0%,(K$3-SUMIF(NGL!$C:$C,'Availability Report - NGL'!$C5,NGL!K:K))/K$3) | L5: =IF((L$3-SUMIF(NGL!$C:$C,'Availability Report - NGL'!$C5,NGL!L:L))/L$3<0%,0%,(L$3-SUMIF(NGL!$C:$C,'Availability Report - NGL'!$C5,NGL!L:L))/L$3) | M5: =IF((M$3-SUMIF(NGL!$C:$C,'Availability Report - NGL'!$C5,NGL!M:M))/M$3<0%,0%,(M$3-SUMIF(NGL!$C:$C,'Availability Report - NGL'!$C5,NGL!M:M))/M$3) | N5: =IF((N$3-SUMIF(NGL!$C:$C,'Availability Report - NGL'!$C5,NGL!N:N))/N$3<0%,0%,(N$3-SUMIF(NGL!$C:$C,'Availability Report - NGL'!$C5,NGL!N:N))/N$3) | O5: =IF((O$3-SUMIF(NGL!$C:$C,'Availability Report - NGL'!$C5,NGL!O:O))/O$3<0%,0%,(O$3-SUMIF(NGL!$C:$C,'Availability Report - NGL'!$C5,NGL!O:O))/O$3) | P5: =IF((P$3-SUMIF(NGL!$C:$C,'Availability Report - NGL'!$C5,NGL!P:P))/P$3<0%,0%,(P$3-SUMIF(NGL!$C:$C,'Availability Report - NGL'!$C5,NGL!P:P))/P$3) | Q5: =IF((Q$3-SUMIF(NGL!$C:$C,'Availability Report - NGL'!$C5,NGL!Q:Q))/Q$3<0%,0%,(Q$3-SUMIF(NGL!$C:$C,'Availability Report - NGL'!$C5,NGL!Q:Q))/Q$3) | R5: =IF((R$3-SUMIF(NGL!$C:$C,'Availability Report - NGL'!$C5,NGL!R:R))/R$3<0%,0%,(R$3-SUMIF(NGL!$C:$C,'Availability Report - NGL'!$C5,NGL!R:R))/R$3) | S5: =IF((S$3-SUMIF(NGL!$C:$C,'Availability Report - NGL'!$C5,NGL!S:S))/S$3<0%,0%,(S$3-SUMIF(NGL!$C:$C,'Availability Report - NGL'!$C5,NGL!S:S))/S$3) | T5: =IF((T$3-SUMIF(NGL!$C:$C,'Availability Report - NGL'!$C5,NGL!T:T))/T$3<0%,0%,(T$3-SUMIF(NGL!$C:$C,'Availability Report - NGL'!$C5,NGL!T:T))/T$3) | AA5: =AVERAGE(I5:T5) | AB5: =AVERAGE(T5) | AC5: 0 | AD5: Fully Billed | AK5: Fully Billed
B6: 2 | C6: Adam Soyfur Miah | D6: Left | E6: D&E | F6: Digital & Engineering Services | G6: Apps & Development | H6: Digital Solutions | I6: =IF((I$3-SUMIF(NGL!$C:$C,'Availability Report - NGL'!$C6,NGL!I:I))/I$3<0%,0%,(I$3-SUMIF(NGL!$C:$C,'Availability Report - NGL'!$C6,NGL!I:I))/I$3) | J6: =IF((J$3-SUMIF(NGL!$C:$C,'Availability Report - NGL'!$C6,NGL!J:J))/J$3<0%,0%,(J$3-SUMIF(NGL!$C:$C,'Availability Report - NGL'!$C6,NGL!J:J))/J$3) | K6: =IF((K$3-SUMIF(NGL!$C:$C,'Availability Report - NGL'!$C6,NGL!K:K))/K$3<0%,0%,(K$3-SUMIF(NGL!$C:$C,'Availability Report - NGL'!$C6,NGL!K:K))/K$3) | L6: =IF((L$3-SUMIF(NGL!$C:$C,'Availability Report - NGL'!$C6,NGL!L:L))/L$3<0%,0%,(L$3-SUMIF(NGL!$C:$C,'Availability Report - NGL'!$C6,NGL!L:L))/L$3) | AA6: =AVERAGE(I6:T6) | AD6: Left | AK6: Left
B7: 3 | C7: Akhil Gupta | D7: Active | E7: D&E | F7: Digital & Engineering Services | G7: Apps & Development | H7: Platform Engineering | I7: =IF((I$3-SUMIF(NGL!$C:$C,'Availability Report - NGL'!$C7,NGL!I:I))/I$3<0%,0%,(I$3-SUMIF(NGL!$C:$C,'Availability Report - NGL'!$C7,NGL!I:I))/I$3) | J7: =IF((J$3-SUMIF(NGL!$C:$C,'Availability Report - NGL'!$C7,NGL!J:J))/J$3<0%,0%,(J$3-SUMIF(NGL!$C:$C,'Availability Report - NGL'!$C7,NGL!J:J))/J$3) | K7: =IF((K$3-SUMIF(NGL!$C:$C,'Availability Report - NGL'!$C7,NGL!K:K))/K$3<0%,0%,(K$3-SUMIF(NGL!$C:$C,'Availability Report - NGL'!$C7,NGL!K:K))/K$3) | L7: =IF((L$3-SUMIF(NGL!$C:$C,'Availability Report - NGL'!$C7,NGL!L:L))/L$3<0%,0%,(L$3-SUMIF(NGL!$C:$C,'Availability Report - NGL'!$C7,NGL!L:L))/L$3) | M7: =IF((M$3-SUMIF(NGL!$C:$C,'Availability Report - NGL'!$C7,NGL!M:M))/M$3<0%,0%,(M$3-SUMIF(NGL!$C:$C,'Availability Report - NGL'!$C7,NGL!M:M))/M$3) | N7: =IF((N$3-SUMIF(NGL!$C:$C,'Availability Report - NGL'!$C7,NGL!N:N))/N$3<0%,0%,(N$3-SUMIF(NGL!$C:$C,'Availability Report - NGL'!$C7,NGL!N:N))/N$3) | O7: =IF((O$3-SUMIF(NGL!$C:$C,'Availability Report - NGL'!$C7,NGL!O:O))/O$3<0%,0%,(O$3-SUMIF(NGL!$C:$C,'Availability Report - NGL'!$C7,NGL!O:O))/O$3) | P7: =IF((P$3-SUMIF(NGL!$C:$C,'Availability Report - NGL'!$C7,NGL!P:P))/P$3<0%,0%,(P$3-SUMIF(NGL!$C:$C,'Availability Report - NGL'!$C7,NGL!P:P))/P$3) | Q7: =IF((Q$3-SUMIF(NGL!$C:$C,'Availability Report - NGL'!$C7,NGL!Q:Q))/Q$3<0%,0%,(Q$3-SUMIF(NGL!$C:$C,'Availability Report - NGL'!$C7,NGL!Q:Q))/Q$3) | R7: =IF((R$3-SUMIF(NGL!$C:$C,'Availability Report - NGL'!$C7,NGL!R:R))/R$3<0%,0%,(R$3-SUMIF(NGL!$C:$C,'Availability Report - NGL'!$C7,NGL!R:R))/R$3) | S7: =IF((S$3-SUMIF(NGL!$C:$C,'Availability Report - NGL'!$C7,NGL!S:S))/S$3<0%,0%,(S$3-SUMIF(NGL!$C:$C,'Availability Report - NGL'!$C7,NGL!S:S))/S$3) | T7: =IF((T$3-SUMIF(NGL!$C:$C,'Availability Report - NGL'!$C7,NGL!T:T))/T$3<0%,0%,(T$3-SUMIF(NGL!$C:$C,'Availability Report - NGL'!$C7,NGL!T:T))/T$3) | U7: Cloud Apps Dev | V7: Cloud Apps Development | W7: Tech. Project Management | Y7: A | Z7: Check extended billing in W&W with Tamo | AA7: =AVERAGE(I7:T7) | AB7: =AVERAGE(T7) | AC7: 0.4 | AD7: 40% available for billing | AE7: WWU - Opent Text, Service Suite; WW - EDM | AK7: Tamo to look intothe commercials for 12 days. Will be billed in EDM
B8: 4 | C8: Amit Fadnavis | D8: Active | E8: D&E | F8: Digital & Engineering Services | G8: Apps & Development | H8: Project & Buiness Analysis | I8: =IF((I$3-SUMIF(NGL!$C:$C,'Availability Report - NGL'!$C8,NGL!I:I))/I$3<0%,0%,(I$3-SUMIF(NGL!$C:$C,'Availability Report - NGL'!$C8,NGL!I:I))/I$3) | J8: =IF((J$3-SUMIF(NGL!$C:$C,'Availability Report - NGL'!$C8,NGL!J:J))/J$3<0%,0%,(J$3-SUMIF(NGL!$C:$C,'Availability Report - NGL'!$C8,NGL!J:J))/J$3) | K8: =IF((K$3-SUMIF(NGL!$C:$C,'Availability Report - NGL'!$C8,NGL!K:K))/K$3<0%,0%,(K$3-SUMIF(NGL!$C:$C,'Availability Report - NGL'!$C8,NGL!K:K))/K$3) | L8: =IF((L$3-SUMIF(NGL!$C:$C,'Availability Report - NGL'!$C8,NGL!L:L))/L$3<0%,0%,(L$3-SUMIF(NGL!$C:$C,'Availability Report - NGL'!$C8,NGL!L:L))/L$3) | M8: =IF((M$3-SUMIF(NGL!$C:$C,'Availability Report - NGL'!$C8,NGL!M:M))/M$3<0%,0%,(M$3-SUMIF(NGL!$C:$C,'Availability Report - NGL'!$C8,NGL!M:M))/M$3) | N8: =IF((N$3-SUMIF(NGL!$C:$C,'Availability Report - NGL'!$C8,NGL!N:N))/N$3<0%,0%,(N$3-SUMIF(NGL!$C:$C,'Availability Report - NGL'!$C8,NGL!N:N))/N$3) | O8: =IF((O$3-SUMIF(NGL!$C:$C,'Availability Report - NGL'!$C8,NGL!O:O))/O$3<0%,0%,(O$3-SUMIF(NGL!$C:$C,'Availability Report - NGL'!$C8,NGL!O:O))/O$3) | P8: =IF((P$3-SUMIF(NGL!$C:$C,'Availability Report - NGL'!$C8,NGL!P:P))/P$3<0%,0%,(P$3-SUMIF(NGL!$C:$C,'Availability Report - NGL'!$C8,NGL!P:P))/P$3) | Q8: =IF((Q$3-SUMIF(NGL!$C:$C,'Availability Report - NGL'!$C8,NGL!Q:Q))/Q$3<0%,0%,(Q$3-SUMIF(NGL!$C:$C,'Availability Report - NGL'!$C8,NGL!Q:Q))/Q$3) | R8: =IF((R$3-SUMIF(NGL!$C:$C,'Availability Report - NGL'!$C8,NGL!R:R))/R$3<0%,0%,(R$3-SUMIF(NGL!$C:$C,'Availability Report - NGL'!$C8,NGL!R:R))/R$3) | S8: =IF((S$3-SUMIF(NGL!$C:$C,'Availability Report - NGL'!$C8,NGL!S:S))/S$3<0%,0%,(S$3-SUMIF(NGL!$C:$C,'Availability Report - NGL'!$C8,NGL!S:S))/S$3) | T8: =IF((T$3-SUMIF(NGL!$C:$C,'Availability Report - NGL'!$C8,NGL!T:T))/T$3<0%,0%,(T$3-SUMIF(NGL!$C:$C,'Availability Report - NGL'!$C8,NGL!T:T))/T$3) | U8: Program management | V8: Cloud Migration, Business Engagement | W8: ADO, Agile PM. | Y8: A | Z8: Explore opportunites in UKPN | AA8: =AVERAGE(I8:T8) | AB8: =AVERAGE(T8) | AC8: 0 | AD8: Awaiting paperwork | AK8: Waiting for paper work - Cyber
B9: 5 | C9: Anil Polat | D9: Active | E9: D&E | F9: Digital & Engineering Services | G9: Apps & Development | H9: Platform Engineering | I9: =IF((I$3-SUMIF(NGL!$C:$C,'Availability Report - NGL'!$C9,NGL!I:I))/I$3<0%,0%,(I$3-SUMIF(NGL!$C:$C,'Availability Report - NGL'!$C9,NGL!I:I))/I$3) | J9: =IF((J$3-SUMIF(NGL!$C:$C,'Availability Report - NGL'!$C9,NGL!J:J))/J$3<0%,0%,(J$3-SUMIF(NGL!$C:$C,'Availability Report - NGL'!$C9,NGL!J:J))/J$3) | K9: =IF((K$3-SUMIF(NGL!$C:$C,'Availability Report - NGL'!$C9,NGL!K:K))/K$3<0%,0%,(K$3-SUMIF(NGL!$C:$C,'Availability Report - NGL'!$C9,NGL!K:K))/K$3) | L9: =IF((L$3-SUMIF(NGL!$C:$C,'Availability Report - NGL'!$C9,NGL!L:L))/L$3<0%,0%,(L$3-SUMIF(NGL!$C:$C,'Availability Report - NGL'!$C9,NGL!L:L))/L$3) | M9: =IF((M$3-SUMIF(NGL!$C:$C,'Availability Report - NGL'!$C9,NGL!M:M))/M$3<0%,0%,(M$3-SUMIF(NGL!$C:$C,'Availability Report - NGL'!$C9,NGL!M:M))/M$3) | N9: =IF((N$3-SUMIF(NGL!$C:$C,'Availability Report - NGL'!$C9,NGL!N:N))/N$3<0%,0%,(N$3-SUMIF(NGL!$C:$C,'Availability Report - NGL'!$C9,NGL!N:N))/N$3) | O9: =IF((O$3-SUMIF(NGL!$C:$C,'Availability Report - NGL'!$C9,NGL!O:O))/O$3<0%,0%,(O$3-SUMIF(NGL!$C:$C,'Availability Report - NGL'!$C9,NGL!O:O))/O$3) | P9: =IF((P$3-SUMIF(NGL!$C:$C,'Availability Report - NGL'!$C9,NGL!P:P))/P$3<0%,0%,(P$3-SUMIF(NGL!$C:$C,'Availability Report - NGL'!$C9,NGL!P:P))/P$3) | Q9: =IF((Q$3-SUMIF(NGL!$C:$C,'Availability Report - NGL'!$C9,NGL!Q:Q))/Q$3<0%,0%,(Q$3-SUMIF(NGL!$C:$C,'Availability Report - NGL'!$C9,NGL!Q:Q))/Q$3) | R9: =IF((R$3-SUMIF(NGL!$C:$C,'Availability Report - NGL'!$C9,NGL!R:R))/R$3<0%,0%,(R$3-SUMIF(NGL!$C:$C,'Availability Report - NGL'!$C9,NGL!R:R))/R$3) | S9: =IF((S$3-SUMIF(NGL!$C:$C,'Availability Report - NGL'!$C9,NGL!S:S))/S$3<0%,0%,(S$3-SUMIF(NGL!$C:$C,'Availability Report - NGL'!$C9,NGL!S:S))/S$3) | T9: =IF((T$3-SUMIF(NGL!$C:$C,'Availability Report - NGL'!$C9,NGL!T:T))/T$3<0%,0%,(T$3-SUMIF(NGL!$C:$C,'Availability Report - NGL'!$C9,NGL!T:T))/T$3) | U9: DevOps Arch. | V9: Cloud DevOps | W9: Kubernetics, Project Management | Y9: R | Z9: Hari to check | AA9: =AVERAGE(I9:T9) | AB9: =AVERAGE(T9) | AC9: 0 | AD9: Will be released | AK9: Will be released.
B10: 6 | C10: Anjali Udoshi | D10: Active | E10: D&E | F10: Digital & Engineering Services | G10: Data & AI | H10: AI and Analytics | I10: =IF((I$3-SUMIF(NGL!$C:$C,'Availability Report - NGL'!$C10,NGL!I:I))/I$3<0%,0%,(I$3-SUMIF(NGL!$C:$C,'Availability Report - NGL'!$C10,NGL!I:I))/I$3) | J10: =IF((J$3-SUMIF(NGL!$C:$C,'Availability Report - NGL'!$C10,NGL!J:J))/J$3<0%,0%,(J$3-SUMIF(NGL!$C:$C,'Availability Report - NGL'!$C10,NGL!J:J))/J$3) | K10: =IF((K$3-SUMIF(NGL!$C:$C,'Availability Report - NGL'!$C10,NGL!K:K))/K$3<0%,0%,(K$3-SUMIF(NGL!$C:$C,'Availability Report - NGL'!$C10,NGL!K:K))/K$3) | L10: =IF((L$3-SUMIF(NGL!$C:$C,'Availability Report - NGL'!$C10,NGL!L:L))/L$3<0%,0%,(L$3-SUMIF(NGL!$C:$C,'Availability Report - NGL'!$C10,NGL!L:L))/L$3) | M10: =IF((M$3-SUMIF(NGL!$C:$C,'Availability Report - NGL'!$C10,NGL!M:M))/M$3<0%,0%,(M$3-SUMIF(NGL!$C:$C,'Availability Report - NGL'!$C10,NGL!M:M))/M$3) | N10: =IF((N$3-SUMIF(NGL!$C:$C,'Availability Report - NGL'!$C10,NGL!N:N))/N$3<0%,0%,(N$3-SUMIF(NGL!$C:$C,'Availability Report - NGL'!$C10,NGL!N:N))/N$3) | O10: =IF((O$3-SUMIF(NGL!$C:$C,'Availability Report - NGL'!$C10,NGL!O:O))/O$3<0%,0%,(O$3-SUMIF(NGL!$C:$C,'Availability Report - NGL'!$C10,NGL!O:O))/O$3) | P10: =IF((P$3-SUMIF(NGL!$C:$C,'Availability Report - NGL'!$C10,NGL!P:P))/P$3<0%,0%,(P$3-SUMIF(NGL!$C:$C,'Availability Report - NGL'!$C10,NGL!P:P))/P$3) | Q10: =IF((Q$3-SUMIF(NGL!$C:$C,'Availability Report - NGL'!$C10,NGL!Q:Q))/Q$3<0%,0%,(Q$3-SUMIF(NGL!$C:$C,'Availability Report - NGL'!$C10,NGL!Q:Q))/Q$3) | R10: =IF((R$3-SUMIF(NGL!$C:$C,'Availability Report - NGL'!$C10,NGL!R:R))/R$3<0%,0%,(R$3-SUMIF(NGL!$C:$C,'Availability Report - NGL'!$C10,NGL!R:R))/R$3) | S10: =IF((S$3-SUMIF(NGL!$C:$C,'Availability Report - NGL'!$C10,NGL!S:S))/S$3<0%,0%,(S$3-SUMIF(NGL!$C:$C,'Availability Report - NGL'!$C10,NGL!S:S))/S$3) | T10: =IF((T$3-SUMIF(NGL!$C:$C,'Availability Report - NGL'!$C10,NGL!T:T))/T$3<0%,0%,(T$3-SUMIF(NGL!$C:$C,'Availability Report - NGL'!$C10,NGL!T:T))/T$3) | AA10: =AVERAGE(I10:T10) | AB10: =AVERAGE(T10) | AC10: 0 | AD10: Maternity | AK10: maternity
B11: 7 | C11: Danie Selvaraju | D11: Active | E11: D&E | F11: Digital & Engineering Services | G11: Data & AI | H11: AI and Analytics | I11: =IF((I$3-SUMIF(NGL!$C:$C,'Availability Report - NGL'!$C11,NGL!I:I))/I$3<0%,0%,(I$3-SUMIF(NGL!$C:$C,'Availability Report - NGL'!$C11,NGL!I:I))/I$3) | J11: =IF((J$3-SUMIF(NGL!$C:$C,'Availability Report - NGL'!$C11,NGL!J:J))/J$3<0%,0%,(J$3-SUMIF(NGL!$C:$C,'Availability Report - NGL'!$C11,NGL!J:J))/J$3) | K11: =IF((K$3-SUMIF(NGL!$C:$C,'Availability Report - NGL'!$C11,NGL!K:K))/K$3<0%,0%,(K$3-SUMIF(NGL!$C:$C,'Availability Report - NGL'!$C11,NGL!K:K))/K$3) | L11: =IF((L$3-SUMIF(NGL!$C:$C,'Availability Report - NGL'!$C11,NGL!L:L))/L$3<0%,0%,(L$3-SUMIF(NGL!$C:$C,'Availability Report - NGL'!$C11,NGL!L:L))/L$3) | M11: =IF((M$3-SUMIF(NGL!$C:$C,'Availability Report - NGL'!$C11,NGL!M:M))/M$3<0%,0%,(M$3-SUMIF(NGL!$C:$C,'Availability Report - NGL'!$C11,NGL!M:M))/M$3) | N11: =IF((N$3-SUMIF(NGL!$C:$C,'Availability Report - NGL'!$C11,NGL!N:N))/N$3<0%,0%,(N$3-SUMIF(NGL!$C:$C,'Availability Report - NGL'!$C11,NGL!N:N))/N$3) | O11: =IF((O$3-SUMIF(NGL!$C:$C,'Availability Report - NGL'!$C11,NGL!O:O))/O$3<0%,0%,(O$3-SUMIF(NGL!$C:$C,'Availability Report - NGL'!$C11,NGL!O:O))/O$3) | P11: =IF((P$3-SUMIF(NGL!$C:$C,'Availability Report - NGL'!$C11,NGL!P:P))/P$3<0%,0%,(P$3-SUMIF(NGL!$C:$C,'Availability Report - NGL'!$C11,NGL!P:P))/P$3) | Q11: =IF((Q$3-SUMIF(NGL!$C:$C,'Availability Report - NGL'!$C11,NGL!Q:Q))/Q$3<0%,0%,(Q$3-SUMIF(NGL!$C:$C,'Availability Report - NGL'!$C11,NGL!Q:Q))/Q$3) | R11: =IF((R$3-SUMIF(NGL!$C:$C,'Availability Report - NGL'!$C11,NGL!R:R))/R$3<0%,0%,(R$3-SUMIF(NGL!$C:$C,'Availability Report - NGL'!$C11,NGL!R:R))/R$3) | S11: =IF((S$3-SUMIF(NGL!$C:$C,'Availability Report - NGL'!$C11,NGL!S:S))/S$3<0%,0%,(S$3-SUMIF(NGL!$C:$C,'Availability Report - NGL'!$C11,NGL!S:S))/S$3) | T11: =IF((T$3-SUMIF(NGL!$C:$C,'Availability Report - NGL'!$C11,NGL!T:T))/T$3<0%,0%,(T$3-SUMIF(NGL!$C:$C,'Availability Report - NGL'!$C11,NGL!T:T))/T$3) | U11: Program management, Architecture | V11: Large Industry Programme Delivery | W11: Business Engagement, Consulting | X11: Enterprise Apps, Financial modelling | Y11: A | Z11: Faster Staging - potentially | AA11: =AVERAGE(I11:T11) | AB11: =AVERAGE(T11) | AD11: Fully Billed
B12: 8 | C12: Darren McNulty | D12: Active | E12: D&E | F12: Digital & Engineering Services | G12: Renewable and Engineering | H12: Renewable Advisory | I12: =IF((I$3-SUMIF(NGL!$C:$C,'Availability Report - NGL'!$C12,NGL!I:I))/I$3<0%,0%,(I$3-SUMIF(NGL!$C:$C,'Availability Report - NGL'!$C12,NGL!I:I))/I$3) | J12: =IF((J$3-SUMIF(NGL!$C:$C,'Availability Report - NGL'!$C12,NGL!J:J))/J$3<0%,0%,(J$3-SUMIF(NGL!$C:$C,'Availability Report - NGL'!$C12,NGL!J:J))/J$3) | K12: =IF((K$3-SUMIF(NGL!$C:$C,'Availability Report - NGL'!$C12,NGL!K:K))/K$3<0%,0%,(K$3-SUMIF(NGL!$C:$C,'Availability Report - NGL'!$C12,NGL!K:K))/K$3) | L12: =IF((L$3-SUMIF(NGL!$C:$C,'Availability Report - NGL'!$C12,NGL!L:L))/L$3<0%,0%,(L$3-SUMIF(NGL!$C:$C,'Availability Report - NGL'!$C12,NGL!L:L))/L$3) | M12: =IF((M$3-SUMIF(NGL!$C:$C,'Availability Report - NGL'!$C12,NGL!M:M))/M$3<0%,0%,(M$3-SUMIF(NGL!$C:$C,'Availability Report - NGL'!$C12,NGL!M:M))/M$3) | N12: =IF((N$3-SUMIF(NGL!$C:$C,'Availability Report - NGL'!$C12,NGL!N:N))/N$3<0%,0%,(N$3-SUMIF(NGL!$C:$C,'Availability Report - NGL'!$C12,NGL!N:N))/N$3) | O12: =IF((O$3-SUMIF(NGL!$C:$C,'Availability Report - NGL'!$C12,NGL!O:O))/O$3<0%,0%,(O$3-SUMIF(NGL!$C:$C,'Availability Report - NGL'!$C12,NGL!O:O))/O$3) | P12: =IF((P$3-SUMIF(NGL!$C:$C,'Availability Report - NGL'!$C12,NGL!P:P))/P$3<0%,0%,(P$3-SUMIF(NGL!$C:$C,'Availability Report - NGL'!$C12,NGL!P:P))/P$3) | Q12: =IF((Q$3-SUMIF(NGL!$C:$C,'Availability Report - NGL'!$C12,NGL!Q:Q))/Q$3<0%,0%,(Q$3-SUMIF(NGL!$C:$C,'Availability Report - NGL'!$C12,NGL!Q:Q))/Q$3) | R12: =IF((R$3-SUMIF(NGL!$C:$C,'Availability Report - NGL'!$C12,NGL!R:R))/R$3<0%,0%,(R$3-SUMIF(NGL!$C:$C,'Availability Report - NGL'!$C12,NGL!R:R))/R$3) | S12: =IF((S$3-SUMIF(NGL!$C:$C,'Availability Report - NGL'!$C12,NGL!S:S))/S$3<0%,0%,(S$3-SUMIF(NGL!$C:$C,'Availability Report - NGL'!$C12,NGL!S:S))/S$3) | T12: =IF((T$3-SUMIF(NGL!$C:$C,'Availability Report - NGL'!$C12,NGL!T:T))/T$3<0%,0%,(T$3-SUMIF(NGL!$C:$C,'Availability Report - NGL'!$C12,NGL!T:T))/T$3) | AA12: =AVERAGE(I12:T12) | AB12: =AVERAGE(T12) | AC12: 0.95 | AD12: 100% available for billing | AK12: Available
B13: 9 | C13: Deepthee Kasal | D13: Active | E13: D&E | F13: Digital & Engineering Services | G13: Apps & Development | H13: SAP | I13: =IF((I$3-SUMIF(NGL!$C:$C,'Availability Report - NGL'!$C13,NGL!I:I))/I$3<0%,0%,(I$3-SUMIF(NGL!$C:$C,'Availability Report - NGL'!$C13,NGL!I:I))/I$3) | J13: =IF((J$3-SUMIF(NGL!$C:$C,'Availability Report - NGL'!$C13,NGL!J:J))/J$3<0%,0%,(J$3-SUMIF(NGL!$C:$C,'Availability Report - NGL'!$C13,NGL!J:J))/J$3) | K13: =IF((K$3-SUMIF(NGL!$C:$C,'Availability Report - NGL'!$C13,NGL!K:K))/K$3<0%,0%,(K$3-SUMIF(NGL!$C:$C,'Availability Report - NGL'!$C13,NGL!K:K))/K$3) | L13: =IF((L$3-SUMIF(NGL!$C:$C,'Availability Report - NGL'!$C13,NGL!L:L))/L$3<0%,0%,(L$3-SUMIF(NGL!$C:$C,'Availability Report - NGL'!$C13,NGL!L:L))/L$3) | M13: =IF((M$3-SUMIF(NGL!$C:$C,'Availability Report - NGL'!$C13,NGL!M:M))/M$3<0%,0%,(M$3-SUMIF(NGL!$C:$C,'Availability Report - NGL'!$C13,NGL!M:M))/M$3) | N13: =IF((N$3-SUMIF(NGL!$C:$C,'Availability Report - NGL'!$C13,NGL!N:N))/N$3<0%,0%,(N$3-SUMIF(NGL!$C:$C,'Availability Report - NGL'!$C13,NGL!N:N))/N$3) | O13: =IF((O$3-SUMIF(NGL!$C:$C,'Availability Report - NGL'!$C13,NGL!O:O))/O$3<0%,0%,(O$3-SUMIF(NGL!$C:$C,'Availability Report - NGL'!$C13,NGL!O:O))/O$3) | P13: =IF((P$3-SUMIF(NGL!$C:$C,'Availability Report - NGL'!$C13,NGL!P:P))/P$3<0%,0%,(P$3-SUMIF(NGL!$C:$C,'Availability Report - NGL'!$C13,NGL!P:P))/P$3) | Q13: =IF((Q$3-SUMIF(NGL!$C:$C,'Availability Report - NGL'!$C13,NGL!Q:Q))/Q$3<0%,0%,(Q$3-SUMIF(NGL!$C:$C,'Availability Report - NGL'!$C13,NGL!Q:Q))/Q$3) | R13: =IF((R$3-SUMIF(NGL!$C:$C,'Availability Report - NGL'!$C13,NGL!R:R))/R$3<0%,0%,(R$3-SUMIF(NGL!$C:$C,'Availability Report - NGL'!$C13,NGL!R:R))/R$3) | S13: =IF((S$3-SUMIF(NGL!$C:$C,'Availability Report - NGL'!$C13,NGL!S:S))/S$3<0%,0%,(S$3-SUMIF(NGL!$C:$C,'Availability Report - NGL'!$C13,NGL!S:S))/S$3) | T13: =IF((T$3-SUMIF(NGL!$C:$C,'Availability Report - NGL'!$C13,NGL!T:T))/T$3<0%,0%,(T$3-SUMIF(NGL!$C:$C,'Availability Report - NGL'!$C13,NGL!T:T))/T$3) | U13: SAP Technical Architect | V13: SAP ABAP and cross functional consultant | W13: Project Management | X13: Cloud Migration | Y13: A | Z13: 5 days in Vision Arch. W&W Explore futher opportunities from Jan | AA13: =AVERAGE(I13:T13) | AB13: =AVERAGE(T13) | AC13: 0.5 | AD13: 50% Billed - SAP Lead | AH13: SAP | AK13: Fatima to update - SAP Lead. Reduce it to 60%.
B14: 10 | C14: Dhruv Hasmukhbhai Patel | D14: Left | E14: D&E | F14: Digital & Engineering Services | G14: Renewable and Engineering | H14: Design Engineering | I14: =IF((I$3-SUMIF(NGL!$C:$C,'Availability Report - NGL'!$C14,NGL!I:I))/I$3<0%,0%,(I$3-SUMIF(NGL!$C:$C,'Availability Report - NGL'!$C14,NGL!I:I))/I$3) | J14: =IF((J$3-SUMIF(NGL!$C:$C,'Availability Report - NGL'!$C14,NGL!J:J))/J$3<0%,0%,(J$3-SUMIF(NGL!$C:$C,'Availability Report - NGL'!$C14,NGL!J:J))/J$3) | K14: =IF((K$3-SUMIF(NGL!$C:$C,'Availability Report - NGL'!$C14,NGL!K:K))/K$3<0%,0%,(K$3-SUMIF(NGL!$C:$C,'Availability Report - NGL'!$C14,NGL!K:K))/K$3) | AA14: =AVERAGE(I14:T14) | AD14: Left
B15: 11 | C15: Durga Prasad | D15: Active | E15: D&E | F15: Digital & Engineering Services | G15: Apps & Development | H15: Digital Solutions | I15: =IF((I$3-SUMIF(NGL!$C:$C,'Availability Report - NGL'!$C15,NGL!I:I))/I$3<0%,0%,(I$3-SUMIF(NGL!$C:$C,'Availability Report - NGL'!$C15,NGL!I:I))/I$3) | J15: =IF((J$3-SUMIF(NGL!$C:$C,'Availability Report - NGL'!$C15,NGL!J:J))/J$3<0%,0%,(J$3-SUMIF(NGL!$C:$C,'Availability Report - NGL'!$C15,NGL!J:J))/J$3) | K15: =IF((K$3-SUMIF(NGL!$C:$C,'Availability Report - NGL'!$C15,NGL!K:K))/K$3<0%,0%,(K$3-SUMIF(NGL!$C:$C,'Availability Report - NGL'!$C15,NGL!K:K))/K$3) | L15: =IF((L$3-SUMIF(NGL!$C:$C,'Availability Report - NGL'!$C15,NGL!L:L))/L$3<0%,0%,(L$3-SUMIF(NGL!$C:$C,'Availability Report - NGL'!$C15,NGL!L:L))/L$3) | M15: =IF((M$3-SUMIF(NGL!$C:$C,'Availability Report - NGL'!$C15,NGL!M:M))/M$3<0%,0%,(M$3-SUMIF(NGL!$C:$C,'Availability Report - NGL'!$C15,NGL!M:M))/M$3) | N15: =IF((N$3-SUMIF(NGL!$C:$C,'Availability Report - NGL'!$C15,NGL!N:N))/N$3<0%,0%,(N$3-SUMIF(NGL!$C:$C,'Availability Report - NGL'!$C15,NGL!N:N))/N$3) | O15: =IF((O$3-SUMIF(NGL!$C:$C,'Availability Report - NGL'!$C15,NGL!O:O))/O$3<0%,0%,(O$3-SUMIF(NGL!$C:$C,'Availability Report - NGL'!$C15,NGL!O:O))/O$3) | P15: =IF((P$3-SUMIF(NGL!$C:$C,'Availability Report - NGL'!$C15,NGL!P:P))/P$3<0%,0%,(P$3-SUMIF(NGL!$C:$C,'Availability Report - NGL'!$C15,NGL!P:P))/P$3) | Q15: =IF((Q$3-SUMIF(NGL!$C:$C,'Availability Report - NGL'!$C15,NGL!Q:Q))/Q$3<0%,0%,(Q$3-SUMIF(NGL!$C:$C,'Availability Report - NGL'!$C15,NGL!Q:Q))/Q$3) | R15: =IF((R$3-SUMIF(NGL!$C:$C,'Availability Report - NGL'!$C15,NGL!R:R))/R$3<0%,0%,(R$3-SUMIF(NGL!$C:$C,'Availability Report - NGL'!$C15,NGL!R:R))/R$3) | S15: =IF((S$3-SUMIF(NGL!$C:$C,'Availability Report - NGL'!$C15,NGL!S:S))/S$3<0%,0%,(S$3-SUMIF(NGL!$C:$C,'Availability Report - NGL'!$C15,NGL!S:S))/S$3) | T15: =IF((T$3-SUMIF(NGL!$C:$C,'Availability Report - NGL'!$C15,NGL!T:T))/T$3<0%,0%,(T$3-SUMIF(NGL!$C:$C,'Availability Report - NGL'!$C15,NGL!T:T))/T$3) | AA15: =AVERAGE(I15:T15) | AB15: =AVERAGE(T15) | AD15: Fully Billed
B16: 12 | C16: Easwar P | D16: Active | E16: Growth | F16: Growth | G16: Growth | H16: Growth | I16: =IF((I$3-SUMIF(NGL!$C:$C,'Availability Report - NGL'!$C16,NGL!I:I))/I$3<0%,0%,(I$3-SUMIF(NGL!$C:$C,'Availability Report - NGL'!$C16,NGL!I:I))/I$3) | J16: =IF((J$3-SUMIF(NGL!$C:$C,'Availability Report - NGL'!$C16,NGL!J:J))/J$3<0%,0%,(J$3-SUMIF(NGL!$C:$C,'Availability Report - NGL'!$C16,NGL!J:J))/J$3) | K16: =IF((K$3-SUMIF(NGL!$C:$C,'Availability Report - NGL'!$C16,NGL!K:K))/K$3<0%,0%,(K$3-SUMIF(NGL!$C:$C,'Availability Report - NGL'!$C16,NGL!K:K))/K$3) | L16: =IF((L$3-SUMIF(NGL!$C:$C,'Availability Report - NGL'!$C16,NGL!L:L))/L$3<0%,0%,(L$3-SUMIF(NGL!$C:$C,'Availability Report - NGL'!$C16,NGL!L:L))/L$3) | M16: =IF((M$3-SUMIF(NGL!$C:$C,'Availability Report - NGL'!$C16,NGL!M:M))/M$3<0%,0%,(M$3-SUMIF(NGL!$C:$C,'Availability Report - NGL'!$C16,NGL!M:M))/M$3) | N16: =IF((N$3-SUMIF(NGL!$C:$C,'Availability Report - NGL'!$C16,NGL!N:N))/N$3<0%,0%,(N$3-SUMIF(NGL!$C:$C,'Availability Report - NGL'!$C16,NGL!N:N))/N$3) | O16: =IF((O$3-SUMIF(NGL!$C:$C,'Availability Report - NGL'!$C16,NGL!O:O))/O$3<0%,0%,(O$3-SUMIF(NGL!$C:$C,'Availability Report - NGL'!$C16,NGL!O:O))/O$3) | P16: =IF((P$3-SUMIF(NGL!$C:$C,'Availability Report - NGL'!$C16,NGL!P:P))/P$3<0%,0%,(P$3-SUMIF(NGL!$C:$C,'Availability Report - NGL'!$C16,NGL!P:P))/P$3) | Q16: =IF((Q$3-SUMIF(NGL!$C:$C,'Availability Report - NGL'!$C16,NGL!Q:Q))/Q$3<0%,0%,(Q$3-SUMIF(NGL!$C:$C,'Availability Report - NGL'!$C16,NGL!Q:Q))/Q$3) | R16: =IF((R$3-SUMIF(NGL!$C:$C,'Availability Report - NGL'!$C16,NGL!R:R))/R$3<0%,0%,(R$3-SUMIF(NGL!$C:$C,'Availability Report - NGL'!$C16,NGL!R:R))/R$3) | S16: =IF((S$3-SUMIF(NGL!$C:$C,'Availability Report - NGL'!$C16,NGL!S:S))/S$3<0%,0%,(S$3-SUMIF(NGL!$C:$C,'Availability Report - NGL'!$C16,NGL!S:S))/S$3) | T16: =IF((T$3-SUMIF(NGL!$C:$C,'Availability Report - NGL'!$C16,NGL!T:T))/T$3<0%,0%,(T$3-SUMIF(NGL!$C:$C,'Availability Report - NGL'!$C16,NGL!T:T))/T$3) | AA16: =AVERAGE(I16:T16) | AB16: =AVERAGE(R16:T16) | AC16: 0.98 | AD16: Growth | AK16: Growth
B17: 13 | C17: Fatima Saviya Fernandes | D17: Active | E17: D&E | F17: Digital & Engineering Services | G17: Apps & Development | H17: Managed Services | I17: =IF((I$3-SUMIF(NGL!$C:$C,'Availability Report - NGL'!$C17,NGL!I:I))/I$3<0%,0%,(I$3-SUMIF(NGL!$C:$C,'Availability Report - NGL'!$C17,NGL!I:I))/I$3) | J17: =IF((J$3-SUMIF(NGL!$C:$C,'Availability Report - NGL'!$C17,NGL!J:J))/J$3<0%,0%,(J$3-SUMIF(NGL!$C:$C,'Availability Report - NGL'!$C17,NGL!J:J))/J$3) | K17: =IF((K$3-SUMIF(NGL!$C:$C,'Availability Report - NGL'!$C17,NGL!K:K))/K$3<0%,0%,(K$3-SUMIF(NGL!$C:$C,'Availability Report - NGL'!$C17,NGL!K:K))/K$3) | L17: =IF((L$3-SUMIF(NGL!$C:$C,'Availability Report - NGL'!$C17,NGL!L:L))/L$3<0%,0%,(L$3-SUMIF(NGL!$C:$C,'Availability Report - NGL'!$C17,NGL!L:L))/L$3) | M17: =IF((M$3-SUMIF(NGL!$C:$C,'Availability Report - NGL'!$C17,NGL!M:M))/M$3<0%,0%,(M$3-SUMIF(NGL!$C:$C,'Availability Report - NGL'!$C17,NGL!M:M))/M$3) | N17: =IF((N$3-SUMIF(NGL!$C:$C,'Availability Report - NGL'!$C17,NGL!N:N))/N$3<0%,0%,(N$3-SUMIF(NGL!$C:$C,'Availability Report - NGL'!$C17,NGL!N:N))/N$3) | O17: =IF((O$3-SUMIF(NGL!$C:$C,'Availability Report - NGL'!$C17,NGL!O:O))/O$3<0%,0%,(O$3-SUMIF(NGL!$C:$C,'Availability Report - NGL'!$C17,NGL!O:O))/O$3) | P17: =IF((P$3-SUMIF(NGL!$C:$C,'Availability Report - NGL'!$C17,NGL!P:P))/P$3<0%,0%,(P$3-SUMIF(NGL!$C:$C,'Availability Report - NGL'!$C17,NGL!P:P))/P$3) | Q17: =IF((Q$3-SUMIF(NGL!$C:$C,'Availability Report - NGL'!$C17,NGL!Q:Q))/Q$3<0%,0%,(Q$3-SUMIF(NGL!$C:$C,'Availability Report - NGL'!$C17,NGL!Q:Q))/Q$3) | R17: =IF((R$3-SUMIF(NGL!$C:$C,'Availability Report - NGL'!$C17,NGL!R:R))/R$3<0%,0%,(R$3-SUMIF(NGL!$C:$C,'Availability Report - NGL'!$C17,NGL!R:R))/R$3) | S17: =IF((S$3-SUMIF(NGL!$C:$C,'Availability Report - NGL'!$C17,NGL!S:S))/S$3<0%,0%,(S$3-SUMIF(NGL!$C:$C,'Availability Report - NGL'!$C17,NGL!S:S))/S$3) | T17: =IF((T$3-SUMIF(NGL!$C:$C,'Availability Report - NGL'!$C17,NGL!T:T))/T$3<0%,0%,(T$3-SUMIF(NGL!$C:$C,'Availability Report - NGL'!$C17,NGL!T:T))/T$3) | AA17: =AVERAGE(I17:T17) | AB17: =AVERAGE(T17) | AD17: Fully Billed
B18: 14 | C18: Girish Menon | D18: Active | E18: D&E | F18: Digital & Engineering Services | G18: Apps & Development | H18: Digital Solutions | I18: =IF((I$3-SUMIF(NGL!$C:$C,'Availability Report - NGL'!$C18,NGL!I:I))/I$3<0%,0%,(I$3-SUMIF(NGL!$C:$C,'Availability Report - NGL'!$C18,NGL!I:I))/I$3) | J18: =IF((J$3-SUMIF(NGL!$C:$C,'Availability Report - NGL'!$C18,NGL!J:J))/J$3<0%,0%,(J$3-SUMIF(NGL!$C:$C,'Availability Report - NGL'!$C18,NGL!J:J))/J$3) | K18: =IF((K$3-SUMIF(NGL!$C:$C,'Availability Report - NGL'!$C18,NGL!K:K))/K$3<0%,0%,(K$3-SUMIF(NGL!$C:$C,'Availability Report - NGL'!$C18,NGL!K:K))/K$3) | L18: =IF((L$3-SUMIF(NGL!$C:$C,'Availability Report - NGL'!$C18,NGL!L:L))/L$3<0%,0%,(L$3-SUMIF(NGL!$C:$C,'Availability Report - NGL'!$C18,NGL!L:L))/L$3) | M18: =IF((M$3-SUMIF(NGL!$C:$C,'Availability Report - NGL'!$C18,NGL!M:M))/M$3<0%,0%,(M$3-SUMIF(NGL!$C:$C,'Availability Report - NGL'!$C18,NGL!M:M))/M$3) | N18: =IF((N$3-SUMIF(NGL!$C:$C,'Availability Report - NGL'!$C18,NGL!N:N))/N$3<0%,0%,(N$3-SUMIF(NGL!$C:$C,'Availability Report - NGL'!$C18,NGL!N:N))/N$3) | O18: =IF((O$3-SUMIF(NGL!$C:$C,'Availability Report - NGL'!$C18,NGL!O:O))/O$3<0%,0%,(O$3-SUMIF(NGL!$C:$C,'Availability Report - NGL'!$C18,NGL!O:O))/O$3) | P18: =IF((P$3-SUMIF(NGL!$C:$C,'Availability Report - NGL'!$C18,NGL!P:P))/P$3<0%,0%,(P$3-SUMIF(NGL!$C:$C,'Availability Report - NGL'!$C18,NGL!P:P))/P$3) | Q18: =IF((Q$3-SUMIF(NGL!$C:$C,'Availability Report - NGL'!$C18,NGL!Q:Q))/Q$3<0%,0%,(Q$3-SUMIF(NGL!$C:$C,'Availability Report - NGL'!$C18,NGL!Q:Q))/Q$3) | R18: =IF((R$3-SUMIF(NGL!$C:$C,'Availability Report - NGL'!$C18,NGL!R:R))/R$3<0%,0%,(R$3-SUMIF(NGL!$C:$C,'Availability Report - NGL'!$C18,NGL!R:R))/R$3) | S18: =IF((S$3-SUMIF(NGL!$C:$C,'Availability Report - NGL'!$C18,NGL!S:S))/S$3<0%,0%,(S$3-SUMIF(NGL!$C:$C,'Availability Report - NGL'!$C18,NGL!S:S))/S$3) | T18: =IF((T$3-SUMIF(NGL!$C:$C,'Availability Report - NGL'!$C18,NGL!T:T))/T$3<0%,0%,(T$3-SUMIF(NGL!$C:$C,'Availability Report - NGL'!$C18,NGL!T:T))/T$3) | AA18: =AVERAGE(I18:T18) | AB18: =AVERAGE(T18) | AD18: Fully Billed
B19: 15 | C19: Harsha Anand Jr | D19: Active | E19: D&E | F19: Digital & Engineering Services | G19: Renewable and Engineering | H19: Renewable Advisory | I19: =IF((I$3-SUMIF(NGL!$C:$C,'Availability Report - NGL'!$C19,NGL!I:I))/I$3<0%,0%,(I$3-SUMIF(NGL!$C:$C,'Availability Report - NGL'!$C19,NGL!I:I))/I$3) | J19: =IF((J$3-SUMIF(NGL!$C:$C,'Availability Report - NGL'!$C19,NGL!J:J))/J$3<0%,0%,(J$3-SUMIF(NGL!$C:$C,'Availability Report - NGL'!$C19,NGL!J:J))/J$3) | K19: =IF((K$3-SUMIF(NGL!$C:$C,'Availability Report - NGL'!$C19,NGL!K:K))/K$3<0%,0%,(K$3-SUMIF(NGL!$C:$C,'Availability Report - NGL'!$C19,NGL!K:K))/K$3) | L19: =IF((L$3-SUMIF(NGL!$C:$C,'Availability Report - NGL'!$C19,NGL!L:L))/L$3<0%,0%,(L$3-SUMIF(NGL!$C:$C,'Availability Report - NGL'!$C19,NGL!L:L))/L$3) | M19: =IF((M$3-SUMIF(NGL!$C:$C,'Availability Report - NGL'!$C19,NGL!M:M))/M$3<0%,0%,(M$3-SUMIF(NGL!$C:$C,'Availability Report - NGL'!$C19,NGL!M:M))/M$3) | N19: =IF((N$3-SUMIF(NGL!$C:$C,'Availability Report - NGL'!$C19,NGL!N:N))/N$3<0%,0%,(N$3-SUMIF(NGL!$C:$C,'Availability Report - NGL'!$C19,NGL!N:N))/N$3) | O19: =IF((O$3-SUMIF(NGL!$C:$C,'Availability Report - NGL'!$C19,NGL!O:O))/O$3<0%,0%,(O$3-SUMIF(NGL!$C:$C,'Availability Report - NGL'!$C19,NGL!O:O))/O$3) | P19: =IF((P$3-SUMIF(NGL!$C:$C,'Availability Report - NGL'!$C19,NGL!P:P))/P$3<0%,0%,(P$3-SUMIF(NGL!$C:$C,'Availability Report - NGL'!$C19,NGL!P:P))/P$3) | Q19: =IF((Q$3-SUMIF(NGL!$C:$C,'Availability Report - NGL'!$C19,NGL!Q:Q))/Q$3<0%,0%,(Q$3-SUMIF(NGL!$C:$C,'Availability Report - NGL'!$C19,NGL!Q:Q))/Q$3) | R19: =IF((R$3-SUMIF(NGL!$C:$C,'Availability Report - NGL'!$C19,NGL!R:R))/R$3<0%,0%,(R$3-SUMIF(NGL!$C:$C,'Availability Report - NGL'!$C19,NGL!R:R))/R$3) | S19: =IF((S$3-SUMIF(NGL!$C:$C,'Availability Report - NGL'!$C19,NGL!S:S))/S$3<0%,0%,(S$3-SUMIF(NGL!$C:$C,'Availability Report - NGL'!$C19,NGL!S:S))/S$3) | T19: =IF((T$3-SUMIF(NGL!$C:$C,'Availability Report - NGL'!$C19,NGL!T:T))/T$3<0%,0%,(T$3-SUMIF(NGL!$C:$C,'Availability Report - NGL'!$C19,NGL!T:T))/T$3) | AA19: =AVERAGE(I19:T19) | AB19: =AVERAGE(T19) | AC19: 1 | AD19: 100% available for billing | AK19: Available
B20: 16 | C20: Justin Vijay | D20: Active | E20: D&E | F20: Digital & Engineering Services | G20: Apps & Development | H20: Platform Engineering | I20: =IF((I$3-SUMIF(NGL!$C:$C,'Availability Report - NGL'!$C20,NGL!I:I))/I$3<0%,0%,(I$3-SUMIF(NGL!$C:$C,'Availability Report - NGL'!$C20,NGL!I:I))/I$3) | J20: =IF((J$3-SUMIF(NGL!$C:$C,'Availability Report - NGL'!$C20,NGL!J:J))/J$3<0%,0%,(J$3-SUMIF(NGL!$C:$C,'Availability Report - NGL'!$C20,NGL!J:J))/J$3) | K20: =IF((K$3-SUMIF(NGL!$C:$C,'Availability Report - NGL'!$C20,NGL!K:K))/K$3<0%,0%,(K$3-SUMIF(NGL!$C:$C,'Availability Report - NGL'!$C20,NGL!K:K))/K$3) | L20: =IF((L$3-SUMIF(NGL!$C:$C,'Availability Report - NGL'!$C20,NGL!L:L))/L$3<0%,0%,(L$3-SUMIF(NGL!$C:$C,'Availability Report - NGL'!$C20,NGL!L:L))/L$3) | M20: =IF((M$3-SUMIF(NGL!$C:$C,'Availability Report - NGL'!$C20,NGL!M:M))/M$3<0%,0%,(M$3-SUMIF(NGL!$C:$C,'Availability Report - NGL'!$C20,NGL!M:M))/M$3) | N20: =IF((N$3-SUMIF(NGL!$C:$C,'Availability Report - NGL'!$C20,NGL!N:N))/N$3<0%,0%,(N$3-SUMIF(NGL!$C:$C,'Availability Report - NGL'!$C20,NGL!N:N))/N$3) | O20: =IF((O$3-SUMIF(NGL!$C:$C,'Availability Report - NGL'!$C20,NGL!O:O))/O$3<0%,0%,(O$3-SUMIF(NGL!$C:$C,'Availability Report - NGL'!$C20,NGL!O:O))/O$3) | P20: =IF((P$3-SUMIF(NGL!$C:$C,'Availability Report - NGL'!$C20,NGL!P:P))/P$3<0%,0%,(P$3-SUMIF(NGL!$C:$C,'Availability Report - NGL'!$C20,NGL!P:P))/P$3) | Q20: =IF((Q$3-SUMIF(NGL!$C:$C,'Availability Report - NGL'!$C20,NGL!Q:Q))/Q$3<0%,0%,(Q$3-SUMIF(NGL!$C:$C,'Availability Report - NGL'!$C20,NGL!Q:Q))/Q$3) | R20: =IF((R$3-SUMIF(NGL!$C:$C,'Availability Report - NGL'!$C20,NGL!R:R))/R$3<0%,0%,(R$3-SUMIF(NGL!$C:$C,'Availability Report - NGL'!$C20,NGL!R:R))/R$3) | S20: =IF((S$3-SUMIF(NGL!$C:$C,'Availability Report - NGL'!$C20,NGL!S:S))/S$3<0%,0%,(S$3-SUMIF(NGL!$C:$C,'Availability Report - NGL'!$C20,NGL!S:S))/S$3) | T20: =IF((T$3-SUMIF(NGL!$C:$C,'Availability Report - NGL'!$C20,NGL!T:T))/T$3<0%,0%,(T$3-SUMIF(NGL!$C:$C,'Availability Report - NGL'!$C20,NGL!T:T))/T$3) | AA20: =AVERAGE(I20:T20) | AB20: =AVERAGE(T20) | AD20: Fully Billed
B21: 17 | C21: Kira Begunova | D21: Left | E21: Growth | F21: Growth | G21: Growth | H21: Growth | I21: =IF((I$3-SUMIF(NGL!$C:$C,'Availability Report - NGL'!$C21,NGL!I:I))/I$3<0%,0%,(I$3-SUMIF(NGL!$C:$C,'Availability Report - NGL'!$C21,NGL!I:I))/I$3) | J21: =IF((J$3-SUMIF(NGL!$C:$C,'Availability Report - NGL'!$C21,NGL!J:J))/J$3<0%,0%,(J$3-SUMIF(NGL!$C:$C,'Availability Report - NGL'!$C21,NGL!J:J))/J$3) | K21: =IF((K$3-SUMIF(NGL!$C:$C,'Availability Report - NGL'!$C21,NGL!K:K))/K$3<0%,0%,(K$3-SUMIF(NGL!$C:$C,'Availability Report - NGL'!$C21,NGL!K:K))/K$3) | L21: =IF((L$3-SUMIF(NGL!$C:$C,'Availability Report - NGL'!$C21,NGL!L:L))/L$3<0%,0%,(L$3-SUMIF(NGL!$C:$C,'Availability Report - NGL'!$C21,NGL!L:L))/L$3) | M21: =IF((M$3-SUMIF(NGL!$C:$C,'Availability Report - NGL'!$C21,NGL!M:M))/M$3<0%,0%,(M$3-SUMIF(NGL!$C:$C,'Availability Report - NGL'!$C21,NGL!M:M))/M$3) | N21: =IF((N$3-SUMIF(NGL!$C:$C,'Availability Report - NGL'!$C21,NGL!N:N))/N$3<0%,0%,(N$3-SUMIF(NGL!$C:$C,'Availability Report - NGL'!$C21,NGL!N:N))/N$3) | O21: =IF((O$3-SUMIF(NGL!$C:$C,'Availability Report - NGL'!$C21,NGL!O:O))/O$3<0%,0%,(O$3-SUMIF(NGL!$C:$C,'Availability Report - NGL'!$C21,NGL!O:O))/O$3) | AA21: =AVERAGE(I21:T21) | AD21: Left
B22: 18 | C22: Kushi Celvan | D22: Active | E22: D&E | F22: Digital & Engineering Services | G22: OT | H22: OT | I22: =IF((I$3-SUMIF(NGL!$C:$C,'Availability Report - NGL'!$C22,NGL!I:I))/I$3<0%,0%,(I$3-SUMIF(NGL!$C:$C,'Availability Report - NGL'!$C22,NGL!I:I))/I$3) | J22: =IF((J$3-SUMIF(NGL!$C:$C,'Availability Report - NGL'!$C22,NGL!J:J))/J$3<0%,0%,(J$3-SUMIF(NGL!$C:$C,'Availability Report - NGL'!$C22,NGL!J:J))/J$3) | K22: =IF((K$3-SUMIF(NGL!$C:$C,'Availability Report - NGL'!$C22,NGL!K:K))/K$3<0%,0%,(K$3-SUMIF(NGL!$C:$C,'Availability Report - NGL'!$C22,NGL!K:K))/K$3) | L22: =IF((L$3-SUMIF(NGL!$C:$C,'Availability Report - NGL'!$C22,NGL!L:L))/L$3<0%,0%,(L$3-SUMIF(NGL!$C:$C,'Availability Report - NGL'!$C22,NGL!L:L))/L$3) | M22: =IF((M$3-SUMIF(NGL!$C:$C,'Availability Report - NGL'!$C22,NGL!M:M))/M$3<0%,0%,(M$3-SUMIF(NGL!$C:$C,'Availability Report - NGL'!$C22,NGL!M:M))/M$3) | N22: =IF((N$3-SUMIF(NGL!$C:$C,'Availability Report - NGL'!$C22,NGL!N:N))/N$3<0%,0%,(N$3-SUMIF(NGL!$C:$C,'Availability Report - NGL'!$C22,NGL!N:N))/N$3) | O22: =IF((O$3-SUMIF(NGL!$C:$C,'Availability Report - NGL'!$C22,NGL!O:O))/O$3<0%,0%,(O$3-SUMIF(NGL!$C:$C,'Availability Report - NGL'!$C22,NGL!O:O))/O$3) | P22: =IF((P$3-SUMIF(NGL!$C:$C,'Availability Report - NGL'!$C22,NGL!P:P))/P$3<0%,0%,(P$3-SUMIF(NGL!$C:$C,'Availability Report - NGL'!$C22,NGL!P:P))/P$3) | Q22: =IF((Q$3-SUMIF(NGL!$C:$C,'Availability Report - NGL'!$C22,NGL!Q:Q))/Q$3<0%,0%,(Q$3-SUMIF(NGL!$C:$C,'Availability Report - NGL'!$C22,NGL!Q:Q))/Q$3) | R22: =IF((R$3-SUMIF(NGL!$C:$C,'Availability Report - NGL'!$C22,NGL!R:R))/R$3<0%,0%,(R$3-SUMIF(NGL!$C:$C,'Availability Report - NGL'!$C22,NGL!R:R))/R$3) | S22: =IF((S$3-SUMIF(NGL!$C:$C,'Availability Report - NGL'!$C22,NGL!S:S))/S$3<0%,0%,(S$3-SUMIF(NGL!$C:$C,'Availability Report - NGL'!$C22,NGL!S:S))/S$3) | T22: =IF((T$3-SUMIF(NGL!$C:$C,'Availability Report - NGL'!$C22,NGL!T:T))/T$3<0%,0%,(T$3-SUMIF(NGL!$C:$C,'Availability Report - NGL'!$C22,NGL!T:T))/T$3) | AA22: =AVERAGE(I22:T22) | AB22: =AVERAGE(T22) | AD22: Fully Billed
B23: 19 | C23: Lakshmanan Kuppaswamy Chokkalingam | D23: Active | E23: D&E | F23: Digital & Engineering Services | G23: OT | H23: Asset & Intelligence | I23: =IF((I$3-SUMIF(NGL!$C:$C,'Availability Report - NGL'!$C23,NGL!I:I))/I$3<0%,0%,(I$3-SUMIF(NGL!$C:$C,'Availability Report - NGL'!$C23,NGL!I:I))/I$3) | J23: =IF((J$3-SUMIF(NGL!$C:$C,'Availability Report - NGL'!$C23,NGL!J:J))/J$3<0%,0%,(J$3-SUMIF(NGL!$C:$C,'Availability Report - NGL'!$C23,NGL!J:J))/J$3) | K23: =IF((K$3-SUMIF(NGL!$C:$C,'Availability Report - NGL'!$C23,NGL!K:K))/K$3<0%,0%,(K$3-SUMIF(NGL!$C:$C,'Availability Report - NGL'!$C23,NGL!K:K))/K$3) | L23: =IF((L$3-SUMIF(NGL!$C:$C,'Availability Report - NGL'!$C23,NGL!L:L))/L$3<0%,0%,(L$3-SUMIF(NGL!$C:$C,'Availability Report - NGL'!$C23,NGL!L:L))/L$3) | M23: =IF((M$3-SUMIF(NGL!$C:$C,'Availability Report - NGL'!$C23,NGL!M:M))/M$3<0%,0%,(M$3-SUMIF(NGL!$C:$C,'Availability Report - NGL'!$C23,NGL!M:M))/M$3) | N23: =IF((N$3-SUMIF(NGL!$C:$C,'Availability Report - NGL'!$C23,NGL!N:N))/N$3<0%,0%,(N$3-SUMIF(NGL!$C:$C,'Availability Report - NGL'!$C23,NGL!N:N))/N$3) | O23: =IF((O$3-SUMIF(NGL!$C:$C,'Availability Report - NGL'!$C23,NGL!O:O))/O$3<0%,0%,(O$3-SUMIF(NGL!$C:$C,'Availability Report - NGL'!$C23,NGL!O:O))/O$3) | P23: =IF((P$3-SUMIF(NGL!$C:$C,'Availability Report - NGL'!$C23,NGL!P:P))/P$3<0%,0%,(P$3-SUMIF(NGL!$C:$C,'Availability Report - NGL'!$C23,NGL!P:P))/P$3) | Q23: =IF((Q$3-SUMIF(NGL!$C:$C,'Availability Report - NGL'!$C23,NGL!Q:Q))/Q$3<0%,0%,(Q$3-SUMIF(NGL!$C:$C,'Availability Report - NGL'!$C23,NGL!Q:Q))/Q$3) | R23: =IF((R$3-SUMIF(NGL!$C:$C,'Availability Report - NGL'!$C23,NGL!R:R))/R$3<0%,0%,(R$3-SUMIF(NGL!$C:$C,'Availability Report - NGL'!$C23,NGL!R:R))/R$3) | S23: =IF((S$3-SUMIF(NGL!$C:$C,'Availability Report - NGL'!$C23,NGL!S:S))/S$3<0%,0%,(S$3-SUMIF(NGL!$C:$C,'Availability Report - NGL'!$C23,NGL!S:S))/S$3) | T23: =IF((T$3-SUMIF(NGL!$C:$C,'Availability Report - NGL'!$C23,NGL!T:T))/T$3<0%,0%,(T$3-SUMIF(NGL!$C:$C,'Availability Report - NGL'!$C23,NGL!T:T))/T$3) | U23: Business Development (GIS, Automation etc..) | V23: Capability Building (GIS, LowCode, SAP) | W23: Enterprise & Solution Architecture | X23: Delivery Management | Y23: H | Z23: Hisham to check | AA23: =AVERAGE(I23:T23) | AB23: =AVERAGE(T23) | AC23: 0.5 | AD23: 50% available for billing | AE23: UKPN CML, GIS Camapign, STW | AI23: ESRI, RMSI, 1Spatial | AJ23: Architecture | AK23: Available 50%
B24: 20 | C24: Mayura Parekh | D24: Active | E24: D&E | F24: Digital & Engineering Services | G24: Apps & Development | H24: Project & Buiness Analysis | I24: =IF((I$3-SUMIF(NGL!$C:$C,'Availability Report - NGL'!$C24,NGL!I:I))/I$3<0%,0%,(I$3-SUMIF(NGL!$C:$C,'Availability Report - NGL'!$C24,NGL!I:I))/I$3) | J24: =IF((J$3-SUMIF(NGL!$C:$C,'Availability Report - NGL'!$C24,NGL!J:J))/J$3<0%,0%,(J$3-SUMIF(NGL!$C:$C,'Availability Report - NGL'!$C24,NGL!J:J))/J$3) | K24: =IF((K$3-SUMIF(NGL!$C:$C,'Availability Report - NGL'!$C24,NGL!K:K))/K$3<0%,0%,(K$3-SUMIF(NGL!$C:$C,'Availability Report - NGL'!$C24,NGL!K:K))/K$3) | L24: =IF((L$3-SUMIF(NGL!$C:$C,'Availability Report - NGL'!$C24,NGL!L:L))/L$3<0%,0%,(L$3-SUMIF(NGL!$C:$C,'Availability Report - NGL'!$C24,NGL!L:L))/L$3) | M24: =IF((M$3-SUMIF(NGL!$C:$C,'Availability Report - NGL'!$C24,NGL!M:M))/M$3<0%,0%,(M$3-SUMIF(NGL!$C:$C,'Availability Report - NGL'!$C24,NGL!M:M))/M$3) | N24: =IF((N$3-SUMIF(NGL!$C:$C,'Availability Report - NGL'!$C24,NGL!N:N))/N$3<0%,0%,(N$3-SUMIF(NGL!$C:$C,'Availability Report - NGL'!$C24,NGL!N:N))/N$3) | O24: =IF((O$3-SUMIF(NGL!$C:$C,'Availability Report - NGL'!$C24,NGL!O:O))/O$3<0%,0%,(O$3-SUMIF(NGL!$C:$C,'Availability Report - NGL'!$C24,NGL!O:O))/O$3) | P24: =IF((P$3-SUMIF(NGL!$C:$C,'Availability Report - NGL'!$C24,NGL!P:P))/P$3<0%,0%,(P$3-SUMIF(NGL!$C:$C,'Availability Report - NGL'!$C24,NGL!P:P))/P$3) | Q24: =IF((Q$3-SUMIF(NGL!$C:$C,'Availability Report - NGL'!$C24,NGL!Q:Q))/Q$3<0%,0%,(Q$3-SUMIF(NGL!$C:$C,'Availability Report - NGL'!$C24,NGL!Q:Q))/Q$3) | R24: =IF((R$3-SUMIF(NGL!$C:$C,'Availability Report - NGL'!$C24,NGL!R:R))/R$3<0%,0%,(R$3-SUMIF(NGL!$C:$C,'Availability Report - NGL'!$C24,NGL!R:R))/R$3) | S24: =IF((S$3-SUMIF(NGL!$C:$C,'Availability Report - NGL'!$C24,NGL!S:S))/S$3<0%,0%,(S$3-SUMIF(NGL!$C:$C,'Availability Report - NGL'!$C24,NGL!S:S))/S$3) | T24: =IF((T$3-SUMIF(NGL!$C:$C,'Availability Report - NGL'!$C24,NGL!T:T))/T$3<0%,0%,(T$3-SUMIF(NGL!$C:$C,'Availability Report - NGL'!$C24,NGL!T:T))/T$3) | U24: Project Management | V24: Agile, SCRUM, Netcall | W24: Test Management, ADO | Y24: A | Z24: Explore ENWL with Sudhakar | AA24: =AVERAGE(I24:T24) | AB24: =AVERAGE(T24) | AC24: 1 | AD24: 100% available for billing | AJ24: Agile PM | AK24: Available
B25: 21 | C25: Mohamed Murshid | D25: Active | E25: D&E | F25: Digital & Engineering Services | G25: Apps & Development | H25: Testing & Assurance | I25: =IF((I$3-SUMIF(NGL!$C:$C,'Availability Report - NGL'!$C25,NGL!I:I))/I$3<0%,0%,(I$3-SUMIF(NGL!$C:$C,'Availability Report - NGL'!$C25,NGL!I:I))/I$3) | J25: =IF((J$3-SUMIF(NGL!$C:$C,'Availability Report - NGL'!$C25,NGL!J:J))/J$3<0%,0%,(J$3-SUMIF(NGL!$C:$C,'Availability Report - NGL'!$C25,NGL!J:J))/J$3) | K25: =IF((K$3-SUMIF(NGL!$C:$C,'Availability Report - NGL'!$C25,NGL!K:K))/K$3<0%,0%,(K$3-SUMIF(NGL!$C:$C,'Availability Report - NGL'!$C25,NGL!K:K))/K$3) | L25: =IF((L$3-SUMIF(NGL!$C:$C,'Availability Report - NGL'!$C25,NGL!L:L))/L$3<0%,0%,(L$3-SUMIF(NGL!$C:$C,'Availability Report - NGL'!$C25,NGL!L:L))/L$3) | M25: =IF((M$3-SUMIF(NGL!$C:$C,'Availability Report - NGL'!$C25,NGL!M:M))/M$3<0%,0%,(M$3-SUMIF(NGL!$C:$C,'Availability Report - NGL'!$C25,NGL!M:M))/M$3) | N25: =IF((N$3-SUMIF(NGL!$C:$C,'Availability Report - NGL'!$C25,NGL!N:N))/N$3<0%,0%,(N$3-SUMIF(NGL!$C:$C,'Availability Report - NGL'!$C25,NGL!N:N))/N$3) | O25: =IF((O$3-SUMIF(NGL!$C:$C,'Availability Report - NGL'!$C25,NGL!O:O))/O$3<0%,0%,(O$3-SUMIF(NGL!$C:$C,'Availability Report - NGL'!$C25,NGL!O:O))/O$3) | P25: =IF((P$3-SUMIF(NGL!$C:$C,'Availability Report - NGL'!$C25,NGL!P:P))/P$3<0%,0%,(P$3-SUMIF(NGL!$C:$C,'Availability Report - NGL'!$C25,NGL!P:P))/P$3) | Q25: =IF((Q$3-SUMIF(NGL!$C:$C,'Availability Report - NGL'!$C25,NGL!Q:Q))/Q$3<0%,0%,(Q$3-SUMIF(NGL!$C:$C,'Availability Report - NGL'!$C25,NGL!Q:Q))/Q$3) | R25: =IF((R$3-SUMIF(NGL!$C:$C,'Availability Report - NGL'!$C25,NGL!R:R))/R$3<0%,0%,(R$3-SUMIF(NGL!$C:$C,'Availability Report - NGL'!$C25,NGL!R:R))/R$3) | S25: =IF((S$3-SUMIF(NGL!$C:$C,'Availability Report - NGL'!$C25,NGL!S:S))/S$3<0%,0%,(S$3-SUMIF(NGL!$C:$C,'Availability Report - NGL'!$C25,NGL!S:S))/S$3) | T25: =IF((T$3-SUMIF(NGL!$C:$C,'Availability Report - NGL'!$C25,NGL!T:T))/T$3<0%,0%,(T$3-SUMIF(NGL!$C:$C,'Availability Report - NGL'!$C25,NGL!T:T))/T$3) | U25: Project Management | V25: Test Management | W25: Business Analysis, Project Management | X25: MPP, Test Management Tools | Y25: A | Z25: IMIB replacement - potentially | AA25: =AVERAGE(I25:T25) | AB25: =AVERAGE(T25) | AC25: 1 | AD25: Marked for potentail projects | AJ25: Testing | AK25: Available - marked for IMIB and ContrilM
B26: 22 | C26: Akeal Mohammed | D26: Active | E26: D&E | F26: Digital & Engineering Services | G26: Apps & Development | H26: Digital Solutions | I26: =IF((I$3-SUMIF(NGL!$C:$C,'Availability Report - NGL'!$C26,NGL!I:I))/I$3<0%,0%,(I$3-SUMIF(NGL!$C:$C,'Availability Report - NGL'!$C26,NGL!I:I))/I$3) | J26: =IF((J$3-SUMIF(NGL!$C:$C,'Availability Report - NGL'!$C26,NGL!J:J))/J$3<0%,0%,(J$3-SUMIF(NGL!$C:$C,'Availability Report - NGL'!$C26,NGL!J:J))/J$3) | K26: =IF((K$3-SUMIF(NGL!$C:$C,'Availability Report - NGL'!$C26,NGL!K:K))/K$3<0%,0%,(K$3-SUMIF(NGL!$C:$C,'Availability Report - NGL'!$C26,NGL!K:K))/K$3) | L26: =IF((L$3-SUMIF(NGL!$C:$C,'Availability Report - NGL'!$C26,NGL!L:L))/L$3<0%,0%,(L$3-SUMIF(NGL!$C:$C,'Availability Report - NGL'!$C26,NGL!L:L))/L$3) | M26: =IF((M$3-SUMIF(NGL!$C:$C,'Availability Report - NGL'!$C26,NGL!M:M))/M$3<0%,0%,(M$3-SUMIF(NGL!$C:$C,'Availability Report - NGL'!$C26,NGL!M:M))/M$3) | N26: =IF((N$3-SUMIF(NGL!$C:$C,'Availability Report - NGL'!$C26,NGL!N:N))/N$3<0%,0%,(N$3-SUMIF(NGL!$C:$C,'Availability Report - NGL'!$C26,NGL!N:N))/N$3) | O26: =IF((O$3-SUMIF(NGL!$C:$C,'Availability Report - NGL'!$C26,NGL!O:O))/O$3<0%,0%,(O$3-SUMIF(NGL!$C:$C,'Availability Report - NGL'!$C26,NGL!O:O))/O$3) | P26: =IF((P$3-SUMIF(NGL!$C:$C,'Availability Report - NGL'!$C26,NGL!P:P))/P$3<0%,0%,(P$3-SUMIF(NGL!$C:$C,'Availability Report - NGL'!$C26,NGL!P:P))/P$3) | Q26: =IF((Q$3-SUMIF(NGL!$C:$C,'Availability Report - NGL'!$C26,NGL!Q:Q))/Q$3<0%,0%,(Q$3-SUMIF(NGL!$C:$C,'Availability Report - NGL'!$C26,NGL!Q:Q))/Q$3) | R26: =IF((R$3-SUMIF(NGL!$C:$C,'Availability Report - NGL'!$C26,NGL!R:R))/R$3<0%,0%,(R$3-SUMIF(NGL!$C:$C,'Availability Report - NGL'!$C26,NGL!R:R))/R$3) | S26: =IF((S$3-SUMIF(NGL!$C:$C,'Availability Report - NGL'!$C26,NGL!S:S))/S$3<0%,0%,(S$3-SUMIF(NGL!$C:$C,'Availability Report - NGL'!$C26,NGL!S:S))/S$3) | T26: =IF((T$3-SUMIF(NGL!$C:$C,'Availability Report - NGL'!$C26,NGL!T:T))/T$3<0%,0%,(T$3-SUMIF(NGL!$C:$C,'Availability Report - NGL'!$C26,NGL!T:T))/T$3) | U26: Business Analyst | V26: Project Management | W26: Testing, Defect management, Presales | AA26: =AVERAGE(I26:T26) | AB26: =AVERAGE(T26) | AC26: 1 | AD26: 100% available for billing | AJ26: Business Analysis | AK26: Available
B27: 23 | C27: Moideen Veedu Hisham Ahammed | D27: Active | E27: D&E | F27: Digital & Engineering Services | G27: Apps & Development | H27: Apps & Development | I27: =IF((I$3-SUMIF(NGL!$C:$C,'Availability Report - NGL'!$C27,NGL!I:I))/I$3<0%,0%,(I$3-SUMIF(NGL!$C:$C,'Availability Report - NGL'!$C27,NGL!I:I))/I$3) | J27: =IF((J$3-SUMIF(NGL!$C:$C,'Availability Report - NGL'!$C27,NGL!J:J))/J$3<0%,0%,(J$3-SUMIF(NGL!$C:$C,'Availability Report - NGL'!$C27,NGL!J:J))/J$3) | K27: =IF((K$3-SUMIF(NGL!$C:$C,'Availability Report - NGL'!$C27,NGL!K:K))/K$3<0%,0%,(K$3-SUMIF(NGL!$C:$C,'Availability Report - NGL'!$C27,NGL!K:K))/K$3) | L27: =IF((L$3-SUMIF(NGL!$C:$C,'Availability Report - NGL'!$C27,NGL!L:L))/L$3<0%,0%,(L$3-SUMIF(NGL!$C:$C,'Availability Report - NGL'!$C27,NGL!L:L))/L$3) | M27: =IF((M$3-SUMIF(NGL!$C:$C,'Availability Report - NGL'!$C27,NGL!M:M))/M$3<0%,0%,(M$3-SUMIF(NGL!$C:$C,'Availability Report - NGL'!$C27,NGL!M:M))/M$3) | N27: =IF((N$3-SUMIF(NGL!$C:$C,'Availability Report - NGL'!$C27,NGL!N:N))/N$3<0%,0%,(N$3-SUMIF(NGL!$C:$C,'Availability Report - NGL'!$C27,NGL!N:N))/N$3) | O27: =IF((O$3-SUMIF(NGL!$C:$C,'Availability Report - NGL'!$C27,NGL!O:O))/O$3<0%,0%,(O$3-SUMIF(NGL!$C:$C,'Availability Report - NGL'!$C27,NGL!O:O))/O$3) | P27: =IF((P$3-SUMIF(NGL!$C:$C,'Availability Report - NGL'!$C27,NGL!P:P))/P$3<0%,0%,(P$3-SUMIF(NGL!$C:$C,'Availability Report - NGL'!$C27,NGL!P:P))/P$3) | Q27: =IF((Q$3-SUMIF(NGL!$C:$C,'Availability Report - NGL'!$C27,NGL!Q:Q))/Q$3<0%,0%,(Q$3-SUMIF(NGL!$C:$C,'Availability Report - NGL'!$C27,NGL!Q:Q))/Q$3) | R27: =IF((R$3-SUMIF(NGL!$C:$C,'Availability Report - NGL'!$C27,NGL!R:R))/R$3<0%,0%,(R$3-SUMIF(NGL!$C:$C,'Availability Report - NGL'!$C27,NGL!R:R))/R$3) | S27: =IF((S$3-SUMIF(NGL!$C:$C,'Availability Report - NGL'!$C27,NGL!S:S))/S$3<0%,0%,(S$3-SUMIF(NGL!$C:$C,'Availability Report - NGL'!$C27,NGL!S:S))/S$3) | T27: =IF((T$3-SUMIF(NGL!$C:$C,'Availability Report - NGL'!$C27,NGL!T:T))/T$3<0%,0%,(T$3-SUMIF(NGL!$C:$C,'Availability Report - NGL'!$C27,NGL!T:T))/T$3) | U27: Architecture | V27: Enterprise Architecture | W27: AWS, Azure,Cloud, Infrastrcuture, Enterprise Apps | X27: Technical Delivery, Stakeholder Management | Y27: A | Z27: Hisham to update | AA27: =AVERAGE(I27:T27) | AB27: =AVERAGE(T27) | AC27: 0 | AD27: Awaiting paperwork | AK27: Awaiting paperwork
B28: 24 | C28: Mubarik Ali | D28: Active | E28: D&E | F28: Digital & Engineering Services | G28: Apps & Development | H28: Digital Solutions | I28: =IF((I$3-SUMIF(NGL!$C:$C,'Availability Report - NGL'!$C28,NGL!I:I))/I$3<0%,0%,(I$3-SUMIF(NGL!$C:$C,'Availability Report - NGL'!$C28,NGL!I:I))/I$3) | J28: =IF((J$3-SUMIF(NGL!$C:$C,'Availability Report - NGL'!$C28,NGL!J:J))/J$3<0%,0%,(J$3-SUMIF(NGL!$C:$C,'Availability Report - NGL'!$C28,NGL!J:J))/J$3) | K28: =IF((K$3-SUMIF(NGL!$C:$C,'Availability Report - NGL'!$C28,NGL!K:K))/K$3<0%,0%,(K$3-SUMIF(NGL!$C:$C,'Availability Report - NGL'!$C28,NGL!K:K))/K$3) | L28: =IF((L$3-SUMIF(NGL!$C:$C,'Availability Report - NGL'!$C28,NGL!L:L))/L$3<0%,0%,(L$3-SUMIF(NGL!$C:$C,'Availability Report - NGL'!$C28,NGL!L:L))/L$3) | M28: =IF((M$3-SUMIF(NGL!$C:$C,'Availability Report - NGL'!$C28,NGL!M:M))/M$3<0%,0%,(M$3-SUMIF(NGL!$C:$C,'Availability Report - NGL'!$C28,NGL!M:M))/M$3) | N28: =IF((N$3-SUMIF(NGL!$C:$C,'Availability Report - NGL'!$C28,NGL!N:N))/N$3<0%,0%,(N$3-SUMIF(NGL!$C:$C,'Availability Report - NGL'!$C28,NGL!N:N))/N$3) | O28: =IF((O$3-SUMIF(NGL!$C:$C,'Availability Report - NGL'!$C28,NGL!O:O))/O$3<0%,0%,(O$3-SUMIF(NGL!$C:$C,'Availability Report - NGL'!$C28,NGL!O:O))/O$3) | P28: =IF((P$3-SUMIF(NGL!$C:$C,'Availability Report - NGL'!$C28,NGL!P:P))/P$3<0%,0%,(P$3-SUMIF(NGL!$C:$C,'Availability Report - NGL'!$C28,NGL!P:P))/P$3) | Q28: =IF((Q$3-SUMIF(NGL!$C:$C,'Availability Report - NGL'!$C28,NGL!Q:Q))/Q$3<0%,0%,(Q$3-SUMIF(NGL!$C:$C,'Availability Report - NGL'!$C28,NGL!Q:Q))/Q$3) | R28: =IF((R$3-SUMIF(NGL!$C:$C,'Availability Report - NGL'!$C28,NGL!R:R))/R$3<0%,0%,(R$3-SUMIF(NGL!$C:$C,'Availability Report - NGL'!$C28,NGL!R:R))/R$3) | S28: =IF((S$3-SUMIF(NGL!$C:$C,'Availability Report - NGL'!$C28,NGL!S:S))/S$3<0%,0%,(S$3-SUMIF(NGL!$C:$C,'Availability Report - NGL'!$C28,NGL!S:S))/S$3) | T28: =IF((T$3-SUMIF(NGL!$C:$C,'Availability Report - NGL'!$C28,NGL!T:T))/T$3<0%,0%,(T$3-SUMIF(NGL!$C:$C,'Availability Report - NGL'!$C28,NGL!T:T))/T$3) | U28: Apprentice | V28: DevOps | W28: Data/AI | X28: C#, Javascript | Y28: R | Z28: No allocation currently | AA28: =AVERAGE(I28:T28) | AB28: =AVERAGE(T28) | AC28: 1 | AD28: 100% available for billing (Graduate) | AJ28: DevOPS, .Net | AK28: Graduate
B29: 25 | C29: Najva Alavi Tabatabaei | D29: Active | E29: D&E | F29: Digital & Engineering Services | G29: Apps & Development | H29: Testing & Assurance | I29: =IF((I$3-SUMIF(NGL!$C:$C,'Availability Report - NGL'!$C29,NGL!I:I))/I$3<0%,0%,(I$3-SUMIF(NGL!$C:$C,'Availability Report - NGL'!$C29,NGL!I:I))/I$3) | J29: =IF((J$3-SUMIF(NGL!$C:$C,'Availability Report - NGL'!$C29,NGL!J:J))/J$3<0%,0%,(J$3-SUMIF(NGL!$C:$C,'Availability Report - NGL'!$C29,NGL!J:J))/J$3) | K29: =IF((K$3-SUMIF(NGL!$C:$C,'Availability Report - NGL'!$C29,NGL!K:K))/K$3<0%,0%,(K$3-SUMIF(NGL!$C:$C,'Availability Report - NGL'!$C29,NGL!K:K))/K$3) | L29: =IF((L$3-SUMIF(NGL!$C:$C,'Availability Report - NGL'!$C29,NGL!L:L))/L$3<0%,0%,(L$3-SUMIF(NGL!$C:$C,'Availability Report - NGL'!$C29,NGL!L:L))/L$3) | M29: =IF((M$3-SUMIF(NGL!$C:$C,'Availability Report - NGL'!$C29,NGL!M:M))/M$3<0%,0%,(M$3-SUMIF(NGL!$C:$C,'Availability Report - NGL'!$C29,NGL!M:M))/M$3) | N29: =IF((N$3-SUMIF(NGL!$C:$C,'Availability Report - NGL'!$C29,NGL!N:N))/N$3<0%,0%,(N$3-SUMIF(NGL!$C:$C,'Availability Report - NGL'!$C29,NGL!N:N))/N$3) | O29: =IF((O$3-SUMIF(NGL!$C:$C,'Availability Report - NGL'!$C29,NGL!O:O))/O$3<0%,0%,(O$3-SUMIF(NGL!$C:$C,'Availability Report - NGL'!$C29,NGL!O:O))/O$3) | P29: =IF((P$3-SUMIF(NGL!$C:$C,'Availability Report - NGL'!$C29,NGL!P:P))/P$3<0%,0%,(P$3-SUMIF(NGL!$C:$C,'Availability Report - NGL'!$C29,NGL!P:P))/P$3) | Q29: =IF((Q$3-SUMIF(NGL!$C:$C,'Availability Report - NGL'!$C29,NGL!Q:Q))/Q$3<0%,0%,(Q$3-SUMIF(NGL!$C:$C,'Availability Report - NGL'!$C29,NGL!Q:Q))/Q$3) | R29: =IF((R$3-SUMIF(NGL!$C:$C,'Availability Report - NGL'!$C29,NGL!R:R))/R$3<0%,0%,(R$3-SUMIF(NGL!$C:$C,'Availability Report - NGL'!$C29,NGL!R:R))/R$3) | S29: =IF((S$3-SUMIF(NGL!$C:$C,'Availability Report - NGL'!$C29,NGL!S:S))/S$3<0%,0%,(S$3-SUMIF(NGL!$C:$C,'Availability Report - NGL'!$C29,NGL!S:S))/S$3) | T29: =IF((T$3-SUMIF(NGL!$C:$C,'Availability Report - NGL'!$C29,NGL!T:T))/T$3<0%,0%,(T$3-SUMIF(NGL!$C:$C,'Availability Report - NGL'!$C29,NGL!T:T))/T$3) | U29: Test Engineer | V29: Manual Testing | W29: AI Basics, Business Analysis? | Y29: R | Z29: Explore UKPN Evolve | AA29: =AVERAGE(I29:T29) | AB29: =AVERAGE(T29) | AC29: 1 | AD29: 100% available for billing | AJ29: testing | AK29: Available
B30: 26 | C30: NANDHITHA Palanisamy | D30: Active | E30: D&E | F30: Digital & Engineering Services | G30: Apps & Development | H30: Testing & Assurance | I30: =IF((I$3-SUMIF(NGL!$C:$C,'Availability Report - NGL'!$C30,NGL!I:I))/I$3<0%,0%,(I$3-SUMIF(NGL!$C:$C,'Availability Report - NGL'!$C30,NGL!I:I))/I$3) | J30: =IF((J$3-SUMIF(NGL!$C:$C,'Availability Report - NGL'!$C30,NGL!J:J))/J$3<0%,0%,(J$3-SUMIF(NGL!$C:$C,'Availability Report - NGL'!$C30,NGL!J:J))/J$3) | K30: =IF((K$3-SUMIF(NGL!$C:$C,'Availability Report - NGL'!$C30,NGL!K:K))/K$3<0%,0%,(K$3-SUMIF(NGL!$C:$C,'Availability Report - NGL'!$C30,NGL!K:K))/K$3) | L30: =IF((L$3-SUMIF(NGL!$C:$C,'Availability Report - NGL'!$C30,NGL!L:L))/L$3<0%,0%,(L$3-SUMIF(NGL!$C:$C,'Availability Report - NGL'!$C30,NGL!L:L))/L$3) | M30: =IF((M$3-SUMIF(NGL!$C:$C,'Availability Report - NGL'!$C30,NGL!M:M))/M$3<0%,0%,(M$3-SUMIF(NGL!$C:$C,'Availability Report - NGL'!$C30,NGL!M:M))/M$3) | N30: =IF((N$3-SUMIF(NGL!$C:$C,'Availability Report - NGL'!$C30,NGL!N:N))/N$3<0%,0%,(N$3-SUMIF(NGL!$C:$C,'Availability Report - NGL'!$C30,NGL!N:N))/N$3) | O30: =IF((O$3-SUMIF(NGL!$C:$C,'Availability Report - NGL'!$C30,NGL!O:O))/O$3<0%,0%,(O$3-SUMIF(NGL!$C:$C,'Availability Report - NGL'!$C30,NGL!O:O))/O$3) | P30: =IF((P$3-SUMIF(NGL!$C:$C,'Availability Report - NGL'!$C30,NGL!P:P))/P$3<0%,0%,(P$3-SUMIF(NGL!$C:$C,'Availability Report - NGL'!$C30,NGL!P:P))/P$3) | Q30: =IF((Q$3-SUMIF(NGL!$C:$C,'Availability Report - NGL'!$C30,NGL!Q:Q))/Q$3<0%,0%,(Q$3-SUMIF(NGL!$C:$C,'Availability Report - NGL'!$C30,NGL!Q:Q))/Q$3) | R30: =IF((R$3-SUMIF(NGL!$C:$C,'Availability Report - NGL'!$C30,NGL!R:R))/R$3<0%,0%,(R$3-SUMIF(NGL!$C:$C,'Availability Report - NGL'!$C30,NGL!R:R))/R$3) | S30: =IF((S$3-SUMIF(NGL!$C:$C,'Availability Report - NGL'!$C30,NGL!S:S))/S$3<0%,0%,(S$3-SUMIF(NGL!$C:$C,'Availability Report - NGL'!$C30,NGL!S:S))/S$3) | T30: =IF((T$3-SUMIF(NGL!$C:$C,'Availability Report - NGL'!$C30,NGL!T:T))/T$3<0%,0%,(T$3-SUMIF(NGL!$C:$C,'Availability Report - NGL'!$C30,NGL!T:T))/T$3) | U30: Test Lead | V30: Testing, Automation Testing, Scripting (Selenium) | W30: Power Automate, Busines Analysis, SQL Basics | Y30: R | Z30: Explore UKPN Evolve | AA30: =AVERAGE(I30:T30) | AB30: =AVERAGE(T30) | AC30: 0.5 | AD30: 50% available for billing | AJ30: Testing | AK30: Tamo to update commercials
B31: 27 | C31: Okan Benli | D31: Active | E31: D&E | F31: Digital & Engineering Services | G31: Renewable and Engineering | H31: Design Engineering | I31: =IF((I$3-SUMIF(NGL!$C:$C,'Availability Report - NGL'!$C31,NGL!I:I))/I$3<0%,0%,(I$3-SUMIF(NGL!$C:$C,'Availability Report - NGL'!$C31,NGL!I:I))/I$3) | J31: =IF((J$3-SUMIF(NGL!$C:$C,'Availability Report - NGL'!$C31,NGL!J:J))/J$3<0%,0%,(J$3-SUMIF(NGL!$C:$C,'Availability Report - NGL'!$C31,NGL!J:J))/J$3) | K31: =IF((K$3-SUMIF(NGL!$C:$C,'Availability Report - NGL'!$C31,NGL!K:K))/K$3<0%,0%,(K$3-SUMIF(NGL!$C:$C,'Availability Report - NGL'!$C31,NGL!K:K))/K$3) | L31: =IF((L$3-SUMIF(NGL!$C:$C,'Availability Report - NGL'!$C31,NGL!L:L))/L$3<0%,0%,(L$3-SUMIF(NGL!$C:$C,'Availability Report - NGL'!$C31,NGL!L:L))/L$3) | M31: =IF((M$3-SUMIF(NGL!$C:$C,'Availability Report - NGL'!$C31,NGL!M:M))/M$3<0%,0%,(M$3-SUMIF(NGL!$C:$C,'Availability Report - NGL'!$C31,NGL!M:M))/M$3) | N31: =IF((N$3-SUMIF(NGL!$C:$C,'Availability Report - NGL'!$C31,NGL!N:N))/N$3<0%,0%,(N$3-SUMIF(NGL!$C:$C,'Availability Report - NGL'!$C31,NGL!N:N))/N$3) | O31: =IF((O$3-SUMIF(NGL!$C:$C,'Availability Report - NGL'!$C31,NGL!O:O))/O$3<0%,0%,(O$3-SUMIF(NGL!$C:$C,'Availability Report - NGL'!$C31,NGL!O:O))/O$3) | P31: =IF((P$3-SUMIF(NGL!$C:$C,'Availability Report - NGL'!$C31,NGL!P:P))/P$3<0%,0%,(P$3-SUMIF(NGL!$C:$C,'Availability Report - NGL'!$C31,NGL!P:P))/P$3) | Q31: =IF((Q$3-SUMIF(NGL!$C:$C,'Availability Report - NGL'!$C31,NGL!Q:Q))/Q$3<0%,0%,(Q$3-SUMIF(NGL!$C:$C,'Availability Report - NGL'!$C31,NGL!Q:Q))/Q$3) | R31: =IF((R$3-SUMIF(NGL!$C:$C,'Availability Report - NGL'!$C31,NGL!R:R))/R$3<0%,0%,(R$3-SUMIF(NGL!$C:$C,'Availability Report - NGL'!$C31,NGL!R:R))/R$3) | S31: =IF((S$3-SUMIF(NGL!$C:$C,'Availability Report - NGL'!$C31,NGL!S:S))/S$3<0%,0%,(S$3-SUMIF(NGL!$C:$C,'Availability Report - NGL'!$C31,NGL!S:S))/S$3) | T31: =IF((T$3-SUMIF(NGL!$C:$C,'Availability Report - NGL'!$C31,NGL!T:T))/T$3<0%,0%,(T$3-SUMIF(NGL!$C:$C,'Availability Report - NGL'!$C31,NGL!T:T))/T$3) | AA31: =AVERAGE(I31:T31) | AB31: =AVERAGE(T31) | AC31: 0 | AD31: Awaiting paperwork | AK31: Awaiting paperwork
B32: 28 | C32: Önder Yelmenoğlu | D32: Left | E32: D&E | F32: Digital & Engineering Services | G32: Renewable and Engineering | H32: Design Engineering | I32: =IF((I$3-SUMIF(NGL!$C:$C,'Availability Report - NGL'!$C32,NGL!I:I))/I$3<0%,0%,(I$3-SUMIF(NGL!$C:$C,'Availability Report - NGL'!$C32,NGL!I:I))/I$3) | J32: =IF((J$3-SUMIF(NGL!$C:$C,'Availability Report - NGL'!$C32,NGL!J:J))/J$3<0%,0%,(J$3-SUMIF(NGL!$C:$C,'Availability Report - NGL'!$C32,NGL!J:J))/J$3) | K32: =IF((K$3-SUMIF(NGL!$C:$C,'Availability Report - NGL'!$C32,NGL!K:K))/K$3<0%,0%,(K$3-SUMIF(NGL!$C:$C,'Availability Report - NGL'!$C32,NGL!K:K))/K$3) | L32: =IF((L$3-SUMIF(NGL!$C:$C,'Availability Report - NGL'!$C32,NGL!L:L))/L$3<0%,0%,(L$3-SUMIF(NGL!$C:$C,'Availability Report - NGL'!$C32,NGL!L:L))/L$3) | M32: =IF((M$3-SUMIF(NGL!$C:$C,'Availability Report - NGL'!$C32,NGL!M:M))/M$3<0%,0%,(M$3-SUMIF(NGL!$C:$C,'Availability Report - NGL'!$C32,NGL!M:M))/M$3) | N32: =IF((N$3-SUMIF(NGL!$C:$C,'Availability Report - NGL'!$C32,NGL!N:N))/N$3<0%,0%,(N$3-SUMIF(NGL!$C:$C,'Availability Report - NGL'!$C32,NGL!N:N))/N$3) | O32: =IF((O$3-SUMIF(NGL!$C:$C,'Availability Report - NGL'!$C32,NGL!O:O))/O$3<0%,0%,(O$3-SUMIF(NGL!$C:$C,'Availability Report - NGL'!$C32,NGL!O:O))/O$3) | P32: =IF((P$3-SUMIF(NGL!$C:$C,'Availability Report - NGL'!$C32,NGL!P:P))/P$3<0%,0%,(P$3-SUMIF(NGL!$C:$C,'Availability Report - NGL'!$C32,NGL!P:P))/P$3) | Q32: =IF((Q$3-SUMIF(NGL!$C:$C,'Availability Report - NGL'!$C32,NGL!Q:Q))/Q$3<0%,0%,(Q$3-SUMIF(NGL!$C:$C,'Availability Report - NGL'!$C32,NGL!Q:Q))/Q$3) | R32: =IF((R$3-SUMIF(NGL!$C:$C,'Availability Report - NGL'!$C32,NGL!R:R))/R$3<0%,0%,(R$3-SUMIF(NGL!$C:$C,'Availability Report - NGL'!$C32,NGL!R:R))/R$3) | S32: =IF((S$3-SUMIF(NGL!$C:$C,'Availability Report - NGL'!$C32,NGL!S:S))/S$3<0%,0%,(S$3-SUMIF(NGL!$C:$C,'Availability Report - NGL'!$C32,NGL!S:S))/S$3) | AA32: =AVERAGE(I32:T32) | AB32: =AVERAGE(T32) | AC32: 0 | AD32: Resigned | AK32: Resigned
